Workbook

Sheet 00 — Painel Inicial
B2: KIT DE 6 CALCULADORAS AUTOMÁTICAS DE ENGENHARIA AMBIENTAL
B3: Resolva, confira e entenda cálculos de hidráulica, carga poluidora, eficiência, balanço de massa, diluição e dosagem química. Tudo automático, com a fórmula explicada passo a passo.
B6: 📘 COMECE AQUI (GUIA) | D6: 📚 BIBLIOTECA DE EXEMPLOS | F6: ▶ COMO USAR EM 5 PASSOS
B8: ESCOLHA SUA CALCULADORA
B9: 💧 CALCULADORA 01 | D9: 🏭 CALCULADORA 02 | F9: 📉 CALCULADORA 03
B10: Vazão e Hidráulica | D10: Carga Poluidora | F10: Eficiência de Tratamento
B11: Calcule vazão por volume e tempo, vazão em tubulações, velocidade do escoamento e tempo de detenção hidráulica, com conversão automática de unidades. | D11: Descubra quantos kg por dia de DBO, DQO, SST, nitrogênio ou fósforo uma corrente transporta. Também calcula a concentração ou a vazão a partir da carga. | F11: Avalie quanto um sistema de tratamento removeu, por concentração ou por carga, com gráfico de antes e depois e interpretação automática.
B12: 4 ferramentas · m³/s, L/s, m³/h, m³/dia · aba 02 | D12: 3 ferramentas · kg/dia, mg/L, m³/dia · aba 03 | F12: 2 ferramentas · % de remoção e gráficos · aba 04
B13: Abrir calculadora ▶ | D13: Abrir calculadora ▶ | F13: Abrir calculadora ▶
B16: ⚖️ CALCULADORA 04 | D16: 🧪 CALCULADORA 05 | F16: ⚗️ CALCULADORA 06
B17: Balanço de Massa | D17: Diluição de Soluções | F17: Dosagem de Produtos Químicos
B18: Misture duas correntes, feche o balanço de um decantador e calcule o acúmulo de massa em um sistema, com cada etapa explicada. | D18: Prepare soluções no laboratório com C₁V₁ = C₂V₂. Escolha o que quer descobrir e receba a instrução de preparo pronta. | F18: Calcule a massa de componente ativo, a massa de produto comercial e o volume diário de produto líquido para uma dosagem definida.
B19: 3 ferramentas · mistura, decantador, acúmulo · aba 05 | D19: 1 fórmula · 4 incógnitas possíveis · aba 06 | F19: 3 etapas · kg/dia e L/dia · aba 07
B20: Abrir calculadora ▶ | D20: Abrir calculadora ▶ | F20: Abrir calculadora ▶
B23: COMO COMEÇAR | F23: LEGENDA DAS CORES
B24: 1. Escolha uma calculadora e clique em Abrir calculadora. | F24: Amarelo-claro: campo para você digitar ou escolher
B25: 2. Na lista Cenário, escolha Exemplo 01, Exemplo 02 ou Meu cálculo. | F25: Verde: resultado automático e indicadores positivos
B26: 3. Em Meu cálculo, preencha os campos amarelos da coluna MEU CÁLCULO. | F26: Azul-claro: valor em uso, que entrou na conta
B27: 4. Confira o resultado automático destacado em verde. | F27: Azul: botão de navegação (clique)
B28: 5. Leia a explicação em Entenda o cálculo e verifique as unidades. | F28: Cinza-claro: explicações e exemplos cadastrados
B29: Dúvidas? Abra o guia completo na aba 01: Comece Aqui. | F29: Vermelho suave: avisos e dados inválidos
B31: Importante: os resultados são cálculos teóricos de apoio ao estudo. Projetos, laudos e decisões operacionais exigem normas técnicas, legislação aplicável e responsável técnico. Guarde uma cópia original deste arquivo e salve cada trabalho com outro nome.
B32: Sem macros · Sem internet · Excel e Google Planilhas · Abas protegidas sem senha contra alterações acidentais

Sheet 01 — Comece Aqui
B1: 📘 COMECE AQUI: GUIA COMPLETO
B2: Leia esta página uma vez e você saberá usar todo o kit.
B3: 🏠 Painel Inicial | C3: 📚 Exemplos Resolvidos | D3: Primeira calculadora ▶
B6: 1 O QUE É O KIT
B7: Este kit reúne 6 calculadoras automáticas para os cálculos mais comuns da Engenharia Ambiental: vazão e hidráulica, carga poluidora, eficiência de tratamento, balanço de massa, diluição de soluções e dosagem de produtos químicos. Você informa os dados, a planilha calcula na hora e mostra a fórmula usada, a substituição dos valores e uma explicação do resultado. Funciona como um pequeno aplicativo dentro da planilha, sem macros e sem internet.
B9: 2 PARA QUEM FOI DESENVOLVIDO
B10: Para estudantes de Engenharia Ambiental e de cursos próximos (Sanitária, Civil, Química, Gestão Ambiental) que precisam resolver listas de exercícios, conferir contas de provas e trabalhos, preparar relatórios de laboratório ou apoiar atividades de estágio. Você não precisa saber Excel: basta escolher opções nas listas e digitar números nos campos amarelos.
B12: 3 COMO USAR EM 5 PASSOS
B13: PASSO 1 | C13: Escolha uma calculadora. No Painel Inicial, clique no card da calculadora que resolve o seu problema. Na dúvida, use a tabela Qual calculadora usar, logo abaixo.
B14: PASSO 2 | C14: Selecione um exemplo ou a opção "Meu cálculo". Cada ferramenta tem a lista Cenário. Exemplo 01 e Exemplo 02 carregam dados prontos. Meu cálculo usa os valores que você digitar.
B15: PASSO 3 | C15: Preencha os campos amarelos. Digite seus valores na coluna MEU CÁLCULO e escolha as unidades nas listas. A coluna Valor em uso mostra exatamente o que está entrando na conta.
B16: PASSO 4 | C16: Confira o resultado automático destacado em verde. O card verde mostra o resultado principal, outras unidades, uma interpretação e o status dos dados. Se faltar algo, aparece uma mensagem em vermelho dizendo o que corrigir.
B17: PASSO 5 | C17: Leia a explicação e verifique as unidades utilizadas. Em Entenda o cálculo você vê a fórmula, os valores usados e a conta montada. Confira se as unidades fazem sentido para o seu exercício.
B19: 4 QUAIS CÁLCULOS ESTÃO DISPONÍVEIS
B20: Calculadora (clique para abrir) | C20: Onde fica | D20: O que ela resolve
B21: 💧 01 · Vazão e Hidráulica | C21: Aba 02 — Vazão e Hidráulica | D21: Vazão a partir de volume e tempo; Vazão em tubulações; Velocidade do escoamento; Tempo de detenção hidráulica (TDH)
B22: 🏭 02 · Carga Poluidora | C22: Aba 03 — Carga Poluidora | D22: Calcular carga poluidora; Descobrir a concentração; Descobrir a vazão
B23: 📉 03 · Eficiência | C23: Aba 04 — Eficiência de Tratamento | D23: Eficiência por concentração; Eficiência por carga
B24: ⚖️ 04 · Balanço de Massa | C24: Aba 05 — Balanço de Massa | D24: Mistura de duas correntes; Balanço de massa em decantadores; Acúmulo de massa
B25: 🧪 05 · Diluição | C25: Aba 06 — Diluição de Soluções | D25: Volume de estoque, concentração final, volume final ou concentração do estoque
B26: ⚗️ 06 · Dosagem Química | C26: Aba 07 — Dosagem Química | D26: Massa de ativo; massa de produto comercial; volume de produto líquido
B28: 5 COMO ESCOLHER A CALCULADORA CERTA
B29: Preciso calcular | C29: Qual calculadora utilizar | D29: Exemplo de aplicação
B30: Descobrir a vazão de uma tubulação | C30: 02 · Vazão e Hidráulica (Ferramenta 2) | D30: Tubo de 0,30 m com água a 1,5 m/s.
B31: Descobrir a vazão a partir de volume e tempo | C31: 02 · Vazão e Hidráulica (Ferramenta 1) | D31: Tanque de 360 m³ que enche em 2 horas.
B32: Verificar a velocidade da água em um tubo | C32: 02 · Vazão e Hidráulica (Ferramenta 3) | D32: 0,05 m³/s passando em tubo de 0,20 m.
B33: Calcular o tempo de detenção de um tanque | C33: 02 · Vazão e Hidráulica (Ferramenta 4) | D33: Tanque de 500 m³ recebendo 50 m³/h.
B34: Calcular a carga de DBO de um efluente | C34: 03 · Carga Poluidora (Ferramenta 1) | D34: 400 m³/dia com 180 mg/L de DBO.
B35: Descobrir a concentração a partir da carga | C35: 03 · Carga Poluidora (Ferramenta 2) | D35: 24 kg/dia de DBO em 400 m³/dia.
B36: Avaliar a eficiência de uma ETE | C36: 04 · Eficiência de Tratamento | D36: DBO de 250 mg/L na entrada e 50 mg/L na saída.
B37: Calcular a concentração após misturar dois efluentes | C37: 05 · Balanço de Massa (Ferramenta 1) | D37: 120 m³/dia a 200 mg/L + 80 m³/dia a 50 mg/L.
B38: Calcular a concentração do lodo de um decantador | C38: 05 · Balanço de Massa (Ferramenta 2) | D38: Entrada, clarificado e lodo de um decantador primário.
B39: Saber se a massa está acumulando em um sistema | C39: 05 · Balanço de Massa (Ferramenta 3) | D39: Tanque que recebe mais sólidos do que descarta.
B40: Preparar uma solução diluída | C40: 06 · Diluição de Soluções | D40: 500 mL a 200 mg/L a partir de um padrão de 1.000 mg/L.
B41: Calcular a quantidade diária de um produto químico | C41: 07 · Dosagem Química | D41: 4 mg/L de ativo em 500 m³/dia com produto a 50%.
B43: 6 COMO INFORMAR OS DADOS
B44: • Digite somente nos campos amarelos da coluna MEU CÁLCULO. As outras células estão protegidas para evitar que uma fórmula seja apagada sem querer.
B45: • Use vírgula para decimais (0,5), como no padrão brasileiro. Não digite a unidade junto do número: escreva 500, e não 500 m³.
B46: • Ao clicar em um campo amarelo aparece uma dica com o que deve ser digitado.
B47: • Se você digitar algo inválido (texto ou número negativo), a planilha avisa e não aceita.
B48: • Seus dados ficam guardados quando você troca para um exemplo. Ao voltar para Meu cálculo, eles continuam lá.
B50: 7 COMO ESCOLHER AS UNIDADES
B51: Algumas ferramentas têm uma linha Unidade de ... com lista. Escolha a unidade em que o seu dado está e a calculadora converte tudo sozinha. Nas linhas sem lista, use exatamente a unidade indicada na coluna Unidade (por exemplo, m³/dia e mg/L). A tabela abaixo ajuda nas conversões feitas à mão.
B52: Grandeza | C52: Relação | D52: Observação
B53: Vazão | C53: 1 L/s = 3,6 m³/h = 86,4 m³/dia | D53: 1 m³/s = 1.000 L/s
B54: Volume | C54: 1 m³ = 1.000 L | D54: 1 L = 1.000 mL
B55: Tempo | C55: 1 h = 60 min = 3.600 s | D55: 1 dia = 24 h = 86.400 s
B56: Comprimento | C56: 1 m = 100 cm = 1.000 mm | D56: 1 polegada = 2,54 cm
B57: Concentração | C57: 1 mg/L = 1 g/m³ | D57: Em água diluída, 1 mg/L é aproximadamente 1 ppm
B58: Carga | C58: kg/dia = m³/dia × mg/L × 0,001 | D58: 1 kg = 1.000 g
B59: Porcentagem | C59: 50% = 0,50 | D59: Divida por 100 antes de usar na fórmula
B60: Densidade | C60: kg/L | D60: Água ≈ 1 kg/L. Produtos químicos variam: consulte a ficha técnica
B62: 8 COMO UTILIZAR OS EXEMPLOS PRONTOS
B63: Cada ferramenta tem dois exemplos cadastrados (colunas Exemplo 01 e Exemplo 02). Ao escolher um deles na lista Cenário, a calculadora usa esses dados nas mesmas fórmulas do Meu cálculo. Use os exemplos para aprender o caminho da conta e depois troque para Meu cálculo para testar seus valores. A aba 08: Exemplos Resolvidos mostra todos os exemplos explicados passo a passo, com um botão que leva para a calculadora.
B65: 9 COMO INTERPRETAR OS RESULTADOS
B66: O card verde traz o nome do resultado, o valor em destaque e a unidade; outros resultados e unidades; uma interpretação em linguagem simples; e o status dos dados. Com ✔ o cálculo está completo. Com ⚠, leia a mensagem: ela diz qual campo falta ou está incorreto. Nesse caso o resultado fica com um traço (—), porque a calculadora não inventa valores.
B67: Resultados negativos aparecem quando fazem sentido. Uma eficiência negativa indica que o parâmetro aumentou; um acúmulo negativo indica que a massa no sistema está diminuindo. A interpretação explica cada caso.
B69: 10 COMO CONFERIR AS FÓRMULAS
B70: • A área E · Entenda o cálculo mostra a fórmula, cada variável, os valores usados e a substituição numérica. Tudo se atualiza quando você muda um dado.
B71: • Clique em qualquer resultado e veja a fórmula na barra de fórmulas.
B72: • As conversões de unidade e as validações ficam na ÁREA TÉCNICA, à direita de cada calculadora (colunas K e L). Basta rolar a tela para a direita.
B73: • Os exemplos resolvidos podem ser refeitos à mão ou na calculadora do celular para conferir.
B75: 11 O SIGNIFICADO DAS CORES
B76: Cor | C76: Significado | D76: Onde aparece
B77: Amarelo-claro | C77: Campo editável: digite ou escolha aqui | D77: Coluna MEU CÁLCULO e listas de escolha
B78: Verde | C78: Resultado automático e indicadores positivos | D78: Card de resultado e status ✔
B79: Azul-claro | C79: Valor em uso, que entrou na conta | D79: Coluna Valor em uso
B80: Azul | C80: Botões de navegação | D80: Topo das abas e botões dos cards
B81: Azul-marinho | C81: Títulos e cabeçalhos | D81: Faixas de título
B82: Cinza-claro | C82: Explicações, exemplos cadastrados e apoio | D82: Colunas Exemplo 01 e 02 e textos
B83: Vermelho suave | C83: Avisos, erros comuns e dados inválidos | D83: Status ⚠ e linha Erro comum
B85: 12 CUIDADOS ANTES DE UTILIZAR UM RESULTADO
B86: • Confira se as unidades dos seus dados são as mesmas pedidas na calculadora.
B87: • Verifique as hipóteses de cada fórmula (por exemplo, mistura completa e sem reação no balanço de massa).
B88: • Os resultados são cálculos teóricos de apoio ao estudo. Projetos, laudos e decisões operacionais exigem normas técnicas, legislação aplicável e responsável técnico habilitado.
B89: • A calculadora não diz se um valor atende a uma norma ou padrão de lançamento. Compare com o padrão aplicável ao seu caso.
B90: • Arredonde o resultado final de acordo com o que o exercício ou o professor pedir.
B91: • Na dosagem química, considere ficha técnica, compatibilidade e segurança do produto.
B93: 13 GLOSSÁRIO DE SÍMBOLOS E UNIDADES
B94: Símbolo | C94: Significado | D94: Unidade usual
B95: Q | C95: Vazão | D95: m³/s, L/s, m³/h, m³/dia
B96: V | C96: Volume | D96: m³, L, mL
B97: t | C97: Tempo | D97: s, min, h, dia
B98: D | C98: Diâmetro interno (na calculadora 07, D é a dosagem) | D98: m, mm | mg/L
B99: A | C99: Área da seção do tubo | D99: m²
B100: v | C100: Velocidade média do escoamento | D100: m/s
B101: TDH | C101: Tempo de detenção hidráulica | D101: h, min
B102: C | C102: Concentração | D102: mg/L
B103: DBO | C103: Demanda bioquímica de oxigênio | D103: mg/L
B104: DQO | C104: Demanda química de oxigênio | D104: mg/L
B105: SST | C105: Sólidos suspensos totais | D105: mg/L
... B113: ETE / ETA | C113: Estação de tratamento de esgoto / de água | D113: -
B115: 14 PROTEÇÃO, CÓPIAS E COMPATIBILIDADE
B116: • Mantenha uma cópia original deste arquivo sem alterações. Para cada trabalho, salve uma cópia com outro nome (exemplo: Lista3_Hidraulica).
B117: • No Excel, as abas estão protegidas sem senha, só para evitar alterações acidentais. Para editar, use Revisão > Desproteger Planilha (não pede senha).
B118: • Google Planilhas: envie o arquivo .xlsx para o Google Drive, clique com o botão direito > Abrir com > Planilhas Google. Depois use Arquivo > Salvar como Planilhas Google. Os cálculos, listas, cores e gráficos funcionam. Se um botão de navegação não abrir a aba, use as abas na parte de baixo da tela.
B119: • No Google Planilhas, quem é dono do arquivo consegue editar qualquer célula. Para se proteger de apagar uma fórmula sem querer, use Dados > Proteger páginas e intervalos > Mostrar um aviso ao editar.
B120: • O arquivo não usa macros nem internet. LibreOffice Calc também abre e calcula; a aparência dos gráficos pode variar um pouco.
B122: Tudo pronto? Voltar ao Painel Inicial e escolher uma calculadora ▶

Sheet 02 — Vazão e Hidráulica
B1: 💧 CALCULADORA 01 · VAZÃO E HIDRÁULICA | K1: ÁREA TÉCNICA · cálculos auxiliares (não editar)
B2: KIT DE 6 CALCULADORAS AUTOMÁTICAS DE ENGENHARIA AMBIENTAL | K2: Descrição | L2: Valor
B3: 🏠 Painel | C3: 📘 Guia | E3: 📚 Exemplos | G3: ◀ Anterior | H3: Próxima aba ▶ | K3: ferramenta escolhida (número) | L3: =IFERROR(MATCH($C$18,{"Ferramenta 1: Vazão por volume e tempo","Ferramenta 2: Vazão em tubulações","Ferramenta 3: Velocidade do escoamento","Ferramenta 4: Tempo de detenção (TDH)"},0),0) -> 1
K4: índice do cenário (1, 2 ou 3) | L4: =IFERROR(MATCH($C$26,{"Exemplo 01","Exemplo 02","Meu cálculo"},0),0) -> 1
B5: COMO USAR: ① Escolha a ferramenta abaixo ② Escolha o cenário na lista amarela ③ Para usar seus dados, escolha Meu cálculo e digite na coluna amarela ④ Veja o resultado no card verde ⑤ Confira a conta em ENTENDA O CÁLCULO | K5: [Vazão por volume e tempo] fV | L5: =IFERROR(CHOOSE(MATCH($G$31,{"m³","L"},0),1,0.001),"") -> 1
K6: [Vazão por volume e tempo] ft | L6: =IFERROR(CHOOSE(MATCH($G$33,{"s","min","h","dia"},0),1,60,3600,86400),"") -> 3600
B7: A · IDENTIFICAÇÃO | K7: [Vazão por volume e tempo] Vm | L7: =IFERROR($G$30*$L$5,"") -> 360
B8: O que calcula | C8: Vazão (volume por tempo), área da seção de tubos, velocidade do escoamento e tempo de detenção hidráulica (TDH). | K8: [Vazão por volume e tempo] ts | L8: =IFERROR($G$32*$L$6,"") -> 7200
B9: Quando usar | C9: Conferência de tubulações, bombas, tanques, reservatórios, lagoas e unidades de tratamento. Útil em Hidráulica, Saneamento e Tratamento de Água e Esgoto. | K9: [Vazão por volume e tempo] Qs | L9: =IFERROR($L$7/$L$8,"") -> 0.05
B10: Exemplo prático | C10: Descobrir a vazão de uma bomba que enche um tanque de 360 m³ em 2 horas, ou quanto tempo o esgoto fica em um tanque de equalização. | K10: [Vazão por volume e tempo] Qh | L10: =IFERROR($L$9*3600,"") -> 180
K11: [Vazão por volume e tempo] Ql | L11: =IFERROR($L$9*1000,"") -> 50
B12: FERRAMENTAS DESTA CALCULADORA | K12: [Vazão por volume e tempo] Qd | L12: =IFERROR($L$9*86400,"") -> 4320
B13: ▶ Ferramenta 1 | C13: Vazão a partir de volume e tempo: Calcula a vazão quando você sabe quanto volume passou e em quanto tempo. O resultado sai automaticamente em m³/s, m³/h, L/s e m³/dia. | K13: [Vazão por volume e tempo] mensagem de validação | L13: =IFERROR(IF($L$4=0,"Escolha um cenário na lista: Exemplo 01, Exemplo 02 ou Meu cálculo.",IF($G$30="","Informe o volume para continuar.",IF(NOT(ISNUMBER($G$30)),"O volume precisa ser um número. Confira o valor digitado.",IF($G$30<=0,"O volume deve ser maior que zero.",IF($L$5="","Confira a unidade selecionada para o volume.",IF($G$32="","Informe o tempo para continuar.",IF(NOT(ISNUMBER($G$32)),"O tempo precisa ser um número. Confira o valor digitado.",IF($G$32<=0,"O tempo deve ser maior que zero.",IF($L$6="","Confira a unidade selecionada para o tempo.",""))))))))),"Resultado indisponível: existem dados inválidos.")
B14: ▶ Ferramenta 2 | C14: Vazão em tubulações: Calcula a área da seção de um tubo circular e a vazão transportada a partir do diâmetro interno e da velocidade média do escoamento. | K14: [Vazão por volume e tempo] dados válidos? | L14: =$L$13="" -> TRUE
B15: ▶ Ferramenta 3 | C15: Velocidade do escoamento: Calcula a velocidade média do líquido dentro de um tubo circular a partir da vazão e do diâmetro interno. | K15: [Vazão por volume e tempo] Qd (arredondado) | L15: =IFERROR(ROUND($L$12,IF($L$12=0,0,4-INT(LOG10(ABS($L$12))))),"") -> 4320
B16: ▶ Ferramenta 4 | C16: Tempo de detenção hidráulica (TDH): Calcula quanto tempo, em média, o líquido permanece dentro de um tanque, reator ou lagoa. | K16: [Vazão por volume e tempo] Qd (texto) | L16: =IF(ISNUMBER($L$15),FIXED($L$15,IF(ROUND($L$15,0)=$L$15,0,IF(ROUND($L$15,1)=$L$15,1,IF(ROUND($L$15,2)=$L$15,2,IF(ROUND($L$15,3)=$L$15,3,IF(ROUND($L$15,4)=$L$15,4,IF(ROUND($L$15,5)=$L$15,5,IF(ROUND($L$15,6)=$L$15,6,7)))))))),"?") -> 4.320
K17: [Vazão por volume e tempo] Qh (arredondado) | L17: =IFERROR(ROUND($L$10,IF($L$10=0,0,4-INT(LOG10(ABS($L$10))))),"") -> 180
B18: Ferramenta escolhida ▼ | C18: Ferramenta 1: Vazão por volume e tempo | F18: A ferramenta escolhida fica com o título em verde. Use os botões azuis acima para ir até ela. | K18: [Vazão por volume e tempo] Qh (texto) | L18: =IF(ISNUMBER($L$17),FIXED($L$17,IF(ROUND($L$17,0)=$L$17,0,IF(ROUND($L$17,1)=$L$17,1,IF(ROUND($L$17,2)=$L$17,2,IF(ROUND($L$17,3)=$L$17,3,IF(ROUND($L$17,4)=$L$17,4,IF(ROUND($L$17,5)=$L$17,5,IF(ROUND($L$17,6)=$L$17,6,7)))))))),"?") -> 180
B19: Resultado atual | C19: =IFERROR(CHOOSE($L$3,$L$31,$L$55,$L$77,$L$100),"—") -> 180 m³/h | K19: [Vazão por volume e tempo] Ql (arredondado) | L19: =IFERROR(ROUND($L$11,IF($L$11=0,0,4-INT(LOG10(ABS($L$11))))),"") -> 50
B20: Status | C20: =IFERROR(CHOOSE($L$3,C42,C77,C113,C149),"Escolha uma ferramenta.") -> ✔ Dados válidos. Resultado calculado automaticamente. | K20: [Vazão por volume e tempo] Ql (texto) | L20: =IF(ISNUMBER($L$19),FIXED($L$19,IF(ROUND($L$19,0)=$L$19,0,IF(ROUND($L$19,1)=$L$19,1,IF(ROUND($L$19,2)=$L$19,2,IF(ROUND($L$19,3)=$L$19,3,IF(ROUND($L$19,4)=$L$19,4,IF(ROUND($L$19,5)=$L$19,5,IF(ROUND($L$19,6)=$L$19,6,7)))))))),"?") -> 50
K21: [Vazão por volume e tempo] V (arredondado) | L21: =IFERROR(ROUND($G$30,IF($G$30=0,0,4-INT(LOG10(ABS($G$30))))),"") -> 360
B22: FERRAMENTA 1 · VAZÃO A PARTIR DE VOLUME E TEMPO | H22: ▲ Voltar ao topo | K22: [Vazão por volume e tempo] V (texto) | L22: =IF(ISNUMBER($L$21),FIXED($L$21,IF(ROUND($L$21,0)=$L$21,0,IF(ROUND($L$21,1)=$L$21,1,IF(ROUND($L$21,2)=$L$21,2,IF(ROUND($L$21,3)=$L$21,3,IF(ROUND($L$21,4)=$L$21,4,IF(ROUND($L$21,5)=$L$21,5,IF(ROUND($L$21,6)=$L$21,6,7)))))))),"?") -> 360
B23: Calcula a vazão quando você sabe quanto volume passou e em quanto tempo. O resultado sai automaticamente em m³/s, m³/h, L/s e m³/dia. | K23: [Vazão por volume e tempo] t (arredondado) | L23: =IFERROR(ROUND($G$32,IF($G$32=0,0,4-INT(LOG10(ABS($G$32))))),"") -> 2
K24: [Vazão por volume e tempo] t (texto) | L24: =IF(ISNUMBER($L$23),FIXED($L$23,IF(ROUND($L$23,0)=$L$23,0,IF(ROUND($L$23,1)=$L$23,1,IF(ROUND($L$23,2)=$L$23,2,IF(ROUND($L$23,3)=$L$23,3,IF(ROUND($L$23,4)=$L$23,4,IF(ROUND($L$23,5)=$L$23,5,IF(ROUND($L$23,6)=$L$23,6,7)))))))),"?") -> 2
B25: B · ESCOLHA DO CENÁRIO | K25: [Vazão por volume e tempo] Qs (arredondado) | L25: =IFERROR(ROUND($L$9,IF($L$9=0,0,4-INT(LOG10(ABS($L$9))))),"") -> 0.05
B26: Cenário ▼ | C26: Exemplo 01 | E26: Exemplo 01 e Exemplo 02 usam dados prontos. Meu cálculo usa os valores que você digitar na coluna amarela. | K26: [Vazão por volume e tempo] Qs (texto) | L26: =IF(ISNUMBER($L$25),FIXED($L$25,IF(ROUND($L$25,0)=$L$25,0,IF(ROUND($L$25,1)=$L$25,1,IF(ROUND($L$25,2)=$L$25,2,IF(ROUND($L$25,3)=$L$25,3,IF(ROUND($L$25,4)=$L$25,4,IF(ROUND($L$25,5)=$L$25,5,IF(ROUND($L$25,6)=$L$25,6,7)))))))),"?") -> 0,05
K27: [Vazão por volume e tempo] Vm (arredondado) | L27: =IFERROR(ROUND($L$7,IF($L$7=0,0,4-INT(LOG10(ABS($L$7))))),"") -> 360
B28: C · DADOS DE ENTRADA | K28: [Vazão por volume e tempo] Vm (texto) | L28: =IF(ISNUMBER($L$27),FIXED($L$27,IF(ROUND($L$27,0)=$L$27,0,IF(ROUND($L$27,1)=$L$27,1,IF(ROUND($L$27,2)=$L$27,2,IF(ROUND($L$27,3)=$L$27,3,IF(ROUND($L$27,4)=$L$27,4,IF(ROUND($L$27,5)=$L$27,5,IF(ROUND($L$27,6)=$L$27,6,7)))))))),"?") -> 360
B29: Variável | C29: Exemplo 01 | D29: Exemplo 02 | E29: MEU CÁLCULO | F29: Unidade | G29: Valor em uso | H29: Orientação de preenchimento | K29: [Vazão por volume e tempo] ts (arredondado) | L29: =IFERROR(ROUND($L$8,IF($L$8=0,0,4-INT(LOG10(ABS($L$8))))),"") -> 7200
B30: Volume | C30: 360 | D30: 15000 | F30: =$G$31 -> m³ | G30: =IF($L$4=1,C30,IF($L$4=2,D30,IF($L$4=3,IF(E30="","",E30),""))) -> 360 | H30: Volume que passou, encheu ou esvaziou. Ex.: 360 | K30: [Vazão por volume e tempo] ts (texto) | L30: =IF(ISNUMBER($L$29),FIXED($L$29,IF(ROUND($L$29,0)=$L$29,0,IF(ROUND($L$29,1)=$L$29,1,IF(ROUND($L$29,2)=$L$29,2,IF(ROUND($L$29,3)=$L$29,3,IF(ROUND($L$29,4)=$L$29,4,IF(ROUND($L$29,5)=$L$29,5,IF(ROUND($L$29,6)=$L$29,6,7)))))))),"?") -> 7.200
B31: Unidade do volume | C31: m³ | D31: L | E31: m³ | F31: lista ▼ | G31: =IF($L$4=1,C31,IF($L$4=2,D31,IF($L$4=3,IF(E31="","",E31),""))) -> m³ | H31: Escolha m³ ou L na lista. | K31: [Vazão por volume e tempo] resumo | L31: =IF($L$14,$L$18&" "&"m³/h","—") -> 180 m³/h
B32: Tempo | C32: 2 | D32: 25 | F32: =$G$33 -> h | G32: =IF($L$4=1,C32,IF($L$4=2,D32,IF($L$4=3,IF(E32="","",E32),""))) -> 2 | H32: Tempo gasto para esse volume passar. Ex.: 2 | K32: índice do cenário (1, 2 ou 3) | L32: =IFERROR(MATCH($C$62,{"Exemplo 01","Exemplo 02","Meu cálculo"},0),0) -> 1
B33: Unidade do tempo | C33: h | D33: min | E33: h | F33: lista ▼ | G33: =IF($L$4=1,C33,IF($L$4=2,D33,IF($L$4=3,IF(E33="","",E33),""))) -> h | H33: Escolha s, min, h ou dia. | K33: [Vazão em tubulações] fD | L33: =IFERROR(CHOOSE(MATCH($G$67,{"m","cm","mm","pol"},0),1,0.01,0.001,0.0254),"") -> 1
K34: [Vazão em tubulações] Dm | L34: =IFERROR($G$66*$L$33,"") -> 0.3
B35: D · RESULTADO AUTOMÁTICO | K35: [Vazão em tubulações] A | L35: =IFERROR(PI()*$L$34^2/4,"") -> 0.070685835
B36: VAZÃO EM m³/h | E36: OUTROS RESULTADOS | K36: [Vazão em tubulações] Q | L36: =IFERROR($L$35*$G$68,"") -> 0.10602875
B37: =IF($L$14,$L$10,"—") -> 180 | D37: m³/h | E37: Vazão em m³/s | G37: =IF($L$14,$L$9,"—") -> 0.05 | H37: m³/s | K37: [Vazão em tubulações] Ql | L37: =IFERROR($L$36*1000,"") -> 106.02875
E38: Vazão em L/s | G38: =IF($L$14,$L$11,"—") -> 50 | H38: L/s | K38: [Vazão em tubulações] Qh | L38: =IFERROR($L$36*3600,"") -> 381.70351
E39: Vazão em m³/dia | G39: =IF($L$14,$L$12,"—") -> 4320 | H39: m³/dia | K39: [Vazão em tubulações] mensagem de validação | L39: =IFERROR(IF($L$32=0,"Escolha um cenário na lista: Exemplo 01, Exemplo 02 ou Meu cálculo.",IF($G$66="","Informe o diâmetro para continuar.",IF(NOT(ISNUMBER($G$66)),"O diâmetro precisa ser um número. Confira o valor digitado.",IF($G$66<=0,"O diâmetro deve ser maior que zero.",IF($L$33="","Confira a unidade selecionada para o diâmetro.",IF($G$68="","Informe a velocidade para continuar.",IF(NOT(ISNUMBER($G$68)),"A velocidade precisa ser um número. Confira o valor digitado.",IF($G$68<=0,"A velocidade deve ser maior que zero.","")))))))),"Resultado indisponível: existem dados inválidos.")
K40: [Vazão em tubulações] dados válidos? | L40: =$L$39="" -> TRUE
B41: Interpretação | C41: =IF($L$14,"A cada hora passam "&$L$18&" m³ de líquido. Isso é o mesmo que "&$L$20&" litros por segundo, ou "&$L$16&" m³ por dia.","Resultado indisponível: corrija o item indicado em Status dos dados.") -> A cada hora passam 180 m³ de líquido. Isso é o mesmo que 50 litros por segundo, ou 4.320 m³ por dia. | K41: [Vazão em tubulações] A (arredondado) | L41: =IFERROR(ROUND($L$35,IF($L$35=0,0,4-INT(LOG10(ABS($L$35))))),"") -> 0.070686
B42: Status dos dados | C42: =IF($L$14,"✔ Dados válidos. Resultado calculado automaticamente.","⚠ "&$L$13) -> ✔ Dados válidos. Resultado calculado automaticamente. | K42: [Vazão em tubulações] A (texto) | L42: =IF(ISNUMBER($L$41),FIXED($L$41,IF(ROUND($L$41,0)=$L$41,0,IF(ROUND($L$41,1)=$L$41,1,IF(ROUND($L$41,2)=$L$41,2,IF(ROUND($L$41,3)=$L$41,3,IF(ROUND($L$41,4)=$L$41,4,IF(ROUND($L$41,5)=$L$41,5,IF(ROUND($L$41,6)=$L$41,6,7)))))))),"?") -> 0,070686
K43: [Vazão em tubulações] Ql (arredondado) | L43: =IFERROR(ROUND($L$37,IF($L$37=0,0,4-INT(LOG10(ABS($L$37))))),"") -> 106.03
B44: E · ENTENDA O CÁLCULO | K44: [Vazão em tubulações] Ql (texto) | L44: =IF(ISNUMBER($L$43),FIXED($L$43,IF(ROUND($L$43,0)=$L$43,0,IF(ROUND($L$43,1)=$L$43,1,IF(ROUND($L$43,2)=$L$43,2,IF(ROUND($L$43,3)=$L$43,3,IF(ROUND($L$43,4)=$L$43,4,IF(ROUND($L$43,5)=$L$43,5,IF(ROUND($L$43,6)=$L$43,6,7)))))))),"?") -> 106,03
B45: Fórmula | C45: Q = V ÷ t | K45: [Vazão em tubulações] D (arredondado) | L45: =IFERROR(ROUND($G$66,IF($G$66=0,0,4-INT(LOG10(ABS($G$66))))),"") -> 0.3
B46: O que é cada variável | C46: Q = vazão (volume que passa por unidade de tempo) | V = volume | t = tempo gasto | K46: [Vazão em tubulações] D (texto) | L46: =IF(ISNUMBER($L$45),FIXED($L$45,IF(ROUND($L$45,0)=$L$45,0,IF(ROUND($L$45,1)=$L$45,1,IF(ROUND($L$45,2)=$L$45,2,IF(ROUND($L$45,3)=$L$45,3,IF(ROUND($L$45,4)=$L$45,4,IF(ROUND($L$45,5)=$L$45,5,IF(ROUND($L$45,6)=$L$45,6,7)))))))),"?") -> 0,3
B47: Valores inseridos | C47: ="V = "&$L$22&" "&$G$31&" | "&"t = "&$L$24&" "&$G$33 -> V = 360 m³ | t = 2 h | K47: [Vazão em tubulações] v (arredondado) | L47: =IFERROR(ROUND($G$68,IF($G$68=0,0,4-INT(LOG10(ABS($G$68))))),"") -> 1.5
B48: Substituição | C48: =IF($L$14,"Convertendo para o SI: V = "&$L$28&" m³ e t = "&$L$30&" s."&CHAR(10)&"Q = "&$L$28&" ÷ "&$L$30&" = "&$L$26&" m³/s","Aguardando dados válidos para montar a conta.") -> Convertendo para o SI: V = 360 m³ e t = 7.200 s. Q = 360 ÷ 7.200 = 0,05 m³/s | K48: [Vazão em tubulações] v (texto) | L48: =IF(ISNUMBER($L$47),FIXED($L$47,IF(ROUND($L$47,0)=$L$47,0,IF(ROUND($L$47,1)=$L$47,1,IF(ROUND($L$47,2)=$L$47,2,IF(ROUND($L$47,3)=$L$47,3,IF(ROUND($L$47,4)=$L$47,4,IF(ROUND($L$47,5)=$L$47,5,IF(ROUND($L$47,6)=$L$47,6,7)))))))),"?") -> 1,5
B49: Resultado | C49: =IF($L$14,"Q = "&$L$18&" m³/h = "&$L$20&" L/s = "&$L$26&" m³/s = "&$L$16&" m³/dia","Aguardando dados válidos para montar a conta.") -> Q = 180 m³/h = 50 L/s = 0,05 m³/s = 4.320 m³/dia | K49: [Vazão em tubulações] Dm (arredondado) | L49: =IFERROR(ROUND($L$34,IF($L$34=0,0,4-INT(LOG10(ABS($L$34))))),"") -> 0.3
K50: [Vazão em tubulações] Dm (texto) | L50: =IF(ISNUMBER($L$49),FIXED($L$49,IF(ROUND($L$49,0)=$L$49,0,IF(ROUND($L$49,1)=$L$49,1,IF(ROUND($L$49,2)=$L$49,2,IF(ROUND($L$49,3)=$L$49,3,IF(ROUND($L$49,4)=$L$49,4,IF(ROUND($L$49,5)=$L$49,5,IF(ROUND($L$49,6)=$L$49,6,7)))))))),"?") -> 0,3
B51: F · EXEMPLO E ORIENTAÇÃO | K51: [Vazão em tubulações] Q (arredondado) | L51: =IFERROR(ROUND($L$36,IF($L$36=0,0,4-INT(LOG10(ABS($L$36))))),"") -> 0.10603
B52: Exemplos desta ferramenta | C52: Exemplo 01: Uma bomba enche um tanque de 360 m³ em 2 horas. Qual é a vazão da bomba? Exemplo 02: Um reservatório com 15.000 litros foi esvaziado em 25 minutos. Qual foi a vazão média de saída? Escolha o exemplo na lista Cenário para ver a resolução completa. | K52: [Vazão em tubulações] Q (texto) | L52: =IF(ISNUMBER($L$51),FIXED($L$51,IF(ROUND($L$51,0)=$L$51,0,IF(ROUND($L$51,1)=$L$51,1,IF(ROUND($L$51,2)=$L$51,2,IF(ROUND($L$51,3)=$L$51,3,IF(ROUND($L$51,4)=$L$51,4,IF(ROUND($L$51,5)=$L$51,5,IF(ROUND($L$51,6)=$L$51,6,7)))))))),"?") -> 0,10603
B53: Como interpretar | C53: Quanto maior a vazão, mais volume passa no mesmo tempo. Use m³/s em fórmulas de hidráulica e m³/dia em cálculos de carga e dosagem. | K53: [Vazão em tubulações] Qh (arredondado) | L53: =IFERROR(ROUND($L$38,IF($L$38=0,0,4-INT(LOG10(ABS($L$38))))),"") -> 381.7
B54: ⚠ Erro comum | C54: Esquecer de converter o tempo antes de dividir. 360 m³ em 2 h dá 180 m³/h, e não 180 m³/s. | K54: [Vazão em tubulações] Qh (texto) | L54: =IF(ISNUMBER($L$53),FIXED($L$53,IF(ROUND($L$53,0)=$L$53,0,IF(ROUND($L$53,1)=$L$53,1,IF(ROUND($L$53,2)=$L$53,2,IF(ROUND($L$53,3)=$L$53,3,IF(ROUND($L$53,4)=$L$53,4,IF(ROUND($L$53,5)=$L$53,5,IF(ROUND($L$53,6)=$L$53,6,7)))))))),"?") -> 381,7
B55: 💡 Dica prática | C55: Guarde esta relação: 1 L/s = 3,6 m³/h = 86,4 m³/dia. | K55: [Vazão em tubulações] resumo | L55: =IF($L$40,$L$52&" "&"m³/s","—") -> 0,10603 m³/s
K56: índice do cenário (1, 2 ou 3) | L56: =IFERROR(MATCH($C$97,{"Exemplo 01","Exemplo 02","Meu cálculo"},0),0) -> 1
K57: [Velocidade do escoamento] fQ | L57: =IFERROR(CHOOSE(MATCH($G$102,{"m³/s","L/s","m³/h","m³/dia"},0),1,0.001,1/3600,1/86400),"") -> 1
B58: FERRAMENTA 2 · VAZÃO EM TUBULAÇÕES | H58: ▲ Voltar ao topo | K58: [Velocidade do escoamento] Qs | L58: =IFERROR($G$101*$L$57,"") -> 0.05
B59: Calcula a área da seção de um tubo circular e a vazão transportada a partir do diâmetro interno e da velocidade média do escoamento. | K59: [Velocidade do escoamento] fD | L59: =IFERROR(CHOOSE(MATCH($G$104,{"m","cm","mm","pol"},0),1,0.01,0.001,0.0254),"") -> 1
K60: [Velocidade do escoamento] Dm | L60: =IFERROR($G$103*$L$59,"") -> 0.2
B61: B · ESCOLHA DO CENÁRIO | K61: [Velocidade do escoamento] A | L61: =IFERROR(PI()*$L$60^2/4,"") -> 0.031415927
B62: Cenário ▼ | C62: Exemplo 01 | E62: Exemplo 01 e Exemplo 02 usam dados prontos. Meu cálculo usa os valores que você digitar na coluna amarela. | K62: [Velocidade do escoamento] vel | L62: =IFERROR($L$58/$L$61,"") -> 1.5915494
K63: [Velocidade do escoamento] mensagem de validação | L63: =IFERROR(IF($L$56=0,"Escolha um cenário na lista: Exemplo 01, Exemplo 02 ou Meu cálculo.",IF($G$101="","Informe a vazão para continuar.",IF(NOT(ISNUMBER($G$101)),"A vazão precisa ser um número. Confira o valor digitado.",IF($G$101<=0,"A vazão deve ser maior que zero.",IF($L$57="","Confira a unidade selecionada para a vazão.",IF($G$103="","Informe o diâmetro para continuar.",IF(NOT(ISNUMBER($G$103)),"O diâmetro precisa ser um número. Confira o valor digitado.",IF($G$103<=0,"O diâmetro deve ser maior que zero.",IF($L$59="","Confira a unidade selecionada para o diâmetro.",""))))))))),"Resultado indisponível: existem dados inválidos.")
B64: C · DADOS DE ENTRADA | K64: [Velocidade do escoamento] dados válidos? | L64: =$L$63="" -> TRUE
B65: Variável | C65: Exemplo 01 | D65: Exemplo 02 | E65: MEU CÁLCULO | F65: Unidade | G65: Valor em uso | H65: Orientação de preenchimento | K65: [Velocidade do escoamento] vel (arredondado) | L65: =IFERROR(ROUND($L$62,IF($L$62=0,0,4-INT(LOG10(ABS($L$62))))),"") -> 1.5915
B66: Diâmetro interno | C66: 0.3 | D66: 150 | F66: =$G$67 -> m | G66: =IF($L$32=1,C66,IF($L$32=2,D66,IF($L$32=3,IF(E66="","",E66),""))) -> 0.3 | H66: Diâmetro interno do tubo (não use o raio). Ex.: 0,30 | K66: [Velocidade do escoamento] vel (texto) | L66: =IF(ISNUMBER($L$65),FIXED($L$65,IF(ROUND($L$65,0)=$L$65,0,IF(ROUND($L$65,1)=$L$65,1,IF(ROUND($L$65,2)=$L$65,2,IF(ROUND($L$65,3)=$L$65,3,IF(ROUND($L$65,4)=$L$65,4,IF(ROUND($L$65,5)=$L$65,5,IF(ROUND($L$65,6)=$L$65,6,7)))))))),"?") -> 1,5915
B67: Unidade do diâmetro | C67: m | D67: mm | E67: m | F67: lista ▼ | G67: =IF($L$32=1,C67,IF($L$32=2,D67,IF($L$32=3,IF(E67="","",E67),""))) -> m | H67: Escolha m, cm, mm ou pol. | K67: [Velocidade do escoamento] D (arredondado) | L67: =IFERROR(ROUND($G$103,IF($G$103=0,0,4-INT(LOG10(ABS($G$103))))),"") -> 0.2
B68: Velocidade média | C68: 1.5 | D68: 0.8 | F68: m/s | G68: =IF($L$32=1,C68,IF($L$32=2,D68,IF($L$32=3,IF(E68="","",E68),""))) -> 1.5 | H68: Velocidade média da água no tubo. Ex.: 1,5 | K68: [Velocidade do escoamento] D (texto) | L68: =IF(ISNUMBER($L$67),FIXED($L$67,IF(ROUND($L$67,0)=$L$67,0,IF(ROUND($L$67,1)=$L$67,1,IF(ROUND($L$67,2)=$L$67,2,IF(ROUND($L$67,3)=$L$67,3,IF(ROUND($L$67,4)=$L$67,4,IF(ROUND($L$67,5)=$L$67,5,IF(ROUND($L$67,6)=$L$67,6,7)))))))),"?") -> 0,2
K69: [Velocidade do escoamento] Q (arredondado) | L69: =IFERROR(ROUND($G$101,IF($G$101=0,0,4-INT(LOG10(ABS($G$101))))),"") -> 0.05
B70: D · RESULTADO AUTOMÁTICO | K70: [Velocidade do escoamento] Q (texto) | L70: =IF(ISNUMBER($L$69),FIXED($L$69,IF(ROUND($L$69,0)=$L$69,0,IF(ROUND($L$69,1)=$L$69,1,IF(ROUND($L$69,2)=$L$69,2,IF(ROUND($L$69,3)=$L$69,3,IF(ROUND($L$69,4)=$L$69,4,IF(ROUND($L$69,5)=$L$69,5,IF(ROUND($L$69,6)=$L$69,6,7)))))))),"?") -> 0,05
B71: VAZÃO EM m³/s | E71: OUTROS RESULTADOS | K71: [Velocidade do escoamento] A (arredondado) | L71: =IFERROR(ROUND($L$61,IF($L$61=0,0,4-INT(LOG10(ABS($L$61))))),"") -> 0.031416
B72: =IF($L$40,$L$36,"—") -> 0.10602875 | D72: m³/s | E72: Área da seção | G72: =IF($L$40,$L$35,"—") -> 0.070685835 | H72: m² | K72: [Velocidade do escoamento] A (texto) | L72: =IF(ISNUMBER($L$71),FIXED($L$71,IF(ROUND($L$71,0)=$L$71,0,IF(ROUND($L$71,1)=$L$71,1,IF(ROUND($L$71,2)=$L$71,2,IF(ROUND($L$71,3)=$L$71,3,IF(ROUND($L$71,4)=$L$71,4,IF(ROUND($L$71,5)=$L$71,5,IF(ROUND($L$71,6)=$L$71,6,7)))))))),"?") -> 0,031416
E73: Vazão em L/s | G73: =IF($L$40,$L$37,"—") -> 106.02875 | H73: L/s | K73: [Velocidade do escoamento] Dm (arredondado) | L73: =IFERROR(ROUND($L$60,IF($L$60=0,0,4-INT(LOG10(ABS($L$60))))),"") -> 0.2
E74: Vazão em m³/h | G74: =IF($L$40,$L$38,"—") -> 381.70351 | H74: m³/h | K74: [Velocidade do escoamento] Dm (texto) | L74: =IF(ISNUMBER($L$73),FIXED($L$73,IF(ROUND($L$73,0)=$L$73,0,IF(ROUND($L$73,1)=$L$73,1,IF(ROUND($L$73,2)=$L$73,2,IF(ROUND($L$73,3)=$L$73,3,IF(ROUND($L$73,4)=$L$73,4,IF(ROUND($L$73,5)=$L$73,5,IF(ROUND($L$73,6)=$L$73,6,7)))))))),"?") -> 0,2
K75: [Velocidade do escoamento] Qs (arredondado) | L75: =IFERROR(ROUND($L$58,IF($L$58=0,0,4-INT(LOG10(ABS($L$58))))),"") -> 0.05
B76: Interpretação | C76: =IF($L$40,"Pela seção de "&$L$42&" m² passam "&$L$44&" litros por segundo."&IF(OR($G$68<0.6,$G$68>3)," Atenção: a velocidade informada está fora da faixa de referência usual em tubulações de água (cerca de 0,6 a 3 m/s). Confira o dado.",""),"Resultado indisponível: corrija o item indicado em Status dos dados.") -> Pela seção de 0,070686 m² passam 106,03 litros por segundo. | K76: [Velocidade do escoamento] Qs (texto) | L76: =IF(ISNUMBER($L$75),FIXED($L$75,IF(ROUND($L$75,0)=$L$75,0,IF(ROUND($L$75,1)=$L$75,1,IF(ROUND($L$75,2)=$L$75,2,IF(ROUND($L$75,3)=$L$75,3,IF(ROUND($L$75,4)=$L$75,4,IF(ROUND($L$75,5)=$L$75,5,IF(ROUND($L$75,6)=$L$75,6,7)))))))),"?") -> 0,05
B77: Status dos dados | C77: =IF($L$40,"✔ Dados válidos. Resultado calculado automaticamente.","⚠ "&$L$39) -> ✔ Dados válidos. Resultado calculado automaticamente. | K77: [Velocidade do escoamento] resumo | L77: =IF($L$64,$L$66&" "&"m/s","—") -> 1,5915 m/s
K78: índice do cenário (1, 2 ou 3) | L78: =IFERROR(MATCH($C$133,{"Exemplo 01","Exemplo 02","Meu cálculo"},0),0) -> 1
B79: E · ENTENDA O CÁLCULO | K79: [Tempo de detenção (TDH)] fV | L79: =IFERROR(CHOOSE(MATCH($G$138,{"m³","L"},0),1,0.001),"") -> 1
B80: Fórmula | C80: Q = A × v, com A = π × D² ÷ 4 | K80: [Tempo de detenção (TDH)] Vm | L80: =IFERROR($G$137*$L$79,"") -> 500
B81: O que é cada variável | C81: Q = vazão | A = área interna da seção | D = diâmetro interno | v = velocidade média | K81: [Tempo de detenção (TDH)] fQ | L81: =IFERROR(CHOOSE(MATCH($G$140,{"m³/s","L/s","m³/h","m³/dia"},0),1,0.001,1/3600,1/86400),"") -> 0.00027777778
B82: Valores inseridos | C82: ="D = "&$L$46&" "&$G$67&" | "&"v = "&$L$48&" "&"m/s" -> D = 0,3 m | v = 1,5 m/s | K82: [Tempo de detenção (TDH)] Qh | L82: =IFERROR($G$139*$L$81*3600,"") -> 50
B83: Substituição | C83: =IF($L$40,"D em metros = "&$L$50&" m."&CHAR(10)&"A = π × "&$L$50&"² ÷ 4 = "&$L$42&" m² → Q = "&$L$42&" × "&$L$48&" = "&$L$52&" m³/s","Aguardando dados válidos para montar a conta.") -> D em metros = 0,3 m. A = π × 0,3² ÷ 4 = 0,070686 m² → Q = 0,070686 × 1,5 = 0,10603 m³/s | K83: [Tempo de detenção (TDH)] th | L83: =IFERROR($L$80/$L$82,"") -> 10
B84: Resultado | C84: =IF($L$40,"Área = "&$L$42&" m² | Q = "&$L$52&" m³/s = "&$L$44&" L/s = "&$L$54&" m³/h","Aguardando dados válidos para montar a conta.") -> Área = 0,070686 m² | Q = 0,10603 m³/s = 106,03 L/s = 381,7 m³/h | K84: [Tempo de detenção (TDH)] tm | L84: =IFERROR($L$83*60,"") -> 600
K85: [Tempo de detenção (TDH)] td | L85: =IFERROR($L$83/24,"") -> 0.41666667
B86: F · EXEMPLO E ORIENTAÇÃO | K86: [Tempo de detenção (TDH)] mensagem de validação | L86: =IFERROR(IF($L$78=0,"Escolha um cenário na lista: Exemplo 01, Exemplo 02 ou Meu cálculo.",IF($G$137="","Informe o volume útil para continuar.",IF(NOT(ISNUMBER($G$137)),"O volume útil precisa ser um número. Confira o valor digitado.",IF($G$137<=0,"O volume útil deve ser maior que zero.",IF($L$79="","Confira a unidade selecionada para o volume.",IF($G$139="","Informe a vazão para continuar.",IF(NOT(ISNUMBER($G$139)),"A vazão precisa ser um número. Confira o valor digitado.",IF($G$139<=0,"A vazão deve ser maior que zero.",IF($L$81="","Confira a unidade selecionada para a vazão.",""))))))))),"Resultado indisponível: existem dados inválidos.")
B87: Exemplos desta ferramenta | C87: Exemplo 01: Uma adutora tem diâmetro interno de 0,30 m e a água escoa a 1,5 m/s. Qual é a vazão transportada? Exemplo 02: Um tubo com 150 mm de diâmetro interno conduz esgoto tratado a 0,8 m/s. Qual é a vazão? Escolha o exemplo na lista Cenário para ver a resolução completa. | K87: [Tempo de detenção (TDH)] dados válidos? | L87: =$L$86="" -> TRUE
B88: Como interpretar | C88: O resultado mostra quanto líquido o tubo transporta com aquela velocidade. Para levar mais vazão, aumente o diâmetro ou aceite uma velocidade maior. | K88: [Tempo de detenção (TDH)] th (arredondado) | L88: =IFERROR(ROUND($L$83,IF($L$83=0,0,4-INT(LOG10(ABS($L$83))))),"") -> 10
B89: ⚠ Erro comum | C89: Usar o diâmetro em mm ou cm direto na fórmula, ou usar o raio no lugar do diâmetro. Converta para metros antes: 150 mm = 0,15 m. | K89: [Tempo de detenção (TDH)] th (texto) | L89: =IF(ISNUMBER($L$88),FIXED($L$88,IF(ROUND($L$88,0)=$L$88,0,IF(ROUND($L$88,1)=$L$88,1,IF(ROUND($L$88,2)=$L$88,2,IF(ROUND($L$88,3)=$L$88,3,IF(ROUND($L$88,4)=$L$88,4,IF(ROUND($L$88,5)=$L$88,5,IF(ROUND($L$88,6)=$L$88,6,7)))))))),"?") -> 10
B90: 💡 Dica prática | C90: Use sempre o diâmetro interno. O diâmetro nominal (DN) do catálogo pode ser diferente do interno. | K90: [Tempo de detenção (TDH)] tm (arredondado) | L90: =IFERROR(ROUND($L$84,IF($L$84=0,0,4-INT(LOG10(ABS($L$84))))),"") -> 600
K91: [Tempo de detenção (TDH)] tm (texto) | L91: =IF(ISNUMBER($L$90),FIXED($L$90,IF(ROUND($L$90,0)=$L$90,0,IF(ROUND($L$90,1)=$L$90,1,IF(ROUND($L$90,2)=$L$90,2,IF(ROUND($L$90,3)=$L$90,3,IF(ROUND($L$90,4)=$L$90,4,IF(ROUND($L$90,5)=$L$90,5,IF(ROUND($L$90,6)=$L$90,6,7)))))))),"?") -> 600
K92: [Tempo de detenção (TDH)] Q (arredondado) | L92: =IFERROR(ROUND($G$139,IF($G$139=0,0,4-INT(LOG10(ABS($G$139))))),"") -> 50
B93: FERRAMENTA 3 · VELOCIDADE DO ESCOAMENTO | H93: ▲ Voltar ao topo | K93: [Tempo de detenção (TDH)] Q (texto) | L93: =IF(ISNUMBER($L$92),FIXED($L$92,IF(ROUND($L$92,0)=$L$92,0,IF(ROUND($L$92,1)=$L$92,1,IF(ROUND($L$92,2)=$L$92,2,IF(ROUND($L$92,3)=$L$92,3,IF(ROUND($L$92,4)=$L$92,4,IF(ROUND($L$92,5)=$L$92,5,IF(ROUND($L$92,6)=$L$92,6,7)))))))),"?") -> 50
B94: Calcula a velocidade média do líquido dentro de um tubo circular a partir da vazão e do diâmetro interno. | K94: [Tempo de detenção (TDH)] V (arredondado) | L94: =IFERROR(ROUND($G$137,IF($G$137=0,0,4-INT(LOG10(ABS($G$137))))),"") -> 500
K95: [Tempo de detenção (TDH)] V (texto) | L95: =IF(ISNUMBER($L$94),FIXED($L$94,IF(ROUND($L$94,0)=$L$94,0,IF(ROUND($L$94,1)=$L$94,1,IF(ROUND($L$94,2)=$L$94,2,IF(ROUND($L$94,3)=$L$94,3,IF(ROUND($L$94,4)=$L$94,4,IF(ROUND($L$94,5)=$L$94,5,IF(ROUND($L$94,6)=$L$94,6,7)))))))),"?") -> 500
B96: B · ESCOLHA DO CENÁRIO | K96: [Tempo de detenção (TDH)] Qh (arredondado) | L96: =IFERROR(ROUND($L$82,IF($L$82=0,0,4-INT(LOG10(ABS($L$82))))),"") -> 50
B97: Cenário ▼ | C97: Exemplo 01 | E97: Exemplo 01 e Exemplo 02 usam dados prontos. Meu cálculo usa os valores que você digitar na coluna amarela. | K97: [Tempo de detenção (TDH)] Qh (texto) | L97: =IF(ISNUMBER($L$96),FIXED($L$96,IF(ROUND($L$96,0)=$L$96,0,IF(ROUND($L$96,1)=$L$96,1,IF(ROUND($L$96,2)=$L$96,2,IF(ROUND($L$96,3)=$L$96,3,IF(ROUND($L$96,4)=$L$96,4,IF(ROUND($L$96,5)=$L$96,5,IF(ROUND($L$96,6)=$L$96,6,7)))))))),"?") -> 50
K98: [Tempo de detenção (TDH)] Vm (arredondado) | L98: =IFERROR(ROUND($L$80,IF($L$80=0,0,4-INT(LOG10(ABS($L$80))))),"") -> 500
B99: C · DADOS DE ENTRADA | K99: [Tempo de detenção (TDH)] Vm (texto) | L99: =IF(ISNUMBER($L$98),FIXED($L$98,IF(ROUND($L$98,0)=$L$98,0,IF(ROUND($L$98,1)=$L$98,1,IF(ROUND($L$98,2)=$L$98,2,IF(ROUND($L$98,3)=$L$98,3,IF(ROUND($L$98,4)=$L$98,4,IF(ROUND($L$98,5)=$L$98,5,IF(ROUND($L$98,6)=$L$98,6,7)))))))),"?") -> 500
B100: Variável | C100: Exemplo 01 | D100: Exemplo 02 | E100: MEU CÁLCULO | F100: Unidade | G100: Valor em uso | H100: Orientação de preenchimento | K100: [Tempo de detenção (TDH)] resumo | L100: =IF($L$87,$L$89&" "&"horas","—") -> 10 horas
...

Sheet 03 — Carga Poluidora
B1: 🏭 CALCULADORA 02 · CARGA POLUIDORA | K1: ÁREA TÉCNICA · cálculos auxiliares (não editar)
B2: KIT DE 6 CALCULADORAS AUTOMÁTICAS DE ENGENHARIA AMBIENTAL | K2: Descrição | L2: Valor
B3: 🏠 Painel | C3: 📘 Guia | E3: 📚 Exemplos | G3: ◀ Anterior | H3: Próxima aba ▶ | K3: ferramenta escolhida (número) | L3: =IFERROR(MATCH($C$17,{"Ferramenta 1: Calcular carga","Ferramenta 2: Descobrir concentração","Ferramenta 3: Descobrir vazão"},0),0) -> 1
K4: índice do cenário (1, 2 ou 3) | L4: =IFERROR(MATCH($C$25,{"Exemplo 01","Exemplo 02","Meu cálculo"},0),0) -> 1
B5: COMO USAR: ① Escolha a ferramenta abaixo ② Escolha o cenário na lista amarela ③ Para usar seus dados, escolha Meu cálculo e digite na coluna amarela ④ Veja o resultado no card verde ⑤ Confira a conta em ENTENDA O CÁLCULO | K5: [Calcular carga] fQ | L5: =IFERROR(CHOOSE(MATCH($G$31,{"m³/dia","m³/h","L/s"},0),1,24,86.4),"") -> 1
K6: [Calcular carga] Qd | L6: =IFERROR($G$30*$L$5,"") -> 400
B7: A · IDENTIFICAÇÃO | K7: [Calcular carga] kg | L7: =IFERROR($L$6*$G$32*0.001,"") -> 72
B8: O que calcula | C8: A massa de poluente que uma corrente leva por dia (carga), a partir da vazão e da concentração. Também faz o caminho inverso. | K8: [Calcular carga] g | L8: =IFERROR($L$7*1000,"") -> 72000
B9: Quando usar | C9: Caracterização de efluentes, estudos de impacto em rios, comparação entre fontes, equivalente populacional e relatórios de monitoramento. | K9: [Calcular carga] ano | L9: =IFERROR($L$7*365,"") -> 26280
B10: Exemplo prático | C10: Um efluente de 400 m³/dia com DBO de 180 mg/L lança 72 kg de DBO por dia. | K10: [Calcular carga] hab | L10: =IFERROR(ROUND($L$7*1000/54,0),"") -> 1333
K11: [Calcular carga] mensagem de validação | L11: =IFERROR(IF($L$4=0,"Escolha um cenário na lista: Exemplo 01, Exemplo 02 ou Meu cálculo.",IF($L$5="","Confira a unidade selecionada para a vazão.",IF($G$30="","Informe a vazão para continuar.",IF(NOT(ISNUMBER($G$30)),"A vazão precisa ser um número. Confira o valor digitado.",IF($G$30<=0,"A vazão deve ser maior que zero.",IF($G$32="","Informe a concentração para continuar (digite 0 se for o caso).",IF(NOT(ISNUMBER($G$32)),"A concentração precisa ser um número. Confira o valor digitado.",IF($G$32<0,"A concentração não pode ser negativa.","")))))))),"Resultado indisponível: existem dados inválidos.")
B12: FERRAMENTAS DESTA CALCULADORA | K12: [Calcular carga] dados válidos? | L12: =$L$11="" -> TRUE
B13: ▶ Ferramenta 1 | C13: Calcular carga poluidora: Calcula a massa de poluente transportada por dia a partir da vazão e da concentração. O parâmetro escolhido só identifica o cálculo; a fórmula é a mesma para todos. | K13: [Calcular carga] hab (arredondado) | L13: =IFERROR(ROUND($L$10,IF($L$10=0,0,4-INT(LOG10(ABS($L$10))))),"") -> 1333
B14: ▶ Ferramenta 2 | C14: Descobrir a concentração: Calcula a concentração média de um parâmetro quando você conhece a carga diária e a vazão. | K14: [Calcular carga] hab (texto) | L14: =IF(ISNUMBER($L$13),FIXED($L$13,IF(ROUND($L$13,0)=$L$13,0,IF(ROUND($L$13,1)=$L$13,1,IF(ROUND($L$13,2)=$L$13,2,IF(ROUND($L$13,3)=$L$13,3,IF(ROUND($L$13,4)=$L$13,4,IF(ROUND($L$13,5)=$L$13,5,IF(ROUND($L$13,6)=$L$13,6,7)))))))),"?") -> 1.333
B15: ▶ Ferramenta 3 | C15: Descobrir a vazão: Calcula a vazão que transporta uma carga conhecida com uma concentração conhecida. | K15: [Calcular carga] kg (arredondado) | L15: =IFERROR(ROUND($L$7,IF($L$7=0,0,4-INT(LOG10(ABS($L$7))))),"") -> 72
K16: [Calcular carga] kg (texto) | L16: =IF(ISNUMBER($L$15),FIXED($L$15,IF(ROUND($L$15,0)=$L$15,0,IF(ROUND($L$15,1)=$L$15,1,IF(ROUND($L$15,2)=$L$15,2,IF(ROUND($L$15,3)=$L$15,3,IF(ROUND($L$15,4)=$L$15,4,IF(ROUND($L$15,5)=$L$15,5,IF(ROUND($L$15,6)=$L$15,6,7)))))))),"?") -> 72
B17: Ferramenta escolhida ▼ | C17: Ferramenta 1: Calcular carga | F17: A ferramenta escolhida fica com o título em verde. Use os botões azuis acima para ir até ela. | K17: [Calcular carga] C (arredondado) | L17: =IFERROR(ROUND($G$32,IF($G$32=0,0,4-INT(LOG10(ABS($G$32))))),"") -> 180
B18: Resultado atual | C18: =IFERROR(CHOOSE($L$3,$L$25,$L$42,$L$60),"—") -> 72 kg/dia | K18: [Calcular carga] C (texto) | L18: =IF(ISNUMBER($L$17),FIXED($L$17,IF(ROUND($L$17,0)=$L$17,0,IF(ROUND($L$17,1)=$L$17,1,IF(ROUND($L$17,2)=$L$17,2,IF(ROUND($L$17,3)=$L$17,3,IF(ROUND($L$17,4)=$L$17,4,IF(ROUND($L$17,5)=$L$17,5,IF(ROUND($L$17,6)=$L$17,6,7)))))))),"?") -> 180
B19: Status | C19: =IFERROR(CHOOSE($L$3,C41,C77,C112),"Escolha uma ferramenta.") -> ✔ Dados válidos. Resultado calculado automaticamente. | K19: [Calcular carga] Q (arredondado) | L19: =IFERROR(ROUND($G$30,IF($G$30=0,0,4-INT(LOG10(ABS($G$30))))),"") -> 400
K20: [Calcular carga] Q (texto) | L20: =IF(ISNUMBER($L$19),FIXED($L$19,IF(ROUND($L$19,0)=$L$19,0,IF(ROUND($L$19,1)=$L$19,1,IF(ROUND($L$19,2)=$L$19,2,IF(ROUND($L$19,3)=$L$19,3,IF(ROUND($L$19,4)=$L$19,4,IF(ROUND($L$19,5)=$L$19,5,IF(ROUND($L$19,6)=$L$19,6,7)))))))),"?") -> 400
B21: FERRAMENTA 1 · CALCULAR CARGA POLUIDORA | H21: ▲ Voltar ao topo | K21: [Calcular carga] Qd (arredondado) | L21: =IFERROR(ROUND($L$6,IF($L$6=0,0,4-INT(LOG10(ABS($L$6))))),"") -> 400
B22: Calcula a massa de poluente transportada por dia a partir da vazão e da concentração. O parâmetro escolhido só identifica o cálculo; a fórmula é a mesma para todos. | K22: [Calcular carga] Qd (texto) | L22: =IF(ISNUMBER($L$21),FIXED($L$21,IF(ROUND($L$21,0)=$L$21,0,IF(ROUND($L$21,1)=$L$21,1,IF(ROUND($L$21,2)=$L$21,2,IF(ROUND($L$21,3)=$L$21,3,IF(ROUND($L$21,4)=$L$21,4,IF(ROUND($L$21,5)=$L$21,5,IF(ROUND($L$21,6)=$L$21,6,7)))))))),"?") -> 400
K23: [Calcular carga] g (arredondado) | L23: =IFERROR(ROUND($L$8,IF($L$8=0,0,4-INT(LOG10(ABS($L$8))))),"") -> 72000
B24: B · ESCOLHA DO CENÁRIO | K24: [Calcular carga] g (texto) | L24: =IF(ISNUMBER($L$23),FIXED($L$23,IF(ROUND($L$23,0)=$L$23,0,IF(ROUND($L$23,1)=$L$23,1,IF(ROUND($L$23,2)=$L$23,2,IF(ROUND($L$23,3)=$L$23,3,IF(ROUND($L$23,4)=$L$23,4,IF(ROUND($L$23,5)=$L$23,5,IF(ROUND($L$23,6)=$L$23,6,7)))))))),"?") -> 72.000
B25: Cenário ▼ | C25: Exemplo 01 | E25: Exemplo 01 e Exemplo 02 usam dados prontos. Meu cálculo usa os valores que você digitar na coluna amarela. | K25: [Calcular carga] resumo | L25: =IF($L$12,$L$16&" "&"kg/dia","—") -> 72 kg/dia
K26: índice do cenário (1, 2 ou 3) | L26: =IFERROR(MATCH($C$61,{"Exemplo 01","Exemplo 02","Meu cálculo"},0),0) -> 1
B27: C · DADOS DE ENTRADA | K27: [Descobrir concentração] fQ | L27: =IFERROR(CHOOSE(MATCH($G$68,{"m³/dia","m³/h","L/s"},0),1,24,86.4),"") -> 1
B28: Variável | C28: Exemplo 01 | D28: Exemplo 02 | E28: MEU CÁLCULO | F28: Unidade | G28: Valor em uso | H28: Orientação de preenchimento | K28: [Descobrir concentração] Qd | L28: =IFERROR($G$67*$L$27,"") -> 400
B29: Parâmetro | C29: DBO | D29: SST | E29: DBO | F29: lista ▼ | G29: =IF($L$4=1,C29,IF($L$4=2,D29,IF($L$4=3,IF(E29="","",E29),""))) -> DBO | H29: Escolha o parâmetro (serve para identificar o resultado). | K29: [Descobrir concentração] Lg | L29: =IFERROR($G$66*1000,"") -> 24000
B30: Vazão | C30: 400 | D30: 5 | F30: =$G$31 -> m³/dia | G30: =IF($L$4=1,C30,IF($L$4=2,D30,IF($L$4=3,IF(E30="","",E30),""))) -> 400 | H30: Vazão da corrente. Ex.: 400 | K30: [Descobrir concentração] C | L30: =IFERROR($L$29/$L$28,"") -> 60
B31: Unidade da vazão | C31: m³/dia | D31: L/s | E31: m³/dia | F31: lista ▼ | G31: =IF($L$4=1,C31,IF($L$4=2,D31,IF($L$4=3,IF(E31="","",E31),""))) -> m³/dia | H31: Escolha m³/dia, m³/h ou L/s. | K31: [Descobrir concentração] kgm3 | L31: =IFERROR($L$30/1000,"") -> 0.06
B32: Concentração | C32: 180 | D32: 250 | F32: mg/L | G32: =IF($L$4=1,C32,IF($L$4=2,D32,IF($L$4=3,IF(E32="","",E32),""))) -> 180 | H32: Concentração do parâmetro em mg/L. Ex.: 180 | K32: [Descobrir concentração] mensagem de validação | L32: =IFERROR(IF($L$26=0,"Escolha um cenário na lista: Exemplo 01, Exemplo 02 ou Meu cálculo.",IF($G$66="","Informe a carga para continuar (digite 0 se for o caso).",IF(NOT(ISNUMBER($G$66)),"A carga precisa ser um número. Confira o valor digitado.",IF($G$66<0,"A carga não pode ser negativa.",IF($L$27="","Confira a unidade selecionada para a vazão.",IF($G$67="","Informe a vazão para continuar.",IF(NOT(ISNUMBER($G$67)),"A vazão precisa ser um número. Confira o valor digitado.",IF($G$67<=0,"A vazão deve ser maior que zero.","")))))))),"Resultado indisponível: existem dados inválidos.")
K33: [Descobrir concentração] dados válidos? | L33: =$L$32="" -> TRUE
B34: D · RESULTADO AUTOMÁTICO | K34: [Descobrir concentração] C (arredondado) | L34: =IFERROR(ROUND($L$30,IF($L$30=0,0,4-INT(LOG10(ABS($L$30))))),"") -> 60
B35: ="CARGA DE "&UPPER($G$29) -> CARGA DE DBO | E35: OUTROS RESULTADOS | K35: [Descobrir concentração] C (texto) | L35: =IF(ISNUMBER($L$34),FIXED($L$34,IF(ROUND($L$34,0)=$L$34,0,IF(ROUND($L$34,1)=$L$34,1,IF(ROUND($L$34,2)=$L$34,2,IF(ROUND($L$34,3)=$L$34,3,IF(ROUND($L$34,4)=$L$34,4,IF(ROUND($L$34,5)=$L$34,5,IF(ROUND($L$34,6)=$L$34,6,7)))))))),"?") -> 60
B36: =IF($L$12,$L$7,"—") -> 72 | D36: kg/dia | E36: Carga em g/dia | G36: =IF($L$12,$L$8,"—") -> 72000 | H36: g/dia | K36: [Descobrir concentração] L (arredondado) | L36: =IFERROR(ROUND($G$66,IF($G$66=0,0,4-INT(LOG10(ABS($G$66))))),"") -> 24
E37: Carga anual (365 dias) | G37: =IF($L$12,$L$9,"—") -> 26280 | H37: kg/ano | K37: [Descobrir concentração] L (texto) | L37: =IF(ISNUMBER($L$36),FIXED($L$36,IF(ROUND($L$36,0)=$L$36,0,IF(ROUND($L$36,1)=$L$36,1,IF(ROUND($L$36,2)=$L$36,2,IF(ROUND($L$36,3)=$L$36,3,IF(ROUND($L$36,4)=$L$36,4,IF(ROUND($L$36,5)=$L$36,5,IF(ROUND($L$36,6)=$L$36,6,7)))))))),"?") -> 24
E38: Vazão usada | G38: =IF($L$12,$L$6,"—") -> 400 | H38: m³/dia | K38: [Descobrir concentração] Q (arredondado) | L38: =IFERROR(ROUND($G$67,IF($G$67=0,0,4-INT(LOG10(ABS($G$67))))),"") -> 400
K39: [Descobrir concentração] Q (texto) | L39: =IF(ISNUMBER($L$38),FIXED($L$38,IF(ROUND($L$38,0)=$L$38,0,IF(ROUND($L$38,1)=$L$38,1,IF(ROUND($L$38,2)=$L$38,2,IF(ROUND($L$38,3)=$L$38,3,IF(ROUND($L$38,4)=$L$38,4,IF(ROUND($L$38,5)=$L$38,5,IF(ROUND($L$38,6)=$L$38,6,7)))))))),"?") -> 400
B40: Interpretação | C40: =IF($L$12,"Por dia, a corrente transporta "&$L$16&" kg de "&$G$29&". Essa é a massa que chega ao destino em 24 horas."&IF($G$29="DBO"," Isso equivale ao esgoto de aproximadamente "&$L$14&" pessoas (referência usual de 54 g de DBO por habitante por dia).",""),"Resultado indisponível: corrija o item indicado em Status dos dados.") -> Por dia, a corrente transporta 72 kg de DBO. Essa é a massa que chega ao destino em 24 horas. Isso equivale ao esgoto de aproximadamente 1.333 pessoas (referência usual de 54 g de DBO por habitante por dia). | K40: [Descobrir concentração] Qd (arredondado) | L40: =IFERROR(ROUND($L$28,IF($L$28=0,0,4-INT(LOG10(ABS($L$28))))),"") -> 400
B41: Status dos dados | C41: =IF($L$12,"✔ Dados válidos. Resultado calculado automaticamente.","⚠ "&$L$11) -> ✔ Dados válidos. Resultado calculado automaticamente. | K41: [Descobrir concentração] Qd (texto) | L41: =IF(ISNUMBER($L$40),FIXED($L$40,IF(ROUND($L$40,0)=$L$40,0,IF(ROUND($L$40,1)=$L$40,1,IF(ROUND($L$40,2)=$L$40,2,IF(ROUND($L$40,3)=$L$40,3,IF(ROUND($L$40,4)=$L$40,4,IF(ROUND($L$40,5)=$L$40,5,IF(ROUND($L$40,6)=$L$40,6,7)))))))),"?") -> 400
K42: [Descobrir concentração] resumo | L42: =IF($L$33,$L$35&" "&"mg/L","—") -> 60 mg/L
B43: E · ENTENDA O CÁLCULO | K43: índice do cenário (1, 2 ou 3) | L43: =IFERROR(MATCH($C$97,{"Exemplo 01","Exemplo 02","Meu cálculo"},0),0) -> 1
B44: Fórmula | C44: Carga (kg/dia) = Q (m³/dia) × C (mg/L) × 0,001 | K44: [Descobrir vazão] Lg | L44: =IFERROR($G$102*1000,"") -> 72000
B45: O que é cada variável | C45: Q = vazão em m³/dia | C = concentração em mg/L | 0,001 = converte g em kg (1 mg/L = 1 g/m³) | K45: [Descobrir vazão] Qd | L45: =IFERROR($L$44/$G$103,"") -> 400
B46: Valores inseridos | C46: ="Parâmetro: "&$G$29&" | "&"Q = "&$L$20&" "&$G$31&" | "&"C = "&$L$18&" "&"mg/L" -> Parâmetro: DBO | Q = 400 m³/dia | C = 180 mg/L | K46: [Descobrir vazão] Qh | L46: =IFERROR($L$45/24,"") -> 16.666667
B47: Substituição | C47: =IF($L$12,"Carga = "&$L$22&" m³/dia × "&$L$18&" mg/L × 0,001 = "&$L$16&" kg/dia","Aguardando dados válidos para montar a conta.") -> Carga = 400 m³/dia × 180 mg/L × 0,001 = 72 kg/dia | K47: [Descobrir vazão] Qls | L47: =IFERROR($L$45/86.4,"") -> 4.6296296
B48: Resultado | C48: =IF($L$12,"Carga de "&$G$29&" = "&$L$16&" kg/dia = "&$L$24&" g/dia","Aguardando dados válidos para montar a conta.") -> Carga de DBO = 72 kg/dia = 72.000 g/dia | K48: [Descobrir vazão] mensagem de validação | L48: =IFERROR(IF($L$43=0,"Escolha um cenário na lista: Exemplo 01, Exemplo 02 ou Meu cálculo.",IF($G$102="","Informe a carga para continuar (digite 0 se for o caso).",IF(NOT(ISNUMBER($G$102)),"A carga precisa ser um número. Confira o valor digitado.",IF($G$102<0,"A carga não pode ser negativa.",IF($G$103="","Informe a concentração para continuar.",IF(NOT(ISNUMBER($G$103)),"A concentração precisa ser um número. Confira o valor digitado.",IF($G$103<=0,"A concentração deve ser maior que zero.",""))))))),"Resultado indisponível: existem dados inválidos.")
K49: [Descobrir vazão] dados válidos? | L49: =$L$48="" -> TRUE
B50: F · EXEMPLO E ORIENTAÇÃO | K50: [Descobrir vazão] C (arredondado) | L50: =IFERROR(ROUND($G$103,IF($G$103=0,0,4-INT(LOG10(ABS($G$103))))),"") -> 180
B51: Exemplos desta ferramenta | C51: Exemplo 01: Uma indústria lança 400 m³/dia de efluente com DBO de 180 mg/L. Qual é a carga de DBO? Exemplo 02: Um efluente com vazão de 5 L/s tem 250 mg/L de SST. Qual é a carga diária de sólidos? Escolha o exemplo na lista Cenário para ver a resolução completa. | K51: [Descobrir vazão] C (texto) | L51: =IF(ISNUMBER($L$50),FIXED($L$50,IF(ROUND($L$50,0)=$L$50,0,IF(ROUND($L$50,1)=$L$50,1,IF(ROUND($L$50,2)=$L$50,2,IF(ROUND($L$50,3)=$L$50,3,IF(ROUND($L$50,4)=$L$50,4,IF(ROUND($L$50,5)=$L$50,5,IF(ROUND($L$50,6)=$L$50,6,7)))))))),"?") -> 180
B52: Como interpretar | C52: A carga mostra a massa total lançada. Duas correntes com a mesma concentração podem ter cargas muito diferentes se as vazões forem diferentes. | K52: [Descobrir vazão] L (arredondado) | L52: =IFERROR(ROUND($G$102,IF($G$102=0,0,4-INT(LOG10(ABS($G$102))))),"") -> 72
B53: ⚠ Erro comum | C53: Usar a vazão em L/s ou m³/h direto na fórmula. Ela precisa estar em m³/dia. A calculadora converte para você quando você escolhe a unidade. | K53: [Descobrir vazão] L (texto) | L53: =IF(ISNUMBER($L$52),FIXED($L$52,IF(ROUND($L$52,0)=$L$52,0,IF(ROUND($L$52,1)=$L$52,1,IF(ROUND($L$52,2)=$L$52,2,IF(ROUND($L$52,3)=$L$52,3,IF(ROUND($L$52,4)=$L$52,4,IF(ROUND($L$52,5)=$L$52,5,IF(ROUND($L$52,6)=$L$52,6,7)))))))),"?") -> 72
B54: 💡 Dica prática | C54: Entenda o 0,001: 1 mg/L é igual a 1 g/m³. Então m³/dia × g/m³ dá g/dia, e multiplicar por 0,001 dá kg/dia. | K54: [Descobrir vazão] Qd (arredondado) | L54: =IFERROR(ROUND($L$45,IF($L$45=0,0,4-INT(LOG10(ABS($L$45))))),"") -> 400
K55: [Descobrir vazão] Qd (texto) | L55: =IF(ISNUMBER($L$54),FIXED($L$54,IF(ROUND($L$54,0)=$L$54,0,IF(ROUND($L$54,1)=$L$54,1,IF(ROUND($L$54,2)=$L$54,2,IF(ROUND($L$54,3)=$L$54,3,IF(ROUND($L$54,4)=$L$54,4,IF(ROUND($L$54,5)=$L$54,5,IF(ROUND($L$54,6)=$L$54,6,7)))))))),"?") -> 400
K56: [Descobrir vazão] Qls (arredondado) | L56: =IFERROR(ROUND($L$47,IF($L$47=0,0,4-INT(LOG10(ABS($L$47))))),"") -> 4.6296
B57: FERRAMENTA 2 · DESCOBRIR A CONCENTRAÇÃO | H57: ▲ Voltar ao topo | K57: [Descobrir vazão] Qls (texto) | L57: =IF(ISNUMBER($L$56),FIXED($L$56,IF(ROUND($L$56,0)=$L$56,0,IF(ROUND($L$56,1)=$L$56,1,IF(ROUND($L$56,2)=$L$56,2,IF(ROUND($L$56,3)=$L$56,3,IF(ROUND($L$56,4)=$L$56,4,IF(ROUND($L$56,5)=$L$56,5,IF(ROUND($L$56,6)=$L$56,6,7)))))))),"?") -> 4,6296
B58: Calcula a concentração média de um parâmetro quando você conhece a carga diária e a vazão. | K58: [Descobrir vazão] Qh (arredondado) | L58: =IFERROR(ROUND($L$46,IF($L$46=0,0,4-INT(LOG10(ABS($L$46))))),"") -> 16.667
K59: [Descobrir vazão] Qh (texto) | L59: =IF(ISNUMBER($L$58),FIXED($L$58,IF(ROUND($L$58,0)=$L$58,0,IF(ROUND($L$58,1)=$L$58,1,IF(ROUND($L$58,2)=$L$58,2,IF(ROUND($L$58,3)=$L$58,3,IF(ROUND($L$58,4)=$L$58,4,IF(ROUND($L$58,5)=$L$58,5,IF(ROUND($L$58,6)=$L$58,6,7)))))))),"?") -> 16,667
B60: B · ESCOLHA DO CENÁRIO | K60: [Descobrir vazão] resumo | L60: =IF($L$49,$L$55&" "&"m³/dia","—") -> 400 m³/dia
B61: Cenário ▼ | C61: Exemplo 01 | E61: Exemplo 01 e Exemplo 02 usam dados prontos. Meu cálculo usa os valores que você digitar na coluna amarela.
B63: C · DADOS DE ENTRADA
B64: Variável | C64: Exemplo 01 | D64: Exemplo 02 | E64: MEU CÁLCULO | F64: Unidade | G64: Valor em uso | H64: Orientação de preenchimento
B65: Parâmetro | C65: DBO | D65: DQO | E65: DBO | F65: lista ▼ | G65: =IF($L$26=1,C65,IF($L$26=2,D65,IF($L$26=3,IF(E65="","",E65),""))) -> DBO | H65: Escolha o parâmetro (serve para identificar o resultado).
B66: Carga | C66: 24 | D66: 150 | F66: kg/dia | G66: =IF($L$26=1,C66,IF($L$26=2,D66,IF($L$26=3,IF(E66="","",E66),""))) -> 24 | H66: Carga do parâmetro em kg/dia. Ex.: 24
B67: Vazão | C67: 400 | D67: 50 | F67: =$G$68 -> m³/dia | G67: =IF($L$26=1,C67,IF($L$26=2,D67,IF($L$26=3,IF(E67="","",E67),""))) -> 400 | H67: Vazão da corrente. Ex.: 400
B68: Unidade da vazão | C68: m³/dia | D68: m³/h | E68: m³/dia | F68: lista ▼ | G68: =IF($L$26=1,C68,IF($L$26=2,D68,IF($L$26=3,IF(E68="","",E68),""))) -> m³/dia | H68: Escolha m³/dia, m³/h ou L/s.
B70: D · RESULTADO AUTOMÁTICO
B71: ="CONCENTRAÇÃO DE "&UPPER($G$65) -> CONCENTRAÇÃO DE DBO | E71: OUTROS RESULTADOS
B72: =IF($L$33,$L$30,"—") -> 60 | D72: mg/L | E72: Mesmo valor em g/m³ | G72: =IF($L$33,$L$30,"—") -> 60 | H72: g/m³
E73: Em kg/m³ | G73: =IF($L$33,$L$31,"—") -> 0.06 | H73: kg/m³
E74: Vazão usada | G74: =IF($L$33,$L$28,"—") -> 400 | H74: m³/dia
B76: Interpretação | C76: =IF($L$33,"Cada litro do efluente carrega, em média, "&$L$35&" mg de "&$G$65&". É o mesmo que "&$L$35&" g em cada m³.","Resultado indisponível: corrija o item indicado em Status dos dados.") -> Cada litro do efluente carrega, em média, 60 mg de DBO. É o mesmo que 60 g em cada m³.
B77: Status dos dados | C77: =IF($L$33,"✔ Dados válidos. Resultado calculado automaticamente.","⚠ "&$L$32) -> ✔ Dados válidos. Resultado calculado automaticamente.
B79: E · ENTENDA O CÁLCULO
B80: Fórmula | C80: C (mg/L) = Carga (kg/dia) × 1000 ÷ Q (m³/dia)
B81: O que é cada variável | C81: C = concentração | Carga = massa por dia | Q = vazão em m³/dia | 1000 = converte kg em g
B82: Valores inseridos | C82: ="Parâmetro: "&$G$65&" | "&"Carga = "&$L$37&" "&"kg/dia"&" | "&"Q = "&$L$39&" "&$G$68 -> Parâmetro: DBO | Carga = 24 kg/dia | Q = 400 m³/dia
B83: Substituição | C83: =IF($L$33,"C = "&$L$37&" kg/dia × 1000 ÷ "&$L$41&" m³/dia = "&$L$35&" mg/L","Aguardando dados válidos para montar a conta.") -> C = 24 kg/dia × 1000 ÷ 400 m³/dia = 60 mg/L
B84: Resultado | C84: =IF($L$33,"C = "&$L$35&" mg/L","Aguardando dados válidos para montar a conta.") -> C = 60 mg/L
B86: F · EXEMPLO E ORIENTAÇÃO
B87: Exemplos desta ferramenta | C87: Exemplo 01: Um efluente tratado sai com carga de 24 kg/dia de DBO e vazão de 400 m³/dia. Qual é a concentração de DBO? Exemplo 02: Uma lavanderia gera 150 kg/dia de DQO com vazão de 50 m³/h. Qual é a concentração média de DQO? Escolha o exemplo na lista Cenário para ver a resolução completa.
B88: Como interpretar | C88: A concentração diz o quanto cada litro está carregado. Compare com o padrão de lançamento aplicável ao seu caso.
B89: ⚠ Erro comum | C89: Esquecer o fator 1000. Sem ele a resposta sai mil vezes menor (em kg/m³).
B90: 💡 Dica prática | C90: Use esta ferramenta para conferir se uma carga informada em relatório é coerente com a vazão e a concentração medidas.
B93: FERRAMENTA 3 · DESCOBRIR A VAZÃO | H93: ▲ Voltar ao topo
B94: Calcula a vazão que transporta uma carga conhecida com uma concentração conhecida.
B96: B · ESCOLHA DO CENÁRIO
B97: Cenário ▼ | C97: Exemplo 01 | E97: Exemplo 01 e Exemplo 02 usam dados prontos. Meu cálculo usa os valores que você digitar na coluna amarela.
B99: C · DADOS DE ENTRADA
B100: Variável | C100: Exemplo 01 | D100: Exemplo 02 | E100: MEU CÁLCULO | F100: Unidade | G100: Valor em uso | H100: Orientação de preenchimento
B101: Parâmetro | C101: DBO | D101: Fósforo total | E101: DBO | F101: lista ▼ | G101: =IF($L$43=1,C101,IF($L$43=2,D101,IF($L$43=3,IF(E101="","",E101),""))) -> DBO | H101: Escolha o parâmetro (serve para identificar o resultado).
B102: Carga | C102: 72 | D102: 6 | F102: kg/dia | G102: =IF($L$43=1,C102,IF($L$43=2,D102,IF($L$43=3,IF(E102="","",E102),""))) -> 72 | H102: Carga do parâmetro em kg/dia. Ex.: 72
B103: Concentração | C103: 180 | D103: 8 | F103: mg/L | G103: =IF($L$43=1,C103,IF($L$43=2,D103,IF($L$43=3,IF(E103="","",E103),""))) -> 180 | H103: Concentração do parâmetro em mg/L. Ex.: 180
B105: D · RESULTADO AUTOMÁTICO
B106: VAZÃO | E106: OUTROS RESULTADOS
B107: =IF($L$49,$L$45,"—") -> 400 | D107: m³/dia | E107: Vazão em m³/h | G107: =IF($L$49,$L$46,"—") -> 16.666667 | H107: m³/h
E108: Vazão em L/s | G108: =IF($L$49,$L$47,"—") -> 4.6296296 | H108: L/s
B111: Interpretação | C111: =IF($L$49,"Significado físico: para levar "&$L$53&" kg/dia de "&$G$101&" com "&$L$51&" mg/L, precisam passar "&$L$55&" m³ de líquido por dia, cerca de "&$L$57&" litros a cada segundo.","Resultado indisponível: corrija o item indicado em Status dos dados.") -> Significado físico: para levar 72 kg/dia de DBO com 180 mg/L, precisam passar 400 m³ de líquido por dia, cerca de 4,6296 litros a cada segundo.
B112: Status dos dados | C112: =IF($L$49,"✔ Dados válidos. Resultado calculado automaticamente.","⚠ "&$L$48) -> ✔ Dados válidos. Resultado calculado automaticamente.
...

Sheet 04 — Eficiência de Tratamento
B1: 📉 CALCULADORA 03 · EFICIÊNCIA DE TRATAMENTO | K1: ÁREA TÉCNICA · cálculos auxiliares (não editar)
B2: KIT DE 6 CALCULADORAS AUTOMÁTICAS DE ENGENHARIA AMBIENTAL | K2: Descrição | L2: Valor
B3: 🏠 Painel | C3: 📘 Guia | E3: 📚 Exemplos | G3: ◀ Anterior | H3: Próxima aba ▶ | K3: ferramenta escolhida (número) | L3: =IFERROR(MATCH($C$16,{"Ferramenta 1: Eficiência por concentração","Ferramenta 2: Eficiência por carga"},0),0) -> 1
K4: índice do cenário (1, 2 ou 3) | L4: =IFERROR(MATCH($C$24,{"Exemplo 01","Exemplo 02","Meu cálculo"},0),0) -> 1
B5: COMO USAR: ① Escolha a ferramenta abaixo ② Escolha o cenário na lista amarela ③ Para usar seus dados, escolha Meu cálculo e digite na coluna amarela ④ Veja o resultado no card verde ⑤ Confira a conta em ENTENDA O CÁLCULO | K5: [Eficiência por concentração] dif | L5: =IFERROR($G$29-$G$30,"") -> 200
K6: [Eficiência por concentração] E | L6: =IFERROR($L$5/$G$29*100,"") -> 80
B7: A · IDENTIFICAÇÃO | K7: [Eficiência por concentração] Efr | L7: =IFERROR($L$5/$G$29,"") -> 0.8
B8: O que calcula | C8: Quanto do poluente foi removido em um sistema de tratamento, em porcentagem, usando concentrações ou cargas. | K8: [Eficiência por concentração] negE | L8: =IFERROR(-$L$6,"") -> -80
B9: Quando usar | C9: Avaliação de ETEs, reatores, decantadores, filtros e lagoas; relatórios de monitoramento e aulas práticas. | K9: [Eficiência por concentração] rem | L9: =IFERROR($G$30/$G$29*100,"") -> 20
B10: Exemplo prático | C10: DBO de 250 mg/L na entrada e 50 mg/L na saída: eficiência de 80%. | K10: [Eficiência por concentração] mensagem de validação | L10: =IFERROR(IF($L$4=0,"Escolha um cenário na lista: Exemplo 01, Exemplo 02 ou Meu cálculo.",IF($G$29="","Informe a concentração de entrada para continuar.",IF(NOT(ISNUMBER($G$29)),"A concentração de entrada precisa ser um número. Confira o valor digitado.",IF($G$29<=0,"A concentração de entrada deve ser maior que zero.",IF($G$30="","Informe a concentração de saída para continuar (digite 0 se for o caso).",IF(NOT(ISNUMBER($G$30)),"A concentração de saída precisa ser um número. Confira o valor digitado.",IF($G$30<0,"A concentração de saída não pode ser negativa.",""))))))),"Resultado indisponível: existem dados inválidos.")
K11: [Eficiência por concentração] dados válidos? | L11: =$L$10="" -> TRUE
B12: FERRAMENTAS DESTA CALCULADORA | K12: [Eficiência por concentração] E (arredondado) | L12: =IFERROR(ROUND($L$6,IF($L$6=0,0,4-INT(LOG10(ABS($L$6))))),"") -> 80
B13: ▶ Ferramenta 1 | C13: Eficiência por concentração: Calcula a porcentagem de redução entre a concentração de entrada e a de saída de um sistema de tratamento. | K13: [Eficiência por concentração] E (texto) | L13: =IF(ISNUMBER($L$12),FIXED($L$12,IF(ROUND($L$12,0)=$L$12,0,IF(ROUND($L$12,1)=$L$12,1,IF(ROUND($L$12,2)=$L$12,2,IF(ROUND($L$12,3)=$L$12,3,IF(ROUND($L$12,4)=$L$12,4,IF(ROUND($L$12,5)=$L$12,5,IF(ROUND($L$12,6)=$L$12,6,7)))))))),"?") -> 80
B14: ▶ Ferramenta 2 | C14: Eficiência por carga: Calcula a remoção de massa poluidora. Use quando as vazões de entrada e de saída forem diferentes. | K14: [Eficiência por concentração] negE (arredondado) | L14: =IFERROR(ROUND($L$8,IF($L$8=0,0,4-INT(LOG10(ABS($L$8))))),"") -> -80
K15: [Eficiência por concentração] negE (texto) | L15: =IF(ISNUMBER($L$14),FIXED($L$14,IF(ROUND($L$14,0)=$L$14,0,IF(ROUND($L$14,1)=$L$14,1,IF(ROUND($L$14,2)=$L$14,2,IF(ROUND($L$14,3)=$L$14,3,IF(ROUND($L$14,4)=$L$14,4,IF(ROUND($L$14,5)=$L$14,5,IF(ROUND($L$14,6)=$L$14,6,7)))))))),"?") -> -80
B16: Ferramenta escolhida ▼ | C16: Ferramenta 1: Eficiência por concentração | F16: A ferramenta escolhida fica com o título em verde. Use os botões azuis acima para ir até ela. | K16: [Eficiência por concentração] Ce (arredondado) | L16: =IFERROR(ROUND($G$29,IF($G$29=0,0,4-INT(LOG10(ABS($G$29))))),"") -> 250
B17: Resultado atual | C17: =IFERROR(CHOOSE($L$3,$L$22,$L$50),"—") -> 80 % | K17: [Eficiência por concentração] Ce (texto) | L17: =IF(ISNUMBER($L$16),FIXED($L$16,IF(ROUND($L$16,0)=$L$16,0,IF(ROUND($L$16,1)=$L$16,1,IF(ROUND($L$16,2)=$L$16,2,IF(ROUND($L$16,3)=$L$16,3,IF(ROUND($L$16,4)=$L$16,4,IF(ROUND($L$16,5)=$L$16,5,IF(ROUND($L$16,6)=$L$16,6,7)))))))),"?") -> 250
B18: Status | C18: =IFERROR(CHOOSE($L$3,C39,C93),"Escolha uma ferramenta.") -> ✔ Dados válidos. Resultado calculado automaticamente. | K18: [Eficiência por concentração] Cs (arredondado) | L18: =IFERROR(ROUND($G$30,IF($G$30=0,0,4-INT(LOG10(ABS($G$30))))),"") -> 50
K19: [Eficiência por concentração] Cs (texto) | L19: =IF(ISNUMBER($L$18),FIXED($L$18,IF(ROUND($L$18,0)=$L$18,0,IF(ROUND($L$18,1)=$L$18,1,IF(ROUND($L$18,2)=$L$18,2,IF(ROUND($L$18,3)=$L$18,3,IF(ROUND($L$18,4)=$L$18,4,IF(ROUND($L$18,5)=$L$18,5,IF(ROUND($L$18,6)=$L$18,6,7)))))))),"?") -> 50
B20: FERRAMENTA 1 · EFICIÊNCIA POR CONCENTRAÇÃO | H20: ▲ Voltar ao topo | K20: [Eficiência por concentração] dif (arredondado) | L20: =IFERROR(ROUND($L$5,IF($L$5=0,0,4-INT(LOG10(ABS($L$5))))),"") -> 200
B21: Calcula a porcentagem de redução entre a concentração de entrada e a de saída de um sistema de tratamento. | K21: [Eficiência por concentração] dif (texto) | L21: =IF(ISNUMBER($L$20),FIXED($L$20,IF(ROUND($L$20,0)=$L$20,0,IF(ROUND($L$20,1)=$L$20,1,IF(ROUND($L$20,2)=$L$20,2,IF(ROUND($L$20,3)=$L$20,3,IF(ROUND($L$20,4)=$L$20,4,IF(ROUND($L$20,5)=$L$20,5,IF(ROUND($L$20,6)=$L$20,6,7)))))))),"?") -> 200
K22: [Eficiência por concentração] resumo | L22: =IF($L$11,$L$13&" "&"%","—") -> 80 %
B23: B · ESCOLHA DO CENÁRIO | K23: índice do cenário (1, 2 ou 3) | L23: =IFERROR(MATCH($C$76,{"Exemplo 01","Exemplo 02","Meu cálculo"},0),0) -> 1
B24: Cenário ▼ | C24: Exemplo 01 | E24: Exemplo 01 e Exemplo 02 usam dados prontos. Meu cálculo usa os valores que você digitar na coluna amarela. | K24: [Eficiência por carga] Le | L24: =IFERROR($G$81*$G$82*0.001,"") -> 100
K25: [Eficiência por carga] Ls | L25: =IFERROR($G$83*$G$84*0.001,"") -> 20
B26: C · DADOS DE ENTRADA | K26: [Eficiência por carga] Lr | L26: =IFERROR($L$24-$L$25,"") -> 80
B27: Variável | C27: Exemplo 01 | D27: Exemplo 02 | E27: MEU CÁLCULO | F27: Unidade | G27: Valor em uso | H27: Orientação de preenchimento | K27: [Eficiência por carga] E | L27: =IFERROR($L$26/$L$24*100,"") -> 80
B28: Parâmetro | C28: DBO | D28: DQO | E28: DBO | F28: lista ▼ | G28: =IF($L$4=1,C28,IF($L$4=2,D28,IF($L$4=3,IF(E28="","",E28),""))) -> DBO | H28: Escolha o parâmetro avaliado. | K28: [Eficiência por carga] negE | L28: =IFERROR(-$L$27,"") -> -80
B29: Concentração de entrada | C29: 250 | D29: 600 | F29: mg/L | G29: =IF($L$4=1,C29,IF($L$4=2,D29,IF($L$4=3,IF(E29="","",E29),""))) -> 250 | H29: Concentração antes do tratamento. Ex.: 250 | K29: [Eficiência por carga] Ec | L29: =IFERROR(($G$82-$G$84)/$G$82*100,"") -> 75
B30: Concentração de saída | C30: 50 | D30: 180 | F30: mg/L | G30: =IF($L$4=1,C30,IF($L$4=2,D30,IF($L$4=3,IF(E30="","",E30),""))) -> 50 | H30: Concentração depois do tratamento. Ex.: 50 | K30: [Eficiência por carga] mensagem de validação | L30: =IFERROR(IF($L$23=0,"Escolha um cenário na lista: Exemplo 01, Exemplo 02 ou Meu cálculo.",IF($G$81="","Informe a vazão de entrada para continuar.",IF(NOT(ISNUMBER($G$81)),"A vazão de entrada precisa ser um número. Confira o valor digitado.",IF($G$81<=0,"A vazão de entrada deve ser maior que zero.",IF($G$82="","Informe a concentração de entrada para continuar.",IF(NOT(ISNUMBER($G$82)),"A concentração de entrada precisa ser um número. Confira o valor digitado.",IF($G$82<=0,"A concentração de entrada deve ser maior que zero.",IF($G$83="","Informe a vazão de saída para continuar (digite 0 se for o caso).",IF(NOT(ISNUMBER($G$83)),"A vazão de saída precisa ser um número. Confira o valor digitado.",IF($G$83<0,"A vazão de saída não pode ser negativa.",IF($G$84="","Informe a concentração de saída para continuar (digite 0 se for o caso).",IF(NOT(ISNUMBER($G$84)),"A concentração de saída precisa ser um número. Confira o valor digitado.",IF($G$84<0,"A concentração de saída não pode ser negativa.",""))))))))))))),"Resultado indisponível: existem dados inválidos.")
K31: [Eficiência por carga] dados válidos? | L31: =$L$30="" -> TRUE
B32: D · RESULTADO AUTOMÁTICO | K32: [Eficiência por carga] E (arredondado) | L32: =IFERROR(ROUND($L$27,IF($L$27=0,0,4-INT(LOG10(ABS($L$27))))),"") -> 80
B33: EFICIÊNCIA DE REMOÇÃO | E33: OUTROS RESULTADOS | K33: [Eficiência por carga] E (texto) | L33: =IF(ISNUMBER($L$32),FIXED($L$32,IF(ROUND($L$32,0)=$L$32,0,IF(ROUND($L$32,1)=$L$32,1,IF(ROUND($L$32,2)=$L$32,2,IF(ROUND($L$32,3)=$L$32,3,IF(ROUND($L$32,4)=$L$32,4,IF(ROUND($L$32,5)=$L$32,5,IF(ROUND($L$32,6)=$L$32,6,7)))))))),"?") -> 80
B34: =IF($L$11,$L$6,"—") -> 80 | D34: % | E34: Diferença (entrada − saída) | G34: =IF($L$11,$L$5,"—") -> 200 | H34: mg/L | K34: [Eficiência por carga] Ec (arredondado) | L34: =IFERROR(ROUND($L$29,IF($L$29=0,0,4-INT(LOG10(ABS($L$29))))),"") -> 75
E35: Parcela que permanece | G35: =IF($L$11,$L$9,"—") -> 20 | H35: % | K35: [Eficiência por carga] Ec (texto) | L35: =IF(ISNUMBER($L$34),FIXED($L$34,IF(ROUND($L$34,0)=$L$34,0,IF(ROUND($L$34,1)=$L$34,1,IF(ROUND($L$34,2)=$L$34,2,IF(ROUND($L$34,3)=$L$34,3,IF(ROUND($L$34,4)=$L$34,4,IF(ROUND($L$34,5)=$L$34,5,IF(ROUND($L$34,6)=$L$34,6,7)))))))),"?") -> 75
K36: [Eficiência por carga] negE (arredondado) | L36: =IFERROR(ROUND($L$28,IF($L$28=0,0,4-INT(LOG10(ABS($L$28))))),"") -> -80
K37: [Eficiência por carga] negE (texto) | L37: =IF(ISNUMBER($L$36),FIXED($L$36,IF(ROUND($L$36,0)=$L$36,0,IF(ROUND($L$36,1)=$L$36,1,IF(ROUND($L$36,2)=$L$36,2,IF(ROUND($L$36,3)=$L$36,3,IF(ROUND($L$36,4)=$L$36,4,IF(ROUND($L$36,5)=$L$36,5,IF(ROUND($L$36,6)=$L$36,6,7)))))))),"?") -> -80
B38: Interpretação | C38: =IF($L$11,IF($L$6>0,"Houve redução de "&$G$28&": o sistema removeu "&$L$13&"% da concentração de entrada.",IF($L$6=0,"Não houve redução: o valor de saída é igual ao de entrada.","Houve aumento de "&$G$28&": a saída ficou "&$L$15&"% acima da entrada. Confira os dados e o funcionamento do sistema.")),"Resultado indisponível: corrija o item indicado em Status dos dados.") -> Houve redução de DBO: o sistema removeu 80% da concentração de entrada. | K38: [Eficiência por carga] Ce (arredondado) | L38: =IFERROR(ROUND($G$82,IF($G$82=0,0,4-INT(LOG10(ABS($G$82))))),"") -> 200
B39: Status dos dados | C39: =IF($L$11,"✔ Dados válidos. Resultado calculado automaticamente.","⚠ "&$L$10) -> ✔ Dados válidos. Resultado calculado automaticamente. | K39: [Eficiência por carga] Ce (texto) | L39: =IF(ISNUMBER($L$38),FIXED($L$38,IF(ROUND($L$38,0)=$L$38,0,IF(ROUND($L$38,1)=$L$38,1,IF(ROUND($L$38,2)=$L$38,2,IF(ROUND($L$38,3)=$L$38,3,IF(ROUND($L$38,4)=$L$38,4,IF(ROUND($L$38,5)=$L$38,5,IF(ROUND($L$38,6)=$L$38,6,7)))))))),"?") -> 200
K40: [Eficiência por carga] Cs (arredondado) | L40: =IFERROR(ROUND($G$84,IF($G$84=0,0,4-INT(LOG10(ABS($G$84))))),"") -> 50
B41: E · ENTENDA O CÁLCULO | K41: [Eficiência por carga] Cs (texto) | L41: =IF(ISNUMBER($L$40),FIXED($L$40,IF(ROUND($L$40,0)=$L$40,0,IF(ROUND($L$40,1)=$L$40,1,IF(ROUND($L$40,2)=$L$40,2,IF(ROUND($L$40,3)=$L$40,3,IF(ROUND($L$40,4)=$L$40,4,IF(ROUND($L$40,5)=$L$40,5,IF(ROUND($L$40,6)=$L$40,6,7)))))))),"?") -> 50
B42: Fórmula | C42: Eficiência (%) = (Ce − Cs) ÷ Ce × 100 | K42: [Eficiência por carga] Qe (arredondado) | L42: =IFERROR(ROUND($G$81,IF($G$81=0,0,4-INT(LOG10(ABS($G$81))))),"") -> 500
B43: O que é cada variável | C43: Ce = concentração de entrada | Cs = concentração de saída | a divisão é sempre pela entrada | K43: [Eficiência por carga] Qe (texto) | L43: =IF(ISNUMBER($L$42),FIXED($L$42,IF(ROUND($L$42,0)=$L$42,0,IF(ROUND($L$42,1)=$L$42,1,IF(ROUND($L$42,2)=$L$42,2,IF(ROUND($L$42,3)=$L$42,3,IF(ROUND($L$42,4)=$L$42,4,IF(ROUND($L$42,5)=$L$42,5,IF(ROUND($L$42,6)=$L$42,6,7)))))))),"?") -> 500
B44: Valores inseridos | C44: ="Parâmetro: "&$G$28&" | "&"Ce = "&$L$17&" "&"mg/L"&" | "&"Cs = "&$L$19&" "&"mg/L" -> Parâmetro: DBO | Ce = 250 mg/L | Cs = 50 mg/L | K44: [Eficiência por carga] Qs (arredondado) | L44: =IFERROR(ROUND($G$83,IF($G$83=0,0,4-INT(LOG10(ABS($G$83))))),"") -> 400
B45: Substituição | C45: =IF($L$11,"E = ("&$L$17&" − "&$L$19&") ÷ "&$L$17&" × 100 = "&$L$21&" ÷ "&$L$17&" × 100 = "&$L$13&"%","Aguardando dados válidos para montar a conta.") -> E = (250 − 50) ÷ 250 × 100 = 200 ÷ 250 × 100 = 80% | K45: [Eficiência por carga] Qs (texto) | L45: =IF(ISNUMBER($L$44),FIXED($L$44,IF(ROUND($L$44,0)=$L$44,0,IF(ROUND($L$44,1)=$L$44,1,IF(ROUND($L$44,2)=$L$44,2,IF(ROUND($L$44,3)=$L$44,3,IF(ROUND($L$44,4)=$L$44,4,IF(ROUND($L$44,5)=$L$44,5,IF(ROUND($L$44,6)=$L$44,6,7)))))))),"?") -> 400
B46: Resultado | C46: =IF($L$11,"Eficiência = "&$L$13&"% | Diferença = "&$L$21&" mg/L","Aguardando dados válidos para montar a conta.") -> Eficiência = 80% | Diferença = 200 mg/L | K46: [Eficiência por carga] Le (arredondado) | L46: =IFERROR(ROUND($L$24,IF($L$24=0,0,4-INT(LOG10(ABS($L$24))))),"") -> 100
K47: [Eficiência por carga] Le (texto) | L47: =IF(ISNUMBER($L$46),FIXED($L$46,IF(ROUND($L$46,0)=$L$46,0,IF(ROUND($L$46,1)=$L$46,1,IF(ROUND($L$46,2)=$L$46,2,IF(ROUND($L$46,3)=$L$46,3,IF(ROUND($L$46,4)=$L$46,4,IF(ROUND($L$46,5)=$L$46,5,IF(ROUND($L$46,6)=$L$46,6,7)))))))),"?") -> 100
B48: G · COMPARAÇÃO VISUAL | K48: [Eficiência por carga] Ls (arredondado) | L48: =IFERROR(ROUND($L$25,IF($L$25=0,0,4-INT(LOG10(ABS($L$25))))),"") -> 20
E49: Dados do gráfico (atualizam sozinhos) | K49: [Eficiência por carga] Ls (texto) | L49: =IF(ISNUMBER($L$48),FIXED($L$48,IF(ROUND($L$48,0)=$L$48,0,IF(ROUND($L$48,1)=$L$48,1,IF(ROUND($L$48,2)=$L$48,2,IF(ROUND($L$48,3)=$L$48,3,IF(ROUND($L$48,4)=$L$48,4,IF(ROUND($L$48,5)=$L$48,5,IF(ROUND($L$48,6)=$L$48,6,7)))))))),"?") -> 20
E50: Entrada | G50: =IF($L$11,$G$29,"") -> 250 | H50: mg/L | K50: [Eficiência por carga] resumo | L50: =IF($L$31,$L$33&" "&"%","—") -> 80 %
E51: Saída | G51: =IF($L$11,$G$30,"") -> 50 | H51: mg/L
E53: O gráfico usa os mesmos resultados do card verde. Mude um dado e veja as barras mudarem.
B64: F · EXEMPLO E ORIENTAÇÃO
B65: Exemplos desta ferramenta | C65: Exemplo 01: Uma ETE recebe esgoto com DBO de 250 mg/L e o efluente tratado sai com 50 mg/L. Qual é a eficiência de remoção? Exemplo 02: Um reator anaeróbio recebe DQO de 600 mg/L e libera 180 mg/L. Qual é a eficiência? Escolha o exemplo na lista Cenário para ver a resolução completa.
B66: Como interpretar | C66: 80% de eficiência significa que, de cada 100 mg que entram, 80 mg são removidos e 20 mg saem.
B67: ⚠ Erro comum | C67: Dividir pela concentração de saída. A divisão é sempre pela concentração de entrada.
B68: 💡 Dica prática | C68: Se as vazões de entrada e saída forem diferentes (perdas, evaporação, retirada de lodo), use a Ferramenta 2, que trabalha com carga.
B69: Atenção | C69: A calculadora não classifica o resultado como bom ou ruim e não verifica normas. Para isso, compare com o padrão aplicável ao parâmetro e ao seu caso.
B72: FERRAMENTA 2 · EFICIÊNCIA POR CARGA | H72: ▲ Voltar ao topo
B73: Calcula a remoção de massa poluidora. Use quando as vazões de entrada e de saída forem diferentes.
B75: B · ESCOLHA DO CENÁRIO
B76: Cenário ▼ | C76: Exemplo 01 | E76: Exemplo 01 e Exemplo 02 usam dados prontos. Meu cálculo usa os valores que você digitar na coluna amarela.
B78: C · DADOS DE ENTRADA
B79: Variável | C79: Exemplo 01 | D79: Exemplo 02 | E79: MEU CÁLCULO | F79: Unidade | G79: Valor em uso | H79: Orientação de preenchimento
B80: Parâmetro | C80: DBO | D80: SST | E80: DBO | F80: lista ▼ | G80: =IF($L$23=1,C80,IF($L$23=2,D80,IF($L$23=3,IF(E80="","",E80),""))) -> DBO | H80: Escolha o parâmetro avaliado.
B81: Vazão de entrada | C81: 500 | D81: 1000 | F81: m³/dia | G81: =IF($L$23=1,C81,IF($L$23=2,D81,IF($L$23=3,IF(E81="","",E81),""))) -> 500 | H81: Vazão que entra no sistema. Ex.: 500
B82: Concentração de entrada | C82: 200 | D82: 300 | F82: mg/L | G82: =IF($L$23=1,C82,IF($L$23=2,D82,IF($L$23=3,IF(E82="","",E82),""))) -> 200 | H82: Concentração na entrada. Ex.: 200
B83: Vazão de saída | C83: 400 | D83: 950 | F83: m³/dia | G83: =IF($L$23=1,C83,IF($L$23=2,D83,IF($L$23=3,IF(E83="","",E83),""))) -> 400 | H83: Vazão do efluente final. Ex.: 400
B84: Concentração de saída | C84: 50 | D84: 30 | F84: mg/L | G84: =IF($L$23=1,C84,IF($L$23=2,D84,IF($L$23=3,IF(E84="","",E84),""))) -> 50 | H84: Concentração no efluente final. Ex.: 50
B86: D · RESULTADO AUTOMÁTICO
B87: EFICIÊNCIA POR CARGA | E87: OUTROS RESULTADOS
B88: =IF($L$31,$L$27,"—") -> 80 | D88: % | E88: Carga de entrada | G88: =IF($L$31,$L$24,"—") -> 100 | H88: kg/dia
E89: Carga de saída | G89: =IF($L$31,$L$25,"—") -> 20 | H89: kg/dia
E90: Carga removida | G90: =IF($L$31,$L$26,"—") -> 80 | H90: kg/dia
E91: Eficiência por concentração | G91: =IF($L$31,$L$29,"—") -> 75 | H91: %
B92: Interpretação | C92: =IF($L$31,IF($L$27>0,"Houve redução de "&$G$80&": o sistema removeu "&$L$33&"% da carga de entrada.",IF($L$27=0,"Não houve redução: o valor de saída é igual ao de entrada.","Houve aumento de "&$G$80&": a saída ficou "&$L$37&"% acima da entrada. Confira os dados e o funcionamento do sistema."))&" Só pelas concentrações, a eficiência seria "&$L$35&"%.","Resultado indisponível: corrija o item indicado em Status dos dados.") -> Houve redução de DBO: o sistema removeu 80% da carga de entrada. Só pelas concentrações, a eficiência seria 75%.
B93: Status dos dados | C93: =IF($L$31,"✔ Dados válidos. Resultado calculado automaticamente.","⚠ "&$L$30) -> ✔ Dados válidos. Resultado calculado automaticamente.
B95: E · ENTENDA O CÁLCULO
B96: Fórmula | C96: Carga = Q × C × 0,001 | Eficiência (%) = (Carga entrada − Carga saída) ÷ Carga entrada × 100
B97: O que é cada variável | C97: Qe, Ce = vazão (m³/dia) e concentração (mg/L) de entrada | Qs, Cs = vazão e concentração de saída | Carga em kg/dia
B98: Valores inseridos | C98: ="Parâmetro: "&$G$80&" | "&"Qe = "&$L$43&" "&"m³/dia"&" | "&"Ce = "&$L$39&" "&"mg/L"&" | "&"Qs = "&$L$45&" "&"m³/dia"&" | "&"Cs = "&$L$41&" "&"mg/L" -> Parâmetro: DBO | Qe = 500 m³/dia | Ce = 200 mg/L | Qs = 400 m³/dia | Cs = 50 mg/L
B99: Substituição | C99: =IF($L$31,"Carga entrada = "&$L$43&" × "&$L$39&" × 0,001 = "&$L$47&" kg/dia"&CHAR(10)&"Carga saída = "&$L$45&" × "&$L$41&" × 0,001 = "&$L$49&" kg/dia"&CHAR(10)&"E = ("&$L$47&" − "&$L$49&") ÷ "&$L$47&" × 100 = "&$L$33&"%","Aguardando dados válidos para montar a conta.") -> Carga entrada = 500 × 200 × 0,001 = 100 kg/dia Carga saída = 400 × 50 × 0,001 = 20 kg/dia E = (100 − 20) ÷ 100 × 100 = 80%
B100: Resultado | C100: =IF($L$31,"Carga de entrada = "&$L$47&" kg/dia | Carga de saída = "&$L$49&" kg/dia | Eficiência = "&$L$33&"%","Aguardando dados válidos para montar a conta.") -> Carga de entrada = 100 kg/dia | Carga de saída = 20 kg/dia | Eficiência = 80%
B102: G · COMPARAÇÃO VISUAL
E103: Dados do gráfico (atualizam sozinhos)
E104: Carga de entrada | G104: =IF($L$31,$L$24,"") -> 100 | H104: kg/dia
E105: Carga de saída | G105: =IF($L$31,$L$25,"") -> 20 | H105: kg/dia
E107: O gráfico usa os mesmos resultados do card verde. Mude um dado e veja as barras mudarem.
B118: F · EXEMPLO E ORIENTAÇÃO
B119: Exemplos desta ferramenta | C119: Exemplo 01: Uma ETE recebe 500 m³/dia com 200 mg/L de DBO. Parte da água sai com o lodo, e o efluente final tem 400 m³/dia com 50 mg/L. Exemplo 02: Um decantador recebe 1.000 m³/dia com 300 mg/L de SST. O clarificado sai com 950 m³/dia e 30 mg/L. Escolha o exemplo na lista Cenário para ver a resolução completa.
B120: Como interpretar | C120: A eficiência por carga mostra quanto da massa de poluente foi realmente retida ou transformada no sistema, mesmo quando a vazão muda entre a entrada e a saída.
B121: ⚠ Erro comum | C121: Calcular a eficiência só pelas concentrações quando as vazões mudam. Nesse caso o resultado pode enganar.
B122: 💡 Dica prática | C122: Compare as duas eficiências (por carga e por concentração) para entender o efeito da mudança de vazão.
B123: Atenção | C123: A calculadora não classifica o resultado como bom ou ruim e não verifica normas. Para isso, compare com o padrão aplicável ao parâmetro e ao seu caso.
B126: Lembrete: os resultados são cálculos teóricos de apoio ao estudo. Confira unidades e hipóteses antes de usar em trabalhos, relatórios ou no estágio.

Sheet 05 — Balanço de Massa
B1: ⚖️ CALCULADORA 04 · BALANÇO DE MASSA | K1: ÁREA TÉCNICA · cálculos auxiliares (não editar)
B2: KIT DE 6 CALCULADORAS AUTOMÁTICAS DE ENGENHARIA AMBIENTAL | K2: Descrição | L2: Valor
B3: 🏠 Painel | C3: 📘 Guia | E3: 📚 Exemplos | G3: ◀ Anterior | H3: Próxima aba ▶ | K3: ferramenta escolhida (número) | L3: =IFERROR(MATCH($C$17,{"Ferramenta 1: Mistura de duas correntes","Ferramenta 2: Balanço em decantadores","Ferramenta 3: Acúmulo de massa"},0),0) -> 1
K4: índice do cenário (1, 2 ou 3) | L4: =IFERROR(MATCH($C$25,{"Exemplo 01","Exemplo 02","Meu cálculo"},0),0) -> 1
B5: COMO USAR: ① Escolha a ferramenta abaixo ② Escolha o cenário na lista amarela ③ Para usar seus dados, escolha Meu cálculo e digite na coluna amarela ④ Veja o resultado no card verde ⑤ Confira a conta em ENTENDA O CÁLCULO | K5: [Mistura de duas correntes] Qt | L5: =IFERROR($G$29+$G$31,"") -> 200
K6: [Mistura de duas correntes] QC | L6: =IFERROR($G$29*$G$30+$G$31*$G$32,"") -> 28000
B7: A · IDENTIFICAÇÃO | K7: [Mistura de duas correntes] Cf | L7: =IFERROR($L$6/$L$5,"") -> 140
B8: O que calcula | C8: Concentrações e massas em sistemas com entradas e saídas, aplicando a conservação da massa. | K8: [Mistura de duas correntes] L1 | L8: =IFERROR($G$29*$G$30*0.001,"") -> 24
B9: Quando usar | C9: Mistura de efluentes, lançamento em rios, decantadores e adensadores, tanques e reatores, problemas de regime permanente. | K9: [Mistura de duas correntes] L2 | L9: =IFERROR($G$31*$G$32*0.001,"") -> 4
B10: Exemplo prático | C10: Duas correntes de 120 e 80 m³/dia, com 200 e 50 mg/L, formam uma mistura de 140 mg/L. | K10: [Mistura de duas correntes] Lt | L10: =IFERROR($L$8+$L$9,"") -> 28
K11: [Mistura de duas correntes] Cmin | L11: =IFERROR(MIN($G$30,$G$32),"") -> 50
B12: FERRAMENTAS DESTA CALCULADORA | K12: [Mistura de duas correntes] Cmax | L12: =IFERROR(MAX($G$30,$G$32),"") -> 200
B13: ▶ Ferramenta 1 | C13: Mistura de duas correntes: Calcula a vazão total e a concentração final quando duas correntes se juntam. Considera mistura completa, sem perdas e sem transformação do constituinte. | K13: [Mistura de duas correntes] mensagem de validação | L13: =IFERROR(IF($L$4=0,"Escolha um cenário na lista: Exemplo 01, Exemplo 02 ou Meu cálculo.",IF($G$29="","Informe a vazão da corrente 1 para continuar.",IF(NOT(ISNUMBER($G$29)),"A vazão da corrente 1 precisa ser um número. Confira o valor digitado.",IF($G$29<=0,"A vazão da corrente 1 deve ser maior que zero.",IF($G$30="","Informe a concentração da corrente 1 para continuar (digite 0 se for o caso).",IF(NOT(ISNUMBER($G$30)),"A concentração da corrente 1 precisa ser um número. Confira o valor digitado.",IF($G$30<0,"A concentração da corrente 1 não pode ser negativa.",IF($G$31="","Informe a vazão da corrente 2 para continuar.",IF(NOT(ISNUMBER($G$31)),"A vazão da corrente 2 precisa ser um número. Confira o valor digitado.",IF($G$31<=0,"A vazão da corrente 2 deve ser maior que zero.",IF($G$32="","Informe a concentração da corrente 2 para continuar (digite 0 se for o caso).",IF(NOT(ISNUMBER($G$32)),"A concentração da corrente 2 precisa ser um número. Confira o valor digitado.",IF($G$32<0,"A concentração da corrente 2 não pode ser negativa.",""))))))))))))),"Resultado indisponível: existem dados inválidos.")
B14: ▶ Ferramenta 2 | C14: Balanço de massa em decantadores: Calcula a concentração de sólidos no lodo a partir da entrada e do clarificado e confere se o balanço hidráulico fecha (Qe = Qa + Ql). | K14: [Mistura de duas correntes] dados válidos? | L14: =$L$13="" -> TRUE
B15: ▶ Ferramenta 3 | C15: Acúmulo de massa: Aplica a equação geral do balanço de massa para saber se o constituinte está acumulando, diminuindo ou estável dentro do sistema. Todos os termos precisam estar na mesma unidade de massa por tempo. | K15: [Mistura de duas correntes] Cf (arredondado) | L15: =IFERROR(ROUND($L$7,IF($L$7=0,0,4-INT(LOG10(ABS($L$7))))),"") -> 140
K16: [Mistura de duas correntes] Cf (texto) | L16: =IF(ISNUMBER($L$15),FIXED($L$15,IF(ROUND($L$15,0)=$L$15,0,IF(ROUND($L$15,1)=$L$15,1,IF(ROUND($L$15,2)=$L$15,2,IF(ROUND($L$15,3)=$L$15,3,IF(ROUND($L$15,4)=$L$15,4,IF(ROUND($L$15,5)=$L$15,5,IF(ROUND($L$15,6)=$L$15,6,7)))))))),"?") -> 140
B17: Ferramenta escolhida ▼ | C17: Ferramenta 1: Mistura de duas correntes | F17: A ferramenta escolhida fica com o título em verde. Use os botões azuis acima para ir até ela. | K17: [Mistura de duas correntes] Cmax (arredondado) | L17: =IFERROR(ROUND($L$12,IF($L$12=0,0,4-INT(LOG10(ABS($L$12))))),"") -> 200
B18: Resultado atual | C18: =IFERROR(CHOOSE($L$3,$L$35,$L$74,$L$94),"—") -> 140 mg/L | K18: [Mistura de duas correntes] Cmax (texto) | L18: =IF(ISNUMBER($L$17),FIXED($L$17,IF(ROUND($L$17,0)=$L$17,0,IF(ROUND($L$17,1)=$L$17,1,IF(ROUND($L$17,2)=$L$17,2,IF(ROUND($L$17,3)=$L$17,3,IF(ROUND($L$17,4)=$L$17,4,IF(ROUND($L$17,5)=$L$17,5,IF(ROUND($L$17,6)=$L$17,6,7)))))))),"?") -> 200
B19: Status | C19: =IFERROR(CHOOSE($L$3,C41,C94,C147),"Escolha uma ferramenta.") -> ✔ Dados válidos. Resultado calculado automaticamente. | K19: [Mistura de duas correntes] Cmin (arredondado) | L19: =IFERROR(ROUND($L$11,IF($L$11=0,0,4-INT(LOG10(ABS($L$11))))),"") -> 50
K20: [Mistura de duas correntes] Cmin (texto) | L20: =IF(ISNUMBER($L$19),FIXED($L$19,IF(ROUND($L$19,0)=$L$19,0,IF(ROUND($L$19,1)=$L$19,1,IF(ROUND($L$19,2)=$L$19,2,IF(ROUND($L$19,3)=$L$19,3,IF(ROUND($L$19,4)=$L$19,4,IF(ROUND($L$19,5)=$L$19,5,IF(ROUND($L$19,6)=$L$19,6,7)))))))),"?") -> 50
B21: FERRAMENTA 1 · MISTURA DE DUAS CORRENTES | H21: ▲ Voltar ao topo | K21: [Mistura de duas correntes] Lt (arredondado) | L21: =IFERROR(ROUND($L$10,IF($L$10=0,0,4-INT(LOG10(ABS($L$10))))),"") -> 28
B22: Calcula a vazão total e a concentração final quando duas correntes se juntam. Considera mistura completa, sem perdas e sem transformação do constituinte. | K22: [Mistura de duas correntes] Lt (texto) | L22: =IF(ISNUMBER($L$21),FIXED($L$21,IF(ROUND($L$21,0)=$L$21,0,IF(ROUND($L$21,1)=$L$21,1,IF(ROUND($L$21,2)=$L$21,2,IF(ROUND($L$21,3)=$L$21,3,IF(ROUND($L$21,4)=$L$21,4,IF(ROUND($L$21,5)=$L$21,5,IF(ROUND($L$21,6)=$L$21,6,7)))))))),"?") -> 28
K23: [Mistura de duas correntes] C1 (arredondado) | L23: =IFERROR(ROUND($G$30,IF($G$30=0,0,4-INT(LOG10(ABS($G$30))))),"") -> 200
B24: B · ESCOLHA DO CENÁRIO | K24: [Mistura de duas correntes] C1 (texto) | L24: =IF(ISNUMBER($L$23),FIXED($L$23,IF(ROUND($L$23,0)=$L$23,0,IF(ROUND($L$23,1)=$L$23,1,IF(ROUND($L$23,2)=$L$23,2,IF(ROUND($L$23,3)=$L$23,3,IF(ROUND($L$23,4)=$L$23,4,IF(ROUND($L$23,5)=$L$23,5,IF(ROUND($L$23,6)=$L$23,6,7)))))))),"?") -> 200
B25: Cenário ▼ | C25: Exemplo 01 | E25: Exemplo 01 e Exemplo 02 usam dados prontos. Meu cálculo usa os valores que você digitar na coluna amarela. | K25: [Mistura de duas correntes] C2 (arredondado) | L25: =IFERROR(ROUND($G$32,IF($G$32=0,0,4-INT(LOG10(ABS($G$32))))),"") -> 50
K26: [Mistura de duas correntes] C2 (texto) | L26: =IF(ISNUMBER($L$25),FIXED($L$25,IF(ROUND($L$25,0)=$L$25,0,IF(ROUND($L$25,1)=$L$25,1,IF(ROUND($L$25,2)=$L$25,2,IF(ROUND($L$25,3)=$L$25,3,IF(ROUND($L$25,4)=$L$25,4,IF(ROUND($L$25,5)=$L$25,5,IF(ROUND($L$25,6)=$L$25,6,7)))))))),"?") -> 50
B27: C · DADOS DE ENTRADA | K27: [Mistura de duas correntes] Q1 (arredondado) | L27: =IFERROR(ROUND($G$29,IF($G$29=0,0,4-INT(LOG10(ABS($G$29))))),"") -> 120
B28: Variável | C28: Exemplo 01 | D28: Exemplo 02 | E28: MEU CÁLCULO | F28: Unidade | G28: Valor em uso | H28: Orientação de preenchimento | K28: [Mistura de duas correntes] Q1 (texto) | L28: =IF(ISNUMBER($L$27),FIXED($L$27,IF(ROUND($L$27,0)=$L$27,0,IF(ROUND($L$27,1)=$L$27,1,IF(ROUND($L$27,2)=$L$27,2,IF(ROUND($L$27,3)=$L$27,3,IF(ROUND($L$27,4)=$L$27,4,IF(ROUND($L$27,5)=$L$27,5,IF(ROUND($L$27,6)=$L$27,6,7)))))))),"?") -> 120
B29: Vazão da corrente 1 | C29: 120 | D29: 432 | F29: m³/dia | G29: =IF($L$4=1,C29,IF($L$4=2,D29,IF($L$4=3,IF(E29="","",E29),""))) -> 120 | H29: Vazão da primeira corrente. Ex.: 120 | K29: [Mistura de duas correntes] Q2 (arredondado) | L29: =IFERROR(ROUND($G$31,IF($G$31=0,0,4-INT(LOG10(ABS($G$31))))),"") -> 80
B30: Concentração da corrente 1 | C30: 200 | D30: 60 | F30: mg/L | G30: =IF($L$4=1,C30,IF($L$4=2,D30,IF($L$4=3,IF(E30="","",E30),""))) -> 200 | H30: Concentração da primeira corrente. Ex.: 200 | K30: [Mistura de duas correntes] Q2 (texto) | L30: =IF(ISNUMBER($L$29),FIXED($L$29,IF(ROUND($L$29,0)=$L$29,0,IF(ROUND($L$29,1)=$L$29,1,IF(ROUND($L$29,2)=$L$29,2,IF(ROUND($L$29,3)=$L$29,3,IF(ROUND($L$29,4)=$L$29,4,IF(ROUND($L$29,5)=$L$29,5,IF(ROUND($L$29,6)=$L$29,6,7)))))))),"?") -> 80
B31: Vazão da corrente 2 | C31: 80 | D31: 8640 | F31: m³/dia | G31: =IF($L$4=1,C31,IF($L$4=2,D31,IF($L$4=3,IF(E31="","",E31),""))) -> 80 | H31: Vazão da segunda corrente. Ex.: 80 | K31: [Mistura de duas correntes] QC (arredondado) | L31: =IFERROR(ROUND($L$6,IF($L$6=0,0,4-INT(LOG10(ABS($L$6))))),"") -> 28000
B32: Concentração da corrente 2 | C32: 50 | D32: 2 | F32: mg/L | G32: =IF($L$4=1,C32,IF($L$4=2,D32,IF($L$4=3,IF(E32="","",E32),""))) -> 50 | H32: Concentração da segunda corrente. Ex.: 50 | K32: [Mistura de duas correntes] QC (texto) | L32: =IF(ISNUMBER($L$31),FIXED($L$31,IF(ROUND($L$31,0)=$L$31,0,IF(ROUND($L$31,1)=$L$31,1,IF(ROUND($L$31,2)=$L$31,2,IF(ROUND($L$31,3)=$L$31,3,IF(ROUND($L$31,4)=$L$31,4,IF(ROUND($L$31,5)=$L$31,5,IF(ROUND($L$31,6)=$L$31,6,7)))))))),"?") -> 28.000
K33: [Mistura de duas correntes] Qt (arredondado) | L33: =IFERROR(ROUND($L$5,IF($L$5=0,0,4-INT(LOG10(ABS($L$5))))),"") -> 200
B34: D · RESULTADO AUTOMÁTICO | K34: [Mistura de duas correntes] Qt (texto) | L34: =IF(ISNUMBER($L$33),FIXED($L$33,IF(ROUND($L$33,0)=$L$33,0,IF(ROUND($L$33,1)=$L$33,1,IF(ROUND($L$33,2)=$L$33,2,IF(ROUND($L$33,3)=$L$33,3,IF(ROUND($L$33,4)=$L$33,4,IF(ROUND($L$33,5)=$L$33,5,IF(ROUND($L$33,6)=$L$33,6,7)))))))),"?") -> 200
B35: CONCENTRAÇÃO FINAL DA MISTURA | E35: OUTROS RESULTADOS | K35: [Mistura de duas correntes] resumo | L35: =IF($L$14,$L$16&" "&"mg/L","—") -> 140 mg/L
B36: =IF($L$14,$L$7,"—") -> 140 | D36: mg/L | E36: Vazão total | G36: =IF($L$14,$L$5,"—") -> 200 | H36: m³/dia | K36: índice do cenário (1, 2 ou 3) | L36: =IFERROR(MATCH($C$77,{"Exemplo 01","Exemplo 02","Meu cálculo"},0),0) -> 1
E37: Carga da corrente 1 | G37: =IF($L$14,$L$8,"—") -> 24 | H37: kg/dia | K37: [Balanço em decantadores] QeCe | L37: =IFERROR($G$81*$G$82,"") -> 90000
E38: Carga da corrente 2 | G38: =IF($L$14,$L$9,"—") -> 4 | H38: kg/dia | K38: [Balanço em decantadores] QaCa | L38: =IFERROR($G$83*$G$84,"") -> 14700
E39: Carga total | G39: =IF($L$14,$L$10,"—") -> 28 | H39: kg/dia | K39: [Balanço em decantadores] Cl | L39: =IFERROR(($L$37-$L$38)/$G$85,"") -> 7530
B40: Interpretação | C40: =IF($L$14,IF($G$30=$G$32,"As duas correntes têm a mesma concentração, então a mistura também fica com "&$L$16&" mg/L.","A mistura fica com "&$L$16&" mg/L. O valor está entre "&$L$20&" e "&$L$18&" mg/L e fica mais perto da corrente de maior vazão, porque a média é ponderada pelas vazões.")&" A carga total ("&$L$22&" kg/dia) é a soma das cargas das duas correntes.","Resultado indisponível: corrija o item indicado em Status dos dados.") -> A mistura fica com 140 mg/L. O valor está entre 50 e 200 mg/L e fica mais perto da corrente de maior vazão, porque a média é ponderada pelas vazões. A carga total (28 kg/dia) é a soma das cargas das duas correntes. | K40: [Balanço em decantadores] Le | L40: =IFERROR($L$37*0.001,"") -> 90
B41: Status dos dados | C41: =IF($L$14,"✔ Dados válidos. Resultado calculado automaticamente.","⚠ "&$L$13) -> ✔ Dados válidos. Resultado calculado automaticamente. | K41: [Balanço em decantadores] La | L41: =IFERROR($L$38*0.001,"") -> 14.7
K42: [Balanço em decantadores] Ll | L42: =IFERROR($L$40-$L$41,"") -> 75.3
B43: E · ENTENDA O CÁLCULO | K43: [Balanço em decantadores] QaQl | L43: =IFERROR($G$83+$G$85,"") -> 500
B44: Fórmula | C44: Cfinal = (Q₁ × C₁ + Q₂ × C₂) ÷ (Q₁ + Q₂) | K44: [Balanço em decantadores] dQ | L44: =IFERROR($G$81-$L$43,"") -> 0
B45: O que é cada variável | C45: Q₁, Q₂ = vazões das correntes | C₁, C₂ = concentrações | Cfinal = concentração da mistura. Hipóteses: mistura completa, sem perdas e sem reação. | K45: [Balanço em decantadores] fecha | L45: =IFERROR(ABS($L$44)<=0.005*$G$81,"") -> TRUE
B46: Valores inseridos | C46: ="Q₁ = "&$L$28&" "&"m³/dia"&" | "&"C₁ = "&$L$24&" "&"mg/L"&" | "&"Q₂ = "&$L$30&" "&"m³/dia"&" | "&"C₂ = "&$L$26&" "&"mg/L" -> Q₁ = 120 m³/dia | C₁ = 200 mg/L | Q₂ = 80 m³/dia | C₂ = 50 mg/L | K46: [Balanço em decantadores] fecha_txt | L46: =IFERROR(IF($L$45,"✔ Fecha","⚠ Não fecha"),"") -> ✔ Fecha
B47: Substituição | C47: =IF($L$14,"Cfinal = ("&$L$28&" × "&$L$24&" + "&$L$30&" × "&$L$26&") ÷ ("&$L$28&" + "&$L$30&") = "&$L$32&" ÷ "&$L$34&" = "&$L$16&" mg/L","Aguardando dados válidos para montar a conta.") -> Cfinal = (120 × 200 + 80 × 50) ÷ (120 + 80) = 28.000 ÷ 200 = 140 mg/L | K47: [Balanço em decantadores] razao | L47: =IFERROR(ROUND($L$39/$G$82,1),"") -> 41.8
B48: Resultado | C48: =IF($L$14,"Vazão total = "&$L$34&" m³/dia | Cfinal = "&$L$16&" mg/L | Carga total = "&$L$22&" kg/dia","Aguardando dados válidos para montar a conta.") -> Vazão total = 200 m³/dia | Cfinal = 140 mg/L | Carga total = 28 kg/dia | K48: [Balanço em decantadores] mensagem de validação | L48: =IFERROR(IF($L$36=0,"Escolha um cenário na lista: Exemplo 01, Exemplo 02 ou Meu cálculo.",IF($G$81="","Informe a vazão de entrada (Qe) para continuar.",IF(NOT(ISNUMBER($G$81)),"A vazão de entrada (Qe) precisa ser um número. Confira o valor digitado.",IF($G$81<=0,"A vazão de entrada (Qe) deve ser maior que zero.",IF($G$82="","Informe a concentração de entrada (Ce) para continuar (digite 0 se for o caso).",IF(NOT(ISNUMBER($G$82)),"A concentração de entrada (Ce) precisa ser um número. Confira o valor digitado.",IF($G$82<0,"A concentração de entrada (Ce) não pode ser negativa.",IF($G$83="","Informe a vazão do clarificado (Qa) para continuar (digite 0 se for o caso).",IF(NOT(ISNUMBER($G$83)),"A vazão do clarificado (Qa) precisa ser um número. Confira o valor digitado.",IF($G$83<0,"A vazão do clarificado (Qa) não pode ser negativa.",IF($G$84="","Informe a concentração do clarificado (Ca) para continuar (digite 0 se for o caso).",IF(NOT(ISNUMBER($G$84)),"A concentração do clarificado (Ca) precisa ser um número. Confira o valor digitado.",IF($G$84<0,"A concentração do clarificado (Ca) não pode ser negativa.",IF($G$85="","Informe a vazão de lodo (Ql) para continuar.",IF(NOT(ISNUMBER($G$85)),"A vazão de lodo (Ql) precisa ser um número. Confira o valor digitado.",IF($G$85<=0,"A vazão de lodo (Ql) deve ser maior que zero.","")))))))))))))))),"Resultado indisponível: existem dados inválidos.")
K49: [Balanço em decantadores] dados válidos? | L49: =$L$48="" -> TRUE
B50: G · COMPARAÇÃO VISUAL | K50: [Balanço em decantadores] Cl (arredondado) | L50: =IFERROR(ROUND($L$39,IF($L$39=0,0,4-INT(LOG10(ABS($L$39))))),"") -> 7530
E51: Dados do gráfico (atualizam sozinhos) | K51: [Balanço em decantadores] Cl (texto) | L51: =IF(ISNUMBER($L$50),FIXED($L$50,IF(ROUND($L$50,0)=$L$50,0,IF(ROUND($L$50,1)=$L$50,1,IF(ROUND($L$50,2)=$L$50,2,IF(ROUND($L$50,3)=$L$50,3,IF(ROUND($L$50,4)=$L$50,4,IF(ROUND($L$50,5)=$L$50,5,IF(ROUND($L$50,6)=$L$50,6,7)))))))),"?") -> 7.530
E52: Corrente 1 | G52: =IF($L$14,$G$30,"") -> 200 | H52: mg/L | K52: [Balanço em decantadores] QaQl (arredondado) | L52: =IFERROR(ROUND($L$43,IF($L$43=0,0,4-INT(LOG10(ABS($L$43))))),"") -> 500
E53: Corrente 2 | G53: =IF($L$14,$G$32,"") -> 50 | H53: mg/L | K53: [Balanço em decantadores] QaQl (texto) | L53: =IF(ISNUMBER($L$52),FIXED($L$52,IF(ROUND($L$52,0)=$L$52,0,IF(ROUND($L$52,1)=$L$52,1,IF(ROUND($L$52,2)=$L$52,2,IF(ROUND($L$52,3)=$L$52,3,IF(ROUND($L$52,4)=$L$52,4,IF(ROUND($L$52,5)=$L$52,5,IF(ROUND($L$52,6)=$L$52,6,7)))))))),"?") -> 500
E54: Mistura | G54: =IF($L$14,$L$7,"") -> 140 | H54: mg/L | K54: [Balanço em decantadores] Qe (arredondado) | L54: =IFERROR(ROUND($G$81,IF($G$81=0,0,4-INT(LOG10(ABS($G$81))))),"") -> 500
K55: [Balanço em decantadores] Qe (texto) | L55: =IF(ISNUMBER($L$54),FIXED($L$54,IF(ROUND($L$54,0)=$L$54,0,IF(ROUND($L$54,1)=$L$54,1,IF(ROUND($L$54,2)=$L$54,2,IF(ROUND($L$54,3)=$L$54,3,IF(ROUND($L$54,4)=$L$54,4,IF(ROUND($L$54,5)=$L$54,5,IF(ROUND($L$54,6)=$L$54,6,7)))))))),"?") -> 500
E56: O gráfico usa os mesmos resultados do card verde. Mude um dado e veja as barras mudarem. | K56: [Balanço em decantadores] dQ (arredondado) | L56: =IFERROR(ROUND($L$44,IF($L$44=0,0,4-INT(LOG10(ABS($L$44))))),"") -> 0
K57: [Balanço em decantadores] dQ (texto) | L57: =IF(ISNUMBER($L$56),FIXED($L$56,IF(ROUND($L$56,0)=$L$56,0,IF(ROUND($L$56,1)=$L$56,1,IF(ROUND($L$56,2)=$L$56,2,IF(ROUND($L$56,3)=$L$56,3,IF(ROUND($L$56,4)=$L$56,4,IF(ROUND($L$56,5)=$L$56,5,IF(ROUND($L$56,6)=$L$56,6,7)))))))),"?") -> 0
K58: [Balanço em decantadores] razao (arredondado) | L58: =IFERROR(ROUND($L$47,IF($L$47=0,0,4-INT(LOG10(ABS($L$47))))),"") -> 41.8
K59: [Balanço em decantadores] razao (texto) | L59: =IF(ISNUMBER($L$58),FIXED($L$58,IF(ROUND($L$58,0)=$L$58,0,IF(ROUND($L$58,1)=$L$58,1,IF(ROUND($L$58,2)=$L$58,2,IF(ROUND($L$58,3)=$L$58,3,IF(ROUND($L$58,4)=$L$58,4,IF(ROUND($L$58,5)=$L$58,5,IF(ROUND($L$58,6)=$L$58,6,7)))))))),"?") -> 41,8
K60: [Balanço em decantadores] Ca (arredondado) | L60: =IFERROR(ROUND($G$84,IF($G$84=0,0,4-INT(LOG10(ABS($G$84))))),"") -> 30
K61: [Balanço em decantadores] Ca (texto) | L61: =IF(ISNUMBER($L$60),FIXED($L$60,IF(ROUND($L$60,0)=$L$60,0,IF(ROUND($L$60,1)=$L$60,1,IF(ROUND($L$60,2)=$L$60,2,IF(ROUND($L$60,3)=$L$60,3,IF(ROUND($L$60,4)=$L$60,4,IF(ROUND($L$60,5)=$L$60,5,IF(ROUND($L$60,6)=$L$60,6,7)))))))),"?") -> 30
K62: [Balanço em decantadores] Ce (arredondado) | L62: =IFERROR(ROUND($G$82,IF($G$82=0,0,4-INT(LOG10(ABS($G$82))))),"") -> 180
K63: [Balanço em decantadores] Ce (texto) | L63: =IF(ISNUMBER($L$62),FIXED($L$62,IF(ROUND($L$62,0)=$L$62,0,IF(ROUND($L$62,1)=$L$62,1,IF(ROUND($L$62,2)=$L$62,2,IF(ROUND($L$62,3)=$L$62,3,IF(ROUND($L$62,4)=$L$62,4,IF(ROUND($L$62,5)=$L$62,5,IF(ROUND($L$62,6)=$L$62,6,7)))))))),"?") -> 180
K64: [Balanço em decantadores] Qa (arredondado) | L64: =IFERROR(ROUND($G$83,IF($G$83=0,0,4-INT(LOG10(ABS($G$83))))),"") -> 490
K65: [Balanço em decantadores] Qa (texto) | L65: =IF(ISNUMBER($L$64),FIXED($L$64,IF(ROUND($L$64,0)=$L$64,0,IF(ROUND($L$64,1)=$L$64,1,IF(ROUND($L$64,2)=$L$64,2,IF(ROUND($L$64,3)=$L$64,3,IF(ROUND($L$64,4)=$L$64,4,IF(ROUND($L$64,5)=$L$64,5,IF(ROUND($L$64,6)=$L$64,6,7)))))))),"?") -> 490
B66: F · EXEMPLO E ORIENTAÇÃO | K66: [Balanço em decantadores] Ql (arredondado) | L66: =IFERROR(ROUND($G$85,IF($G$85=0,0,4-INT(LOG10(ABS($G$85))))),"") -> 10
B67: Exemplos desta ferramenta | C67: Exemplo 01: Duas linhas de efluente se juntam antes do tratamento: 120 m³/dia com 200 mg/L de DBO e 80 m³/dia com 50 mg/L. Exemplo 02: Um efluente tratado (432 m³/dia, DBO de 60 mg/L) é lançado em um rio com vazão de 8.640 m³/dia e DBO de 2 mg/L. Qual é a DBO logo após a mistura? Escolha o exemplo na lista Cenário para ver a resolução completa. | K67: [Balanço em decantadores] Ql (texto) | L67: =IF(ISNUMBER($L$66),FIXED($L$66,IF(ROUND($L$66,0)=$L$66,0,IF(ROUND($L$66,1)=$L$66,1,IF(ROUND($L$66,2)=$L$66,2,IF(ROUND($L$66,3)=$L$66,3,IF(ROUND($L$66,4)=$L$66,4,IF(ROUND($L$66,5)=$L$66,5,IF(ROUND($L$66,6)=$L$66,6,7)))))))),"?") -> 10
B68: Como interpretar | C68: A concentração final é uma média ponderada: a corrente com mais vazão puxa o resultado para perto dela. | K68: [Balanço em decantadores] QaCa (arredondado) | L68: =IFERROR(ROUND($L$38,IF($L$38=0,0,4-INT(LOG10(ABS($L$38))))),"") -> 14700
B69: ⚠ Erro comum | C69: Fazer a média simples das concentrações ((200 + 50) ÷ 2 = 125 mg/L). A média precisa ser ponderada pelas vazões. | K69: [Balanço em decantadores] QaCa (texto) | L69: =IF(ISNUMBER($L$68),FIXED($L$68,IF(ROUND($L$68,0)=$L$68,0,IF(ROUND($L$68,1)=$L$68,1,IF(ROUND($L$68,2)=$L$68,2,IF(ROUND($L$68,3)=$L$68,3,IF(ROUND($L$68,4)=$L$68,4,IF(ROUND($L$68,5)=$L$68,5,IF(ROUND($L$68,6)=$L$68,6,7)))))))),"?") -> 14.700
B70: 💡 Dica prática | C70: A concentração final funciona com qualquer unidade de vazão, desde que as duas correntes usem a mesma. As cargas em kg/dia assumem m³/dia e mg/L. | K70: [Balanço em decantadores] QeCe (arredondado) | L70: =IFERROR(ROUND($L$37,IF($L$37=0,0,4-INT(LOG10(ABS($L$37))))),"") -> 90000
K71: [Balanço em decantadores] QeCe (texto) | L71: =IF(ISNUMBER($L$70),FIXED($L$70,IF(ROUND($L$70,0)=$L$70,0,IF(ROUND($L$70,1)=$L$70,1,IF(ROUND($L$70,2)=$L$70,2,IF(ROUND($L$70,3)=$L$70,3,IF(ROUND($L$70,4)=$L$70,4,IF(ROUND($L$70,5)=$L$70,5,IF(ROUND($L$70,6)=$L$70,6,7)))))))),"?") -> 90.000
K72: [Balanço em decantadores] Ll (arredondado) | L72: =IFERROR(ROUND($L$42,IF($L$42=0,0,4-INT(LOG10(ABS($L$42))))),"") -> 75.3
B73: FERRAMENTA 2 · BALANÇO DE MASSA EM DECANTADORES | H73: ▲ Voltar ao topo | K73: [Balanço em decantadores] Ll (texto) | L73: =IF(ISNUMBER($L$72),FIXED($L$72,IF(ROUND($L$72,0)=$L$72,0,IF(ROUND($L$72,1)=$L$72,1,IF(ROUND($L$72,2)=$L$72,2,IF(ROUND($L$72,3)=$L$72,3,IF(ROUND($L$72,4)=$L$72,4,IF(ROUND($L$72,5)=$L$72,5,IF(ROUND($L$72,6)=$L$72,6,7)))))))),"?") -> 75,3
B74: Calcula a concentração de sólidos no lodo a partir da entrada e do clarificado e confere se o balanço hidráulico fecha (Qe = Qa + Ql). | K74: [Balanço em decantadores] resumo | L74: =IF($L$49,$L$51&" "&"mg/L","—") -> 7.530 mg/L
K75: índice do cenário (1, 2 ou 3) | L75: =IFERROR(MATCH($C$130,{"Exemplo 01","Exemplo 02","Meu cálculo"},0),0) -> 1
B76: B · ESCOLHA DO CENÁRIO | K76: [Acúmulo de massa] A | L76: =IFERROR($G$135-$G$136+$G$137-$G$138,"") -> 80
B77: Cenário ▼ | C77: Exemplo 01 | E77: Exemplo 01 e Exemplo 02 usam dados prontos. Meu cálculo usa os valores que você digitar na coluna amarela. | K77: [Acúmulo de massa] negA | L77: =IFERROR(-$L$76,"") -> -80
K78: [Acúmulo de massa] tin | L78: =IFERROR($G$135+$G$137,"") -> 100
B79: C · DADOS DE ENTRADA | K79: [Acúmulo de massa] tout | L79: =IFERROR($G$136+$G$138,"") -> 20
B80: Variável | C80: Exemplo 01 | D80: Exemplo 02 | E80: MEU CÁLCULO | F80: Unidade | G80: Valor em uso | H80: Orientação de preenchimento | K80: [Acúmulo de massa] mensagem de validação | L80: =IFERROR(IF($L$75=0,"Escolha um cenário na lista: Exemplo 01, Exemplo 02 ou Meu cálculo.",IF($G$134="","Escolha a unidade dos termos.",IF($G$135="","Informe a entrada para continuar (digite 0 se for o caso).",IF(NOT(ISNUMBER($G$135)),"A entrada precisa ser um número. Confira o valor digitado.",IF($G$135<0,"A entrada não pode ser negativa.",IF($G$136="","Informe a saída para continuar (digite 0 se for o caso).",IF(NOT(ISNUMBER($G$136)),"A saída precisa ser um número. Confira o valor digitado.",IF($G$136<0,"A saída não pode ser negativa.",IF($G$137="","Informe a geração interna para continuar (digite 0 se for o caso).",IF(NOT(ISNUMBER($G$137)),"A geração interna precisa ser um número. Confira o valor digitado.",IF($G$137<0,"A geração interna não pode ser negativa.",IF($G$138="","Informe o consumo para continuar (digite 0 se for o caso).",IF(NOT(ISNUMBER($G$138)),"O consumo precisa ser um número. Confira o valor digitado.",IF($G$138<0,"O consumo não pode ser negativo.","")))))))))))))),"Resultado indisponível: existem dados inválidos.")
B81: Vazão de entrada (Qe) | C81: 500 | D81: 1000 | F81: m³/dia | G81: =IF($L$36=1,C81,IF($L$36=2,D81,IF($L$36=3,IF(E81="","",E81),""))) -> 500 | H81: Vazão que entra no decantador. Ex.: 500 | K81: [Acúmulo de massa] dados válidos? | L81: =$L$80="" -> TRUE
B82: Concentração de entrada (Ce) | C82: 180 | D82: 220 | F82: mg/L | G82: =IF($L$36=1,C82,IF($L$36=2,D82,IF($L$36=3,IF(E82="","",E82),""))) -> 180 | H82: Sólidos na entrada. Ex.: 180 | K82: [Acúmulo de massa] A (arredondado) | L82: =IFERROR(ROUND($L$76,IF($L$76=0,0,4-INT(LOG10(ABS($L$76))))),"") -> 80
B83: Vazão do clarificado (Qa) | C83: 490 | D83: 985 | F83: m³/dia | G83: =IF($L$36=1,C83,IF($L$36=2,D83,IF($L$36=3,IF(E83="","",E83),""))) -> 490 | H83: Vazão que sai por cima. Ex.: 490 | K83: [Acúmulo de massa] A (texto) | L83: =IF(ISNUMBER($L$82),FIXED($L$82,IF(ROUND($L$82,0)=$L$82,0,IF(ROUND($L$82,1)=$L$82,1,IF(ROUND($L$82,2)=$L$82,2,IF(ROUND($L$82,3)=$L$82,3,IF(ROUND($L$82,4)=$L$82,4,IF(ROUND($L$82,5)=$L$82,5,IF(ROUND($L$82,6)=$L$82,6,7)))))))),"?") -> 80
B84: Concentração do clarificado (Ca) | C84: 30 | D84: 25 | F84: mg/L | G84: =IF($L$36=1,C84,IF($L$36=2,D84,IF($L$36=3,IF(E84="","",E84),""))) -> 30 | H84: Sólidos no clarificado. Ex.: 30 | K84: [Acúmulo de massa] negA (arredondado) | L84: =IFERROR(ROUND($L$77,IF($L$77=0,0,4-INT(LOG10(ABS($L$77))))),"") -> -80
B85: Vazão de lodo (Ql) | C85: 10 | D85: 15 | F85: m³/dia | G85: =IF($L$36=1,C85,IF($L$36=2,D85,IF($L$36=3,IF(E85="","",E85),""))) -> 10 | H85: Vazão de lodo retirada pelo fundo. Ex.: 10 | K85: [Acúmulo de massa] negA (texto) | L85: =IF(ISNUMBER($L$84),FIXED($L$84,IF(ROUND($L$84,0)=$L$84,0,IF(ROUND($L$84,1)=$L$84,1,IF(ROUND($L$84,2)=$L$84,2,IF(ROUND($L$84,3)=$L$84,3,IF(ROUND($L$84,4)=$L$84,4,IF(ROUND($L$84,5)=$L$84,5,IF(ROUND($L$84,6)=$L$84,6,7)))))))),"?") -> -80
K86: [Acúmulo de massa] Cn (arredondado) | L86: =IFERROR(ROUND($G$138,IF($G$138=0,0,4-INT(LOG10(ABS($G$138))))),"") -> 0
B87: D · RESULTADO AUTOMÁTICO | K87: [Acúmulo de massa] Cn (texto) | L87: =IF(ISNUMBER($L$86),FIXED($L$86,IF(ROUND($L$86,0)=$L$86,0,IF(ROUND($L$86,1)=$L$86,1,IF(ROUND($L$86,2)=$L$86,2,IF(ROUND($L$86,3)=$L$86,3,IF(ROUND($L$86,4)=$L$86,4,IF(ROUND($L$86,5)=$L$86,5,IF(ROUND($L$86,6)=$L$86,6,7)))))))),"?") -> 0
B88: CONCENTRAÇÃO NO LODO (Cl) | E88: OUTROS RESULTADOS | K88: [Acúmulo de massa] E (arredondado) | L88: =IFERROR(ROUND($G$135,IF($G$135=0,0,4-INT(LOG10(ABS($G$135))))),"") -> 100
B89: =IF($L$49,$L$39,"—") -> 7530 | D89: mg/L | E89: Carga de entrada | G89: =IF($L$49,$L$40,"—") -> 90 | H89: kg/dia | K89: [Acúmulo de massa] E (texto) | L89: =IF(ISNUMBER($L$88),FIXED($L$88,IF(ROUND($L$88,0)=$L$88,0,IF(ROUND($L$88,1)=$L$88,1,IF(ROUND($L$88,2)=$L$88,2,IF(ROUND($L$88,3)=$L$88,3,IF(ROUND($L$88,4)=$L$88,4,IF(ROUND($L$88,5)=$L$88,5,IF(ROUND($L$88,6)=$L$88,6,7)))))))),"?") -> 100
E90: Carga no clarificado | G90: =IF($L$49,$L$41,"—") -> 14.7 | H90: kg/dia | K90: [Acúmulo de massa] G (arredondado) | L90: =IFERROR(ROUND($G$137,IF($G$137=0,0,4-INT(LOG10(ABS($G$137))))),"") -> 0
E91: Carga no lodo | G91: =IF($L$49,$L$42,"—") -> 75.3 | H91: kg/dia | K91: [Acúmulo de massa] G (texto) | L91: =IF(ISNUMBER($L$90),FIXED($L$90,IF(ROUND($L$90,0)=$L$90,0,IF(ROUND($L$90,1)=$L$90,1,IF(ROUND($L$90,2)=$L$90,2,IF(ROUND($L$90,3)=$L$90,3,IF(ROUND($L$90,4)=$L$90,4,IF(ROUND($L$90,5)=$L$90,5,IF(ROUND($L$90,6)=$L$90,6,7)))))))),"?") -> 0
E92: Balanço hidráulico | G92: =IF($L$49,$L$46,"—") -> ✔ Fecha | K92: [Acúmulo de massa] Sd (arredondado) | L92: =IFERROR(ROUND($G$136,IF($G$136=0,0,4-INT(LOG10(ABS($G$136))))),"") -> 20
B93: Interpretação | C93: =IF($L$49,IF($L$39<0,"O resultado é negativo: pelos dados, o clarificado leva mais sólidos do que entram no decantador. Isso não acontece na prática, então confira vazões e concentrações.","O lodo sai com "&$L$51&" mg/L de sólidos."&IF(ISNUMBER($L$47)," É cerca de "&$L$59&" vezes a concentração de entrada.",""))&" "&IF($L$45,"Balanço hidráulico fechado: Qe = Qa + Ql = "&$L$55&" m³/dia.","Atenção: Qe ("&$L$55&") é diferente de Qa + Ql ("&$L$53&"). Diferença de "&$L$57&" m³/dia. Confira as vazões."),"Resultado indisponível: corrija o item indicado em Status dos dados.") -> O lodo sai com 7.530 mg/L de sólidos. É cerca de 41,8 vezes a concentração de entrada. Balanço hidráulico fechado: Qe = Qa + Ql = 500 m³/dia. | K93: [Acúmulo de massa] Sd (texto) | L93: =IF(ISNUMBER($L$92),FIXED($L$92,IF(ROUND($L$92,0)=$L$92,0,IF(ROUND($L$92,1)=$L$92,1,IF(ROUND($L$92,2)=$L$92,2,IF(ROUND($L$92,3)=$L$92,3,IF(ROUND($L$92,4)=$L$92,4,IF(ROUND($L$92,5)=$L$92,5,IF(ROUND($L$92,6)=$L$92,6,7)))))))),"?") -> 20
B94: Status dos dados | C94: =IF($L$49,"✔ Dados válidos. Resultado calculado automaticamente.","⚠ "&$L$48) -> ✔ Dados válidos. Resultado calculado automaticamente. | K94: [Acúmulo de massa] resumo | L94: =IF($L$81,$L$83&" "&$G$134,"—") -> 80 kg/dia
B96: E · ENTENDA O CÁLCULO
B97: Fórmula | C97: Qe × Ce = Qa × Ca + Ql × Cl → Cl = (Qe × Ce − Qa × Ca) ÷ Ql
B98: O que é cada variável | C98: Qe, Ce = entrada | Qa, Ca = clarificado (saída superior) | Ql, Cl = lodo (saída inferior)
B99: Valores inseridos | C99: ="Qe = "&$L$55&" "&"m³/dia"&" | "&"Ce = "&$L$63&" "&"mg/L"&" | "&"Qa = "&$L$65&" "&"m³/dia"&" | "&"Ca = "&$L$61&" "&"mg/L"&" | "&"Ql = "&$L$67&" "&"m³/dia" -> Qe = 500 m³/dia | Ce = 180 mg/L | Qa = 490 m³/dia | Ca = 30 mg/L | Ql = 10 m³/dia
B100: Substituição | C100: =IF($L$49,"Cl = ("&$L$55&" × "&$L$63&" − "&$L$65&" × "&$L$61&") ÷ "&$L$67&" = ("&$L$71&" − "&$L$69&") ÷ "&$L$67&" = "&$L$51&" mg/L","Aguardando dados válidos para montar a conta.") -> Cl = (500 × 180 − 490 × 30) ÷ 10 = (90.000 − 14.700) ÷ 10 = 7.530 mg/L
B101: Resultado | C101: =IF($L$49,"Cl = "&$L$51&" mg/L | Carga no lodo = "&$L$73&" kg/dia | Qa + Ql = "&$L$53&" m³/dia","Aguardando dados válidos para montar a conta.") -> Cl = 7.530 mg/L | Carga no lodo = 75,3 kg/dia | Qa + Ql = 500 m³/dia
...

Sheet 06 — Diluição de Soluções
B1: 🧪 CALCULADORA 05 · DILUIÇÃO DE SOLUÇÕES | K1: ÁREA TÉCNICA · cálculos auxiliares (não editar)
B2: KIT DE 6 CALCULADORAS AUTOMÁTICAS DE ENGENHARIA AMBIENTAL | K2: Descrição | L2: Valor
B3: 🏠 Painel | C3: 📘 Guia | E3: 📚 Exemplos | G3: ◀ Anterior | H3: Próxima aba ▶ | K3: índice do cenário (1, 2 ou 3) | L3: =IFERROR(MATCH($C$19,{"Exemplo 01","Exemplo 02","Meu cálculo"},0),0) -> 1
K4: [Diluição de soluções] m | L4: =IFERROR(IFERROR(MATCH($G$23,{"V₁ (volume de estoque)","C₂ (concentração final)","V₂ (volume final)","C₁ (concentração do estoque)"},0),0),"") -> 1
B5: COMO USAR: ① Escolha o cenário na lista amarela ② Para usar seus dados, escolha Meu cálculo e digite na coluna amarela MEU CÁLCULO ③ Veja o resultado no card verde ④ Confira a conta em ENTENDA O CÁLCULO | K5: [Diluição de soluções] ic1 | L5: =IFERROR(MATCH($G$25,{"mg/L","g/L","µg/L","% (m/v)","mol/L","mmol/L"},0),"") -> 1
K6: [Diluição de soluções] fc1 | L6: =IFERROR(CHOOSE($L$5,1,1000,0.001,10000,1,0.001),"") -> 1
B7: A · IDENTIFICAÇÃO | K7: [Diluição de soluções] fam1 | L7: =IFERROR(CHOOSE($L$5,1,1,1,1,2,2),"") -> 1
B8: O que calcula | C8: Volume de estoque, concentração final, volume final ou concentração do estoque, usando C₁ × V₁ = C₂ × V₂. | K8: [Diluição de soluções] ic2 | L8: =IFERROR(MATCH($G$29,{"mg/L","g/L","µg/L","% (m/v)","mol/L","mmol/L"},0),"") -> 1
B9: Quando usar | C9: Preparo de padrões e curvas de calibração, diluição de amostras para análises (DBO, DQO, metais) e aulas de laboratório. | K9: [Diluição de soluções] fc2 | L9: =IFERROR(CHOOSE($L$8,1,1000,0.001,10000,1,0.001),"") -> 1
B10: Exemplo prático | C10: Para preparar 500 mL a 200 mg/L com um padrão de 1.000 mg/L, use 100 mL do padrão e complete até 500 mL. | K10: [Diluição de soluções] fam2 | L10: =IFERROR(CHOOSE($L$8,1,1,1,1,2,2),"") -> 1
K11: [Diluição de soluções] fv1 | L11: =IFERROR(CHOOSE(MATCH($G$27,{"mL","L","µL"},0),1,1000,0.001),"") -> 1
B12: COMO ESTA CALCULADORA FUNCIONA | K12: [Diluição de soluções] fv2 | L12: =IFERROR(CHOOSE(MATCH($G$31,{"mL","L","µL"},0),1,1000,0.001),"") -> 1
B13: ▶ Ir para o cálculo | C13: Diluição: C₁ × V₁ = C₂ × V₂: Escolha o que deseja encontrar. A variável escolhida é calculada e o valor digitado nela é ignorado. Cada concentração e cada volume tem sua própria unidade. | K13: [Diluição de soluções] c1b | L13: =IFERROR(IF($L$4=4,"",$G$24*$L$6),"") -> 1000
K14: [Diluição de soluções] v1b | L14: =IFERROR(IF($L$4=1,"",$G$26*$L$11),"")
B15: DILUIÇÃO: C₁ × V₁ = C₂ × V₂ | H15: ▲ Voltar ao topo | K15: [Diluição de soluções] c2b | L15: =IFERROR(IF($L$4=2,"",$G$28*$L$9),"") -> 200
B16: Escolha o que deseja encontrar. A variável escolhida é calculada e o valor digitado nela é ignorado. Cada concentração e cada volume tem sua própria unidade. | K16: [Diluição de soluções] v2b | L16: =IFERROR(IF($L$4=3,"",$G$30*$L$12),"") -> 500
K17: [Diluição de soluções] rb | L17: =IFERROR(CHOOSE($L$4,$L$15*$L$16/$L$13,$L$13*$L$14/$L$16,$L$13*$L$14/$L$15,$L$15*$L$16/$L$14),"") -> 100
B18: B · ESCOLHA DO CENÁRIO | K18: [Diluição de soluções] r | L18: =IFERROR(CHOOSE($L$4,$L$17/$L$11,$L$17/$L$9,$L$17/$L$12,$L$17/$L$6),"") -> 100
B19: Cenário ▼ | C19: Exemplo 01 | E19: Exemplo 01 e Exemplo 02 usam dados prontos. Meu cálculo usa os valores que você digitar na coluna amarela. | K19: [Diluição de soluções] C1f | L19: =IFERROR(IF($L$4=4,$L$17,$L$13),"") -> 1000
K20: [Diluição de soluções] V1f | L20: =IFERROR(IF($L$4=1,$L$17,$L$14),"") -> 100
B21: C · DADOS DE ENTRADA | K21: [Diluição de soluções] C2f | L21: =IFERROR(IF($L$4=2,$L$17,$L$15),"") -> 200
B22: Variável | C22: Exemplo 01 | D22: Exemplo 02 | E22: MEU CÁLCULO | F22: Unidade | G22: Valor em uso | H22: Orientação de preenchimento | K22: [Diluição de soluções] V2f | L22: =IFERROR(IF($L$4=3,$L$17,$L$16),"") -> 500
B23: O que deseja encontrar? | C23: V₁ (volume de estoque) | D23: C₂ (concentração final) | E23: V₁ (volume de estoque) | F23: lista ▼ | G23: =IF($L$3=1,C23,IF($L$3=2,D23,IF($L$3=3,IF(E23="","",E23),""))) -> V₁ (volume de estoque) | H23: Escolha a incógnita do problema. | K23: [Diluição de soluções] C1u | L23: =IFERROR($L$19/$L$6,"") -> 1000
B24: C₁: concentração do estoque | C24: 1000 | D24: 1 | F24: =$G$25 -> mg/L | G24: =IF(IFERROR(MATCH($G$23,{"V₁ (volume de estoque)","C₂ (concentração final)","V₂ (volume final)","C₁ (concentração do estoque)"},0),0)=4,"calculado ▼",IF($L$3=1,C24,IF($L$3=2,D24,IF($L$3=3,IF(E24="","",E24),"")))) -> 1000 | H24: Concentração da solução concentrada. Ex.: 1000 | K24: [Diluição de soluções] V1u | L24: =IFERROR($L$20/$L$11,"") -> 100
B25: Unidade de C₁ | C25: mg/L | D25: g/L | E25: mg/L | F25: lista ▼ | G25: =IF($L$3=1,C25,IF($L$3=2,D25,IF($L$3=3,IF(E25="","",E25),""))) -> mg/L | H25: Unidade da concentração do estoque. | K25: [Diluição de soluções] C2u | L25: =IFERROR($L$21/$L$9,"") -> 200
B26: V₁: volume do estoque | C26: — | D26: 5 | F26: =$G$27 -> mL | G26: =IF(IFERROR(MATCH($G$23,{"V₁ (volume de estoque)","C₂ (concentração final)","V₂ (volume final)","C₁ (concentração do estoque)"},0),0)=1,"calculado ▼",IF($L$3=1,C26,IF($L$3=2,D26,IF($L$3=3,IF(E26="","",E26),"")))) -> calculado ▼ | H26: Volume de estoque que será transferido. Ex.: 100 | K26: [Diluição de soluções] V2u | L26: =IFERROR($L$22/$L$12,"") -> 500
B27: Unidade de V₁ | C27: mL | D27: mL | E27: mL | F27: lista ▼ | G27: =IF($L$3=1,C27,IF($L$3=2,D27,IF($L$3=3,IF(E27="","",E27),""))) -> mL | H27: Unidade do volume de estoque. | K27: [Diluição de soluções] solvml | L27: =IFERROR($L$22-$L$20,"") -> 400
B28: C₂: concentração final | C28: 200 | D28: — | F28: =$G$29 -> mg/L | G28: =IF(IFERROR(MATCH($G$23,{"V₁ (volume de estoque)","C₂ (concentração final)","V₂ (volume final)","C₁ (concentração do estoque)"},0),0)=2,"calculado ▼",IF($L$3=1,C28,IF($L$3=2,D28,IF($L$3=3,IF(E28="","",E28),"")))) -> 200 | H28: Concentração desejada na solução final. Ex.: 200 | K28: [Diluição de soluções] solv | L28: =IFERROR($L$27/$L$12,"") -> 400
B29: Unidade de C₂ | C29: mg/L | D29: mg/L | E29: mg/L | F29: lista ▼ | G29: =IF($L$3=1,C29,IF($L$3=2,D29,IF($L$3=3,IF(E29="","",E29),""))) -> mg/L | H29: Unidade da concentração final. | K29: [Diluição de soluções] fd | L29: =IFERROR($L$19/$L$21,"") -> 5
B30: V₂: volume final | C30: 500 | D30: 250 | F30: =$G$31 -> mL | G30: =IF(IFERROR(MATCH($G$23,{"V₁ (volume de estoque)","C₂ (concentração final)","V₂ (volume final)","C₁ (concentração do estoque)"},0),0)=3,"calculado ▼",IF($L$3=1,C30,IF($L$3=2,D30,IF($L$3=3,IF(E30="","",E30),"")))) -> 500 | H30: Volume final da solução (balão). Ex.: 500 | K30: [Diluição de soluções] bu | L30: =IFERROR(IF($L$7=1,"mg/L","mol/L"),"") -> mg/L
B31: Unidade de V₂ | C31: mL | D31: mL | E31: mL | F31: lista ▼ | G31: =IF($L$3=1,C31,IF($L$3=2,D31,IF($L$3=3,IF(E31="","",E31),""))) -> mL | H31: Unidade do volume final. | K31: [Diluição de soluções] rlabel | L31: =IFERROR(CHOOSE($L$4,"VOLUME DE ESTOQUE (V₁)","CONCENTRAÇÃO FINAL (C₂)","VOLUME FINAL (V₂)","CONCENTRAÇÃO DO ESTOQUE (C₁)"),"") -> VOLUME DE ESTOQUE (V₁)
K32: [Diluição de soluções] rsym | L32: =IFERROR(CHOOSE($L$4,"V₁","C₂","V₂","C₁"),"") -> V₁
B33: D · RESULTADO AUTOMÁTICO | K33: [Diluição de soluções] runit | L33: =IFERROR(CHOOSE($L$4,$G$27,$G$29,$G$31,$G$25),"") -> mL
B34: =IF($L$35,$L$31,"RESULTADO") -> VOLUME DE ESTOQUE (V₁) | E34: OUTROS RESULTADOS | K34: [Diluição de soluções] mensagem de validação | L34: =IFERROR(IF($L$3=0,"Escolha um cenário na lista: Exemplo 01, Exemplo 02 ou Meu cálculo.",IF($L$4=0,"Escolha na lista o que você deseja encontrar.",IF($L$6="","Confira a unidade selecionada para C₁.",IF($L$11="","Confira a unidade selecionada para V₁.",IF($L$9="","Confira a unidade selecionada para C₂.",IF($L$12="","Confira a unidade selecionada para V₂.",IF($L$7<>$L$10,"Confira a unidade selecionada: C₁ e C₂ precisam ser do mesmo tipo (massa por volume ou mol por volume).",IF(AND(NOT($L$4=4),$G$24=""),"Informe a concentração do estoque (C₁) para continuar.",IF(AND(NOT($L$4=4),NOT(ISNUMBER($G$24))),"A concentração do estoque (C₁) precisa ser um número. Confira o valor digitado.",IF(AND(NOT($L$4=4),$G$24<=0),"A concentração do estoque (C₁) deve ser maior que zero.",IF(AND(NOT($L$4=1),$G$26=""),"Informe o volume do estoque (V₁) para continuar.",IF(AND(NOT($L$4=1),NOT(ISNUMBER($G$26))),"O volume do estoque (V₁) precisa ser um número. Confira o valor digitado.",IF(AND(NOT($L$4=1),$G$26<=0),"O volume do estoque (V₁) deve ser maior que zero.",IF(AND(NOT($L$4=2),$G$28=""),"Informe a concentração final (C₂) para continuar.",IF(AND(NOT($L$4=2),NOT(ISNUMBER($G$28))),"A concentração final (C₂) precisa ser um número. Confira o valor digitado.",IF(AND(NOT($L$4=2),$G$28<=0),"A concentração final (C₂) deve ser maior que zero.",IF(AND(NOT($L$4=3),$G$30=""),"Informe o volume final (V₂) para continuar.",IF(AND(NOT($L$4=3),NOT(ISNUMBER($G$30))),"O volume final (V₂) precisa ser um número. Confira o valor digitado.",IF(AND(NOT($L$4=3),$G$30<=0),"O volume final (V₂) deve ser maior que zero.",IF(AND(OR($L$4=1,$L$4=3),$L$15>$L$13),"A concentração desejada é maior que a solução estoque. Em uma diluição simples, C₂ precisa ser menor ou igual a C₁.",IF(AND(OR($L$4=2,$L$4=4),$L$14>$L$16),"O volume de estoque (V₁) não pode ser maior que o volume final (V₂).",""))))))))))))))))))))),"Resultado indisponível: existem dados inválidos.")
B35: =IF($L$35,$L$18,"—") -> 100 | D35: =IF($L$35,$L$33,"") -> mL | E35: Solvente a adicionar | G35: =IF($L$35,$L$28,"—") -> 400 | H35: =$G$31 -> mL | K35: [Diluição de soluções] dados válidos? | L35: =$L$34="" -> TRUE
E36: Fator de diluição | G36: =IF($L$35,$L$29,"—") -> 5 | H36: vezes | K36: [Diluição de soluções] C1u (arredondado) | L36: =IFERROR(ROUND($L$23,IF($L$23=0,0,4-INT(LOG10(ABS($L$23))))),"") -> 1000
E37: Volume de estoque (V₁) | G37: =IF($L$35,$L$24,"—") -> 100 | H37: =$G$27 -> mL | K37: [Diluição de soluções] C1u (texto) | L37: =IF(ISNUMBER($L$36),FIXED($L$36,IF(ROUND($L$36,0)=$L$36,0,IF(ROUND($L$36,1)=$L$36,1,IF(ROUND($L$36,2)=$L$36,2,IF(ROUND($L$36,3)=$L$36,3,IF(ROUND($L$36,4)=$L$36,4,IF(ROUND($L$36,5)=$L$36,5,IF(ROUND($L$36,6)=$L$36,6,7)))))))),"?") -> 1.000
E38: Concentração final (C₂) | G38: =IF($L$35,$L$25,"—") -> 200 | H38: =$G$29 -> mg/L | K38: [Diluição de soluções] C2u (arredondado) | L38: =IFERROR(ROUND($L$25,IF($L$25=0,0,4-INT(LOG10(ABS($L$25))))),"") -> 200
B39: Interpretação | C39: =IF($L$35,"Utilize "&$L$41&" "&$G$27&" da solução estoque e complete com solvente até atingir o volume final de "&$L$43&" "&$G$31&". A solução final terá concentração de "&$L$39&" "&$G$29&"."&IF($L$4=4," A solução estoque precisa ter "&$L$37&" "&$G$25&".","")&IF(ROUND($L$29,9)=1," Como C₁ = C₂, não há diluição.",""),"Resultado indisponível: corrija o item indicado em Status dos dados.") -> Utilize 100 mL da solução estoque e complete com solvente até atingir o volume final de 500 mL. A solução final terá concentração de 200 mg/L. | K39: [Diluição de soluções] C2u (texto) | L39: =IF(ISNUMBER($L$38),FIXED($L$38,IF(ROUND($L$38,0)=$L$38,0,IF(ROUND($L$38,1)=$L$38,1,IF(ROUND($L$38,2)=$L$38,2,IF(ROUND($L$38,3)=$L$38,3,IF(ROUND($L$38,4)=$L$38,4,IF(ROUND($L$38,5)=$L$38,5,IF(ROUND($L$38,6)=$L$38,6,7)))))))),"?") -> 200
B40: Status dos dados | C40: =IF($L$35,"✔ Dados válidos. Resultado calculado automaticamente.","⚠ "&$L$34) -> ✔ Dados válidos. Resultado calculado automaticamente. | K40: [Diluição de soluções] V1u (arredondado) | L40: =IFERROR(ROUND($L$24,IF($L$24=0,0,4-INT(LOG10(ABS($L$24))))),"") -> 100
K41: [Diluição de soluções] V1u (texto) | L41: =IF(ISNUMBER($L$40),FIXED($L$40,IF(ROUND($L$40,0)=$L$40,0,IF(ROUND($L$40,1)=$L$40,1,IF(ROUND($L$40,2)=$L$40,2,IF(ROUND($L$40,3)=$L$40,3,IF(ROUND($L$40,4)=$L$40,4,IF(ROUND($L$40,5)=$L$40,5,IF(ROUND($L$40,6)=$L$40,6,7)))))))),"?") -> 100
B42: ESQUEMA DE PREPARO DA SOLUÇÃO | K42: [Diluição de soluções] V2u (arredondado) | L42: =IFERROR(ROUND($L$26,IF($L$26=0,0,4-INT(LOG10(ABS($L$26))))),"") -> 500
B43: ① SOLUÇÃO ESTOQUE ➜ | C43: ② TRANSFERÊNCIA ➜ | E43: ③ DILUIÇÃO ➜ | H43: ④ SOLUÇÃO FINAL | K43: [Diluição de soluções] V2u (texto) | L43: =IF(ISNUMBER($L$42),FIXED($L$42,IF(ROUND($L$42,0)=$L$42,0,IF(ROUND($L$42,1)=$L$42,1,IF(ROUND($L$42,2)=$L$42,2,IF(ROUND($L$42,3)=$L$42,3,IF(ROUND($L$42,4)=$L$42,4,IF(ROUND($L$42,5)=$L$42,5,IF(ROUND($L$42,6)=$L$42,6,7)))))))),"?") -> 500
B44: =IF($L$35,"Frasco com C₁ = "&$L$37&" "&$G$25,"—") -> Frasco com C₁ = 1.000 mg/L | C44: =IF($L$35,"Retire "&$L$41&" "&$G$27&" da solução estoque com pipeta volumétrica","—") -> Retire 100 mL da solução estoque com pipeta volumétrica | E44: =IF($L$35,"Coloque no balão e complete com cerca de "&$L$45&" "&$G$31&" de solvente até a marca","—") -> Coloque no balão e complete com cerca de 400 mL de solvente até a marca | H44: =IF($L$35,$L$43&" "&$G$31&" de solução com C₂ = "&$L$39&" "&$G$29,"—") -> 500 mL de solução com C₂ = 200 mg/L | K44: [Diluição de soluções] solv (arredondado) | L44: =IFERROR(ROUND($L$28,IF($L$28=0,0,4-INT(LOG10(ABS($L$28))))),"") -> 400
K45: [Diluição de soluções] solv (texto) | L45: =IF(ISNUMBER($L$44),FIXED($L$44,IF(ROUND($L$44,0)=$L$44,0,IF(ROUND($L$44,1)=$L$44,1,IF(ROUND($L$44,2)=$L$44,2,IF(ROUND($L$44,3)=$L$44,3,IF(ROUND($L$44,4)=$L$44,4,IF(ROUND($L$44,5)=$L$44,5,IF(ROUND($L$44,6)=$L$44,6,7)))))))),"?") -> 400
B46: E · ENTENDA O CÁLCULO | K46: [Diluição de soluções] C1 (arredondado) | L46: =IFERROR(ROUND($G$24,IF($G$24=0,0,4-INT(LOG10(ABS($G$24))))),"") -> 1000
B47: Fórmula | C47: C₁ × V₁ = C₂ × V₂ | K47: [Diluição de soluções] C1 (texto) | L47: =IF(ISNUMBER($L$46),FIXED($L$46,IF(ROUND($L$46,0)=$L$46,0,IF(ROUND($L$46,1)=$L$46,1,IF(ROUND($L$46,2)=$L$46,2,IF(ROUND($L$46,3)=$L$46,3,IF(ROUND($L$46,4)=$L$46,4,IF(ROUND($L$46,5)=$L$46,5,IF(ROUND($L$46,6)=$L$46,6,7)))))))),"?") -> 1.000
B48: O que é cada variável | C48: C₁ = concentração do estoque | V₁ = volume de estoque transferido | C₂ = concentração desejada | V₂ = volume final | K48: [Diluição de soluções] C2 (arredondado) | L48: =IFERROR(ROUND($G$28,IF($G$28=0,0,4-INT(LOG10(ABS($G$28))))),"") -> 200
B49: Valores inseridos | C49: ="C₁ = "&IF($L$4=4,"? (a calcular)",$L$47&" "&$G$25)&" | V₁ = "&IF($L$4=1,"? (a calcular)",$L$51&" "&$G$27)&" | C₂ = "&IF($L$4=2,"? (a calcular)",$L$49&" "&$G$29)&" | V₂ = "&IF($L$4=3,"? (a calcular)",$L$53&" "&$G$31) -> C₁ = 1.000 mg/L | V₁ = ? (a calcular) | C₂ = 200 mg/L | V₂ = 500 mL | K49: [Diluição de soluções] C2 (texto) | L49: =IF(ISNUMBER($L$48),FIXED($L$48,IF(ROUND($L$48,0)=$L$48,0,IF(ROUND($L$48,1)=$L$48,1,IF(ROUND($L$48,2)=$L$48,2,IF(ROUND($L$48,3)=$L$48,3,IF(ROUND($L$48,4)=$L$48,4,IF(ROUND($L$48,5)=$L$48,5,IF(ROUND($L$48,6)=$L$48,6,7)))))))),"?") -> 200
B50: Substituição | C50: =IF($L$35,CHOOSE($L$4,"V₁ = C₂ × V₂ ÷ C₁ = "&$L$57&" × "&$L$61&" ÷ "&$L$55&" = "&$L$59&" mL","C₂ = C₁ × V₁ ÷ V₂ = "&$L$55&" × "&$L$59&" ÷ "&$L$61&" = "&$L$57&" "&$L$30,"V₂ = C₁ × V₁ ÷ C₂ = "&$L$55&" × "&$L$59&" ÷ "&$L$57&" = "&$L$61&" mL","C₁ = C₂ × V₂ ÷ V₁ = "&$L$57&" × "&$L$61&" ÷ "&$L$59&" = "&$L$55&" "&$L$30)&CHAR(10)&"(concentrações em "&$L$30&" e volumes em mL) → "&$L$32&" = "&$L$63&" "&$L$33,"Aguardando dados válidos para montar a conta.") -> V₁ = C₂ × V₂ ÷ C₁ = 200 × 500 ÷ 1.000 = 100 mL (concentrações em mg/L e volumes em mL) → V₁ = 100 mL | K50: [Diluição de soluções] V1 (arredondado) | L50: =IFERROR(ROUND($G$26,IF($G$26=0,0,4-INT(LOG10(ABS($G$26))))),"")
B51: Resultado | C51: =IF($L$35,$L$32&" = "&$L$63&" "&$L$33&" | Solvente a adicionar = "&$L$45&" "&$G$31,"Aguardando dados válidos para montar a conta.") -> V₁ = 100 mL | Solvente a adicionar = 400 mL | K51: [Diluição de soluções] V1 (texto) | L51: =IF(ISNUMBER($L$50),FIXED($L$50,IF(ROUND($L$50,0)=$L$50,0,IF(ROUND($L$50,1)=$L$50,1,IF(ROUND($L$50,2)=$L$50,2,IF(ROUND($L$50,3)=$L$50,3,IF(ROUND($L$50,4)=$L$50,4,IF(ROUND($L$50,5)=$L$50,5,IF(ROUND($L$50,6)=$L$50,6,7)))))))),"?") -> ?
K52: [Diluição de soluções] V2 (arredondado) | L52: =IFERROR(ROUND($G$30,IF($G$30=0,0,4-INT(LOG10(ABS($G$30))))),"") -> 500
B53: G · COMPARAÇÃO VISUAL | K53: [Diluição de soluções] V2 (texto) | L53: =IF(ISNUMBER($L$52),FIXED($L$52,IF(ROUND($L$52,0)=$L$52,0,IF(ROUND($L$52,1)=$L$52,1,IF(ROUND($L$52,2)=$L$52,2,IF(ROUND($L$52,3)=$L$52,3,IF(ROUND($L$52,4)=$L$52,4,IF(ROUND($L$52,5)=$L$52,5,IF(ROUND($L$52,6)=$L$52,6,7)))))))),"?") -> 500
E54: Dados do gráfico (atualizam sozinhos) | K54: [Diluição de soluções] C1f (arredondado) | L54: =IFERROR(ROUND($L$19,IF($L$19=0,0,4-INT(LOG10(ABS($L$19))))),"") -> 1000
E55: Solução estoque | G55: =IF($L$35,$L$20,"") -> 100 | H55: mL | K55: [Diluição de soluções] C1f (texto) | L55: =IF(ISNUMBER($L$54),FIXED($L$54,IF(ROUND($L$54,0)=$L$54,0,IF(ROUND($L$54,1)=$L$54,1,IF(ROUND($L$54,2)=$L$54,2,IF(ROUND($L$54,3)=$L$54,3,IF(ROUND($L$54,4)=$L$54,4,IF(ROUND($L$54,5)=$L$54,5,IF(ROUND($L$54,6)=$L$54,6,7)))))))),"?") -> 1.000
E56: Solvente | G56: =IF($L$35,$L$27,"") -> 400 | H56: mL | K56: [Diluição de soluções] C2f (arredondado) | L56: =IFERROR(ROUND($L$21,IF($L$21=0,0,4-INT(LOG10(ABS($L$21))))),"") -> 200
K57: [Diluição de soluções] C2f (texto) | L57: =IF(ISNUMBER($L$56),FIXED($L$56,IF(ROUND($L$56,0)=$L$56,0,IF(ROUND($L$56,1)=$L$56,1,IF(ROUND($L$56,2)=$L$56,2,IF(ROUND($L$56,3)=$L$56,3,IF(ROUND($L$56,4)=$L$56,4,IF(ROUND($L$56,5)=$L$56,5,IF(ROUND($L$56,6)=$L$56,6,7)))))))),"?") -> 200
E58: O gráfico usa os mesmos resultados do card verde. Mude um dado e veja as barras mudarem. | K58: [Diluição de soluções] V1f (arredondado) | L58: =IFERROR(ROUND($L$20,IF($L$20=0,0,4-INT(LOG10(ABS($L$20))))),"") -> 100
K59: [Diluição de soluções] V1f (texto) | L59: =IF(ISNUMBER($L$58),FIXED($L$58,IF(ROUND($L$58,0)=$L$58,0,IF(ROUND($L$58,1)=$L$58,1,IF(ROUND($L$58,2)=$L$58,2,IF(ROUND($L$58,3)=$L$58,3,IF(ROUND($L$58,4)=$L$58,4,IF(ROUND($L$58,5)=$L$58,5,IF(ROUND($L$58,6)=$L$58,6,7)))))))),"?") -> 100
K60: [Diluição de soluções] V2f (arredondado) | L60: =IFERROR(ROUND($L$22,IF($L$22=0,0,4-INT(LOG10(ABS($L$22))))),"") -> 500
K61: [Diluição de soluções] V2f (texto) | L61: =IF(ISNUMBER($L$60),FIXED($L$60,IF(ROUND($L$60,0)=$L$60,0,IF(ROUND($L$60,1)=$L$60,1,IF(ROUND($L$60,2)=$L$60,2,IF(ROUND($L$60,3)=$L$60,3,IF(ROUND($L$60,4)=$L$60,4,IF(ROUND($L$60,5)=$L$60,5,IF(ROUND($L$60,6)=$L$60,6,7)))))))),"?") -> 500
K62: [Diluição de soluções] r (arredondado) | L62: =IFERROR(ROUND($L$18,IF($L$18=0,0,4-INT(LOG10(ABS($L$18))))),"") -> 100
K63: [Diluição de soluções] r (texto) | L63: =IF(ISNUMBER($L$62),FIXED($L$62,IF(ROUND($L$62,0)=$L$62,0,IF(ROUND($L$62,1)=$L$62,1,IF(ROUND($L$62,2)=$L$62,2,IF(ROUND($L$62,3)=$L$62,3,IF(ROUND($L$62,4)=$L$62,4,IF(ROUND($L$62,5)=$L$62,5,IF(ROUND($L$62,6)=$L$62,6,7)))))))),"?") -> 100
K64: [Diluição de soluções] resumo | L64: =IF($L$35,$L$63&" "&$L$33,"—") -> 100 mL
B69: F · EXEMPLO E ORIENTAÇÃO
B70: Exemplos desta ferramenta | C70: Exemplo 01: No laboratório há uma solução padrão de 1.000 mg/L. Você precisa preparar 500 mL de uma solução com 200 mg/L. Quanto da solução padrão deve usar? Exemplo 02: Foram transferidos 5 mL de uma solução de 1 g/L para um balão de 250 mL, completado com água destilada. Qual é a concentração final em mg/L? Escolha o exemplo na lista Cenário para ver a resolução completa.
B71: Como interpretar | C71: V₁ é o quanto você retira do frasco de estoque. Depois, complete com solvente até a marca do volume final.
B72: ⚠ Erro comum | C72: Usar volumes em unidades diferentes sem converter, ou pedir uma concentração final maior que a do estoque. Diluir sempre reduz a concentração.
B73: 💡 Dica prática | C73: Use vidraria volumétrica (pipeta e balão volumétrico) para ter precisão. O volume de solvente é V₂ − V₁.
B76: Lembrete: os resultados são cálculos teóricos de apoio ao estudo. Confira unidades e hipóteses antes de usar em trabalhos, relatórios ou no estágio.

Sheet 07 — Dosagem Química
B1: ⚗️ CALCULADORA 06 · DOSAGEM DE PRODUTOS QUÍMICOS | K1: ÁREA TÉCNICA · cálculos auxiliares (não editar)
B2: KIT DE 6 CALCULADORAS AUTOMÁTICAS DE ENGENHARIA AMBIENTAL | K2: Descrição | L2: Valor
B3: 🏠 Painel | C3: 📘 Guia | E3: 📚 Exemplos | G3: ◀ Anterior | H3: Próxima aba ▶ | K3: índice do cenário (1, 2 ou 3) | L3: =IFERROR(MATCH($C$19,{"Exemplo 01","Exemplo 02","Meu cálculo"},0),0) -> 1
K4: [Dosagem química] fQ | L4: =IFERROR(CHOOSE(MATCH($G$25,{"m³/dia","m³/h","L/s"},0),1,24,86.4),"") -> 1
B5: COMO USAR: ① Escolha o cenário na lista amarela ② Para usar seus dados, escolha Meu cálculo e digite na coluna amarela MEU CÁLCULO ③ Veja o resultado no card verde ④ Confira a conta em ENTENDA O CÁLCULO | K5: [Dosagem química] Qd | L5: =IFERROR($G$24*$L$4,"") -> 500
K6: [Dosagem química] frac | L6: =IFERROR($G$27/100,"") -> 0.5
B7: A · IDENTIFICAÇÃO | K7: [Dosagem química] ma | L7: =IFERROR($L$5*$G$26*0.001,"") -> 2
B8: O que calcula | C8: A quantidade teórica de produto químico por dia: massa de ativo, massa de produto comercial e volume de produto líquido. | K8: [Dosagem química] mc | L8: =IFERROR($L$7/$L$6,"") -> 4
B9: Quando usar | C9: Coagulação, desinfecção com cloro, correção de pH, estimativa de custo operacional e planejamento de estoque em ETAs e ETEs. | K9: [Dosagem química] vol | L9: =IFERROR(IF($G$28="","",$L$8/$G$28),"") -> 3.3333333
B10: Exemplo prático | C10: Aplicar 4 mg/L de ativo em 500 m³/dia com produto a 50% exige 4 kg/dia de produto comercial. | K10: [Dosagem química] Dc | L10: =IFERROR($G$26/$L$6,"") -> 8
K11: [Dosagem química] mcm | L11: =IFERROR($L$8*30,"") -> 120
B12: COMO ESTA CALCULADORA FUNCIONA | K12: [Dosagem química] vol_txt | L12: =IFERROR(IF($G$28="","sem densidade",$L$9),"") -> 3.3333333
B13: ▶ Ir para o cálculo | C13: Dosagem: 3 ferramentas em sequência: Ferramenta 1 calcula a massa de componente ativo. Ferramenta 2 converte em massa de produto comercial. Ferramenta 3 converte em volume de produto líquido (quando houver densidade). | K13: [Dosagem química] mensagem de validação | L13: =IFERROR(IF($L$3=0,"Escolha um cenário na lista: Exemplo 01, Exemplo 02 ou Meu cálculo.",IF($G$24="","Informe a vazão para continuar.",IF(NOT(ISNUMBER($G$24)),"A vazão precisa ser um número. Confira o valor digitado.",IF($G$24<=0,"A vazão deve ser maior que zero.",IF($L$4="","Confira a unidade selecionada para a vazão.",IF($G$26="","Informe a dosagem ativa para continuar.",IF(NOT(ISNUMBER($G$26)),"A dosagem ativa precisa ser um número. Confira o valor digitado.",IF($G$26<=0,"A dosagem ativa deve ser maior que zero.",IF($G$27="","Confira a porcentagem do componente ativo: o campo está vazio.",IF(NOT(ISNUMBER($G$27)),"Confira a porcentagem do componente ativo: digite um número de 0 a 100.",IF($G$27<=0,"Confira a porcentagem do componente ativo: ela precisa ser maior que zero.",IF($G$27>100,"Confira a porcentagem do componente ativo: o valor não pode passar de 100%.",IF(AND($G$28<>"",NOT(ISNUMBER($G$28))),"A densidade precisa ser um número. Deixe em branco se o produto for sólido.",IF(AND(ISNUMBER($G$28),$G$28<=0),"A densidade deve ser maior que zero. Deixe em branco se o produto for sólido.","")))))))))))))),"Resultado indisponível: existem dados inválidos.")
K14: [Dosagem química] dados válidos? | L14: =$L$13="" -> TRUE
B15: DOSAGEM: 3 FERRAMENTAS EM SEQUÊNCIA | H15: ▲ Voltar ao topo | K15: [Dosagem química] D (arredondado) | L15: =IFERROR(ROUND($G$26,IF($G$26=0,0,4-INT(LOG10(ABS($G$26))))),"") -> 4
B16: Ferramenta 1 calcula a massa de componente ativo. Ferramenta 2 converte em massa de produto comercial. Ferramenta 3 converte em volume de produto líquido (quando houver densidade). | K16: [Dosagem química] D (texto) | L16: =IF(ISNUMBER($L$15),FIXED($L$15,IF(ROUND($L$15,0)=$L$15,0,IF(ROUND($L$15,1)=$L$15,1,IF(ROUND($L$15,2)=$L$15,2,IF(ROUND($L$15,3)=$L$15,3,IF(ROUND($L$15,4)=$L$15,4,IF(ROUND($L$15,5)=$L$15,5,IF(ROUND($L$15,6)=$L$15,6,7)))))))),"?") -> 4
K17: [Dosagem química] Qd (arredondado) | L17: =IFERROR(ROUND($L$5,IF($L$5=0,0,4-INT(LOG10(ABS($L$5))))),"") -> 500
B18: B · ESCOLHA DO CENÁRIO | K18: [Dosagem química] Qd (texto) | L18: =IF(ISNUMBER($L$17),FIXED($L$17,IF(ROUND($L$17,0)=$L$17,0,IF(ROUND($L$17,1)=$L$17,1,IF(ROUND($L$17,2)=$L$17,2,IF(ROUND($L$17,3)=$L$17,3,IF(ROUND($L$17,4)=$L$17,4,IF(ROUND($L$17,5)=$L$17,5,IF(ROUND($L$17,6)=$L$17,6,7)))))))),"?") -> 500
B19: Cenário ▼ | C19: Exemplo 01 | E19: Exemplo 01 e Exemplo 02 usam dados prontos. Meu cálculo usa os valores que você digitar na coluna amarela. | K19: [Dosagem química] ma (arredondado) | L19: =IFERROR(ROUND($L$7,IF($L$7=0,0,4-INT(LOG10(ABS($L$7))))),"") -> 2
K20: [Dosagem química] ma (texto) | L20: =IF(ISNUMBER($L$19),FIXED($L$19,IF(ROUND($L$19,0)=$L$19,0,IF(ROUND($L$19,1)=$L$19,1,IF(ROUND($L$19,2)=$L$19,2,IF(ROUND($L$19,3)=$L$19,3,IF(ROUND($L$19,4)=$L$19,4,IF(ROUND($L$19,5)=$L$19,5,IF(ROUND($L$19,6)=$L$19,6,7)))))))),"?") -> 2
B21: C · DADOS DE ENTRADA | K21: [Dosagem química] mc (arredondado) | L21: =IFERROR(ROUND($L$8,IF($L$8=0,0,4-INT(LOG10(ABS($L$8))))),"") -> 4
B22: Variável | C22: Exemplo 01 | D22: Exemplo 02 | E22: MEU CÁLCULO | F22: Unidade | G22: Valor em uso | H22: Orientação de preenchimento | K22: [Dosagem química] mc (texto) | L22: =IF(ISNUMBER($L$21),FIXED($L$21,IF(ROUND($L$21,0)=$L$21,0,IF(ROUND($L$21,1)=$L$21,1,IF(ROUND($L$21,2)=$L$21,2,IF(ROUND($L$21,3)=$L$21,3,IF(ROUND($L$21,4)=$L$21,4,IF(ROUND($L$21,5)=$L$21,5,IF(ROUND($L$21,6)=$L$21,6,7)))))))),"?") -> 4
B23: Produto (opcional) | C23: Coagulante líquido | D23: Hipoclorito de sódio | F23: texto | G23: =IF($L$3=1,C23,IF($L$3=2,D23,IF($L$3=3,IF(E23="","",E23),""))) -> Coagulante líquido | H23: Nome do produto, só para identificação. | K23: [Dosagem química] pct (arredondado) | L23: =IFERROR(ROUND($G$27,IF($G$27=0,0,4-INT(LOG10(ABS($G$27))))),"") -> 50
B24: Vazão tratada | C24: 500 | D24: 25 | F24: =$G$25 -> m³/dia | G24: =IF($L$3=1,C24,IF($L$3=2,D24,IF($L$3=3,IF(E24="","",E24),""))) -> 500 | H24: Vazão de água ou efluente que recebe o produto. Ex.: 500 | K24: [Dosagem química] pct (texto) | L24: =IF(ISNUMBER($L$23),FIXED($L$23,IF(ROUND($L$23,0)=$L$23,0,IF(ROUND($L$23,1)=$L$23,1,IF(ROUND($L$23,2)=$L$23,2,IF(ROUND($L$23,3)=$L$23,3,IF(ROUND($L$23,4)=$L$23,4,IF(ROUND($L$23,5)=$L$23,5,IF(ROUND($L$23,6)=$L$23,6,7)))))))),"?") -> 50
B25: Unidade da vazão | C25: m³/dia | D25: L/s | E25: m³/dia | F25: lista ▼ | G25: =IF($L$3=1,C25,IF($L$3=2,D25,IF($L$3=3,IF(E25="","",E25),""))) -> m³/dia | H25: Escolha m³/dia, m³/h ou L/s. | K25: [Dosagem química] vol (arredondado) | L25: =IFERROR(ROUND($L$9,IF($L$9=0,0,4-INT(LOG10(ABS($L$9))))),"") -> 3.3333
B26: Dosagem de componente ativo | C26: 4 | D26: 2 | F26: mg/L | G26: =IF($L$3=1,C26,IF($L$3=2,D26,IF($L$3=3,IF(E26="","",E26),""))) -> 4 | H26: Dose de ATIVO desejada, em mg/L. Ex.: 4 | K26: [Dosagem química] vol (texto) | L26: =IF(ISNUMBER($L$25),FIXED($L$25,IF(ROUND($L$25,0)=$L$25,0,IF(ROUND($L$25,1)=$L$25,1,IF(ROUND($L$25,2)=$L$25,2,IF(ROUND($L$25,3)=$L$25,3,IF(ROUND($L$25,4)=$L$25,4,IF(ROUND($L$25,5)=$L$25,5,IF(ROUND($L$25,6)=$L$25,6,7)))))))),"?") -> 3,3333
B27: Componente ativo no produto | C27: 50 | D27: 12 | F27: % | G27: =IF($L$3=1,C27,IF($L$3=2,D27,IF($L$3=3,IF(E27="","",E27),""))) -> 50 | H27: Porcentagem de ativo no produto comercial. Para 50%, digite 50. | K27: [Dosagem química] frac (arredondado) | L27: =IFERROR(ROUND($L$6,IF($L$6=0,0,4-INT(LOG10(ABS($L$6))))),"") -> 0.5
B28: Densidade do produto | C28: 1.2 | D28: 1.2 | F28: kg/L | G28: =IF($L$3=1,C28,IF($L$3=2,D28,IF($L$3=3,IF(E28="","",E28),""))) -> 1.2 | H28: Somente para produto líquido. Deixe em branco se for sólido. Ex.: 1,2 | K28: [Dosagem química] frac (texto) | L28: =IF(ISNUMBER($L$27),FIXED($L$27,IF(ROUND($L$27,0)=$L$27,0,IF(ROUND($L$27,1)=$L$27,1,IF(ROUND($L$27,2)=$L$27,2,IF(ROUND($L$27,3)=$L$27,3,IF(ROUND($L$27,4)=$L$27,4,IF(ROUND($L$27,5)=$L$27,5,IF(ROUND($L$27,6)=$L$27,6,7)))))))),"?") -> 0,5
K29: [Dosagem química] dens (arredondado) | L29: =IFERROR(ROUND($G$28,IF($G$28=0,0,4-INT(LOG10(ABS($G$28))))),"") -> 1.2
B30: D · RESULTADO AUTOMÁTICO | K30: [Dosagem química] dens (texto) | L30: =IF(ISNUMBER($L$29),FIXED($L$29,IF(ROUND($L$29,0)=$L$29,0,IF(ROUND($L$29,1)=$L$29,1,IF(ROUND($L$29,2)=$L$29,2,IF(ROUND($L$29,3)=$L$29,3,IF(ROUND($L$29,4)=$L$29,4,IF(ROUND($L$29,5)=$L$29,5,IF(ROUND($L$29,6)=$L$29,6,7)))))))),"?") -> 1,2
B31: FERRAMENTA 2 · MASSA DE PRODUTO COMERCIAL | E31: OUTROS RESULTADOS | K31: [Dosagem química] Q (arredondado) | L31: =IFERROR(ROUND($G$24,IF($G$24=0,0,4-INT(LOG10(ABS($G$24))))),"") -> 500
B32: =IF($L$14,$L$8,"—") -> 4 | D32: kg/dia | E32: Ferramenta 1 · Massa de ativo | G32: =IF($L$14,$L$7,"—") -> 2 | H32: kg/dia | K32: [Dosagem química] Q (texto) | L32: =IF(ISNUMBER($L$31),FIXED($L$31,IF(ROUND($L$31,0)=$L$31,0,IF(ROUND($L$31,1)=$L$31,1,IF(ROUND($L$31,2)=$L$31,2,IF(ROUND($L$31,3)=$L$31,3,IF(ROUND($L$31,4)=$L$31,4,IF(ROUND($L$31,5)=$L$31,5,IF(ROUND($L$31,6)=$L$31,6,7)))))))),"?") -> 500
E33: Ferramenta 3 · Volume de produto | G33: =IF($L$14,$L$12,"—") -> 3.3333333 | H33: L/dia | K33: [Dosagem química] resumo | L33: =IF($L$14,$L$22&" "&"kg/dia","—") -> 4 kg/dia
E34: Dose em produto comercial | G34: =IF($L$14,$L$10,"—") -> 8 | H34: mg/L
E35: Consumo mensal (30 dias) | G35: =IF($L$14,$L$11,"—") -> 120 | H35: kg/mês
B36: Interpretação | C36: =IF($L$14,"Para dosar "&$L$16&" mg/L de componente ativo em "&$L$18&" m³/dia são necessários "&$L$20&" kg/dia de ativo, que correspondem a "&$L$22&" kg/dia do produto comercial"&IF($G$28="",". Para converter em volume, informe a densidade (somente produto líquido).",", ou cerca de "&$L$26&" L/dia de produto líquido.")&IF($G$27<1," Atenção: você informou "&$L$24&"% de ativo. Se o produto tem 50%, digite 50 (e não 0,5).","")&IF(AND(ISNUMBER($G$28),OR($G$28<0.8,$G$28>2))," Confira a densidade: o valor está fora da faixa comum de produtos líquidos (0,8 a 2,0 kg/L).",""),"Resultado indisponível: corrija o item indicado em Status dos dados.") -> Para dosar 4 mg/L de componente ativo em 500 m³/dia são necessários 2 kg/dia de ativo, que correspondem a 4 kg/dia do produto comercial, ou cerca de 3,3333 L/dia de produto líquido.
B37: Status dos dados | C37: =IF($L$14,"✔ Dados válidos. Resultado calculado automaticamente.","⚠ "&$L$13) -> ✔ Dados válidos. Resultado calculado automaticamente.
B39: E · ENTENDA O CÁLCULO
B40: Ferramenta 1 | C40: Massa ativa (kg/dia) = Q (m³/dia) × D (mg/L) × 0,001
B41: Substituição F1 | C41: =IF($L$14,"Massa ativa = "&$L$18&" × "&$L$16&" × 0,001 = "&$L$20&" kg/dia","Aguardando dados válidos para montar a conta.") -> Massa ativa = 500 × 4 × 0,001 = 2 kg/dia
B42: Ferramenta 2 | C42: Massa comercial = Massa ativa ÷ Fração ativa (50% = 0,50)
B43: Substituição F2 | C43: =IF($L$14,"Fração ativa = "&$L$24&" ÷ 100 = "&$L$28&" → Massa comercial = "&$L$20&" ÷ "&$L$28&" = "&$L$22&" kg/dia","Aguardando dados válidos para montar a conta.") -> Fração ativa = 50 ÷ 100 = 0,5 → Massa comercial = 2 ÷ 0,5 = 4 kg/dia
B44: Ferramenta 3 | C44: Volume (L/dia) = Massa comercial (kg/dia) ÷ Densidade (kg/L)
B45: Substituição F3 | C45: =IF($L$14,IF($G$28="","Sem densidade informada: etapa não aplicável (produto sólido ou densidade desconhecida).","Volume = "&$L$22&" ÷ "&$L$30&" = "&$L$26&" L/dia"),"Aguardando dados válidos para montar a conta.") -> Volume = 4 ÷ 1,2 = 3,3333 L/dia
B46: O que é cada variável | C46: Q = vazão tratada | D = dosagem de componente ATIVO | Fração ativa = porcentagem ÷ 100 | Densidade = massa de 1 litro do produto
B47: Valores inseridos | C47: ="Produto: "&IF($G$23="","não informado",$G$23)&" | "&"Q = "&$L$32&" "&$G$25&" | "&"D = "&$L$16&" "&"mg/L"&" | "&"Ativo = "&$L$24&" "&"%"&" | "&"ρ = "&IF($G$28="","não informada",$L$30&" "&"kg/L") -> Produto: Coagulante líquido | Q = 500 m³/dia | D = 4 mg/L | Ativo = 50 % | ρ = 1,2 kg/L
B49: G · COMPARAÇÃO VISUAL
E50: Dados do gráfico (atualizam sozinhos)
E51: Componente ativo | G51: =IF($L$14,$L$7,"") -> 2 | H51: kg/dia
E52: Produto comercial | G52: =IF($L$14,$L$8,"") -> 4 | H52: kg/dia
E54: O gráfico usa os mesmos resultados do card verde. Mude um dado e veja as barras mudarem.
B65: F · EXEMPLO E ORIENTAÇÃO
B66: Exemplos desta ferramenta | C66: Exemplo 01: Uma ETA trata 500 m³/dia e precisa aplicar 4 mg/L de componente ativo. O produto comercial tem 50% de ativo e densidade de 1,2 kg/L. Exemplo 02: Uma estação desinfeta 25 L/s de água com 2 mg/L de cloro ativo, usando hipoclorito de sódio com 12% de cloro ativo e densidade de 1,20 kg/L. Escolha o exemplo na lista Cenário para ver a resolução completa.
B67: Como interpretar | C67: A dosagem é definida em componente ativo. Como o produto comercial tem só uma parte de ativo, a massa de produto é sempre maior que a massa de ativo.
B68: ⚠ Erro comum | C68: Usar a porcentagem como número inteiro na fórmula (dividir por 50 em vez de 0,50) ou confundir dosagem de ativo com dosagem de produto comercial.
B69: 💡 Dica prática | C69: Não assuma densidade de 1 kg/L. Consulte a ficha técnica (FDS/FISPQ) do produto.
B70: Atenção | C70: Valores teóricos de apoio. A aplicação operacional exige considerar especificações do fabricante, compatibilidade, segurança e critérios técnicos.
B73: Lembrete: os resultados são cálculos teóricos de apoio ao estudo. Confira unidades e hipóteses antes de usar em trabalhos, relatórios ou no estágio.

Sheet 08 — Exemplos Resolvidos
B1: 📚 BIBLIOTECA DE EXEMPLOS RESOLVIDOS | K1: ÁREA TÉCNICA · cálculos auxiliares (não editar)
B2: Estude o passo a passo e depois teste outros valores na calculadora | K2: Descrição | L2: Valor
B3: 🏠 Painel | C3: 📘 Guia | E3: 📚 Exemplos | G3: ◀ Anterior | H3: Próxima aba ▶ | K3: [Ex 1.1] fV | L3: =IFERROR(CHOOSE(MATCH('02 — Vazão e Hidráulica'!$C$31,{"m³","L"},0),1,0.001),"") -> 1
K4: [Ex 1.1] ft | L4: =IFERROR(CHOOSE(MATCH('02 — Vazão e Hidráulica'!$C$33,{"s","min","h","dia"},0),1,60,3600,86400),"") -> 3600
B5: Como estudar: leia a situação, tente resolver sozinho, confira a resolução e depois clique em Abrir na calculadora para testar outros valores. Todos os números desta aba são calculados por fórmulas a partir dos mesmos dados cadastrados nas calculadoras. | K5: [Ex 1.1] Vm | L5: =IFERROR('02 — Vazão e Hidráulica'!$C$30*$L$3,"") -> 360
K6: [Ex 1.1] ts | L6: =IFERROR('02 — Vazão e Hidráulica'!$C$32*$L$4,"") -> 7200
B7: ÍNDICE POR CATEGORIA (clique para ir) | K7: [Ex 1.1] Qs | L7: =IFERROR($L$5/$L$6,"") -> 0.05
B8: 💧 01 · Vazão e Hidráulica | C8: 8 exemplos: Vazão a partir de volume e tempo; Vazão em tubulações; Velocidade do escoamento; Tempo de detenção hidráulica (TDH) | K8: [Ex 1.1] Qh | L8: =IFERROR($L$7*3600,"") -> 180
B9: 🏭 02 · Carga Poluidora | C9: 6 exemplos: Calcular carga poluidora; Descobrir a concentração; Descobrir a vazão | K9: [Ex 1.1] Ql | L9: =IFERROR($L$7*1000,"") -> 50
B10: 📉 03 · Eficiência | C10: 4 exemplos: Eficiência por concentração; Eficiência por carga | K10: [Ex 1.1] Qd | L10: =IFERROR($L$7*86400,"") -> 4320
B11: ⚖️ 04 · Balanço de Massa | C11: 6 exemplos: Mistura de duas correntes; Balanço de massa em decantadores; Acúmulo de massa | K11: [Ex 1.1] V (arredondado) | L11: =IFERROR(ROUND('02 — Vazão e Hidráulica'!$C$30,IF('02 — Vazão e Hidráulica'!$C$30=0,0,4-INT(LOG10(ABS('02 — Vazão e Hidráulica'!$C$30))))),"") -> 360
B12: 🧪 05 · Diluição | C12: 2 exemplos: Diluição: C₁ × V₁ = C₂ × V₂ | K12: [Ex 1.1] V (texto) | L12: =IF(ISNUMBER($L$11),FIXED($L$11,IF(ROUND($L$11,0)=$L$11,0,IF(ROUND($L$11,1)=$L$11,1,IF(ROUND($L$11,2)=$L$11,2,IF(ROUND($L$11,3)=$L$11,3,IF(ROUND($L$11,4)=$L$11,4,IF(ROUND($L$11,5)=$L$11,5,IF(ROUND($L$11,6)=$L$11,6,7)))))))),"?") -> 360
B13: ⚗️ 06 · Dosagem Química | C13: 2 exemplos: Dosagem: 3 ferramentas em sequência | K13: [Ex 1.1] t (arredondado) | L13: =IFERROR(ROUND('02 — Vazão e Hidráulica'!$C$32,IF('02 — Vazão e Hidráulica'!$C$32=0,0,4-INT(LOG10(ABS('02 — Vazão e Hidráulica'!$C$32))))),"") -> 2
K14: [Ex 1.1] t (texto) | L14: =IF(ISNUMBER($L$13),FIXED($L$13,IF(ROUND($L$13,0)=$L$13,0,IF(ROUND($L$13,1)=$L$13,1,IF(ROUND($L$13,2)=$L$13,2,IF(ROUND($L$13,3)=$L$13,3,IF(ROUND($L$13,4)=$L$13,4,IF(ROUND($L$13,5)=$L$13,5,IF(ROUND($L$13,6)=$L$13,6,7)))))))),"?") -> 2
B15: 💧 CALCULADORA 01 · VAZÃO E HIDRÁULICA | H15: ▲ Voltar ao índice | K15: [Ex 1.1] Qs (arredondado) | L15: =IFERROR(ROUND($L$7,IF($L$7=0,0,4-INT(LOG10(ABS($L$7))))),"") -> 0.05
K16: [Ex 1.1] Qs (texto) | L16: =IF(ISNUMBER($L$15),FIXED($L$15,IF(ROUND($L$15,0)=$L$15,0,IF(ROUND($L$15,1)=$L$15,1,IF(ROUND($L$15,2)=$L$15,2,IF(ROUND($L$15,3)=$L$15,3,IF(ROUND($L$15,4)=$L$15,4,IF(ROUND($L$15,5)=$L$15,5,IF(ROUND($L$15,6)=$L$15,6,7)))))))),"?") -> 0,05
B17: EXEMPLO 1.1 · Enchimento de tanque por bomba | G17: ▶ Abrir na calculadora | K17: [Ex 1.1] Vm (arredondado) | L17: =IFERROR(ROUND($L$5,IF($L$5=0,0,4-INT(LOG10(ABS($L$5))))),"") -> 360
B18: Situação prática | C18: Uma bomba enche um tanque de 360 m³ em 2 horas. Qual é a vazão da bomba? | K18: [Ex 1.1] Vm (texto) | L18: =IF(ISNUMBER($L$17),FIXED($L$17,IF(ROUND($L$17,0)=$L$17,0,IF(ROUND($L$17,1)=$L$17,1,IF(ROUND($L$17,2)=$L$17,2,IF(ROUND($L$17,3)=$L$17,3,IF(ROUND($L$17,4)=$L$17,4,IF(ROUND($L$17,5)=$L$17,5,IF(ROUND($L$17,6)=$L$17,6,7)))))))),"?") -> 360
B19: Dados utilizados | C19: ="V = "&$L$12&" "&'02 — Vazão e Hidráulica'!$C$31&" | "&"t = "&$L$14&" "&'02 — Vazão e Hidráulica'!$C$33 -> V = 360 m³ | t = 2 h | K19: [Ex 1.1] ts (arredondado) | L19: =IFERROR(ROUND($L$6,IF($L$6=0,0,4-INT(LOG10(ABS($L$6))))),"") -> 7200
B20: Fórmula | C20: Q = V ÷ t | K20: [Ex 1.1] ts (texto) | L20: =IF(ISNUMBER($L$19),FIXED($L$19,IF(ROUND($L$19,0)=$L$19,0,IF(ROUND($L$19,1)=$L$19,1,IF(ROUND($L$19,2)=$L$19,2,IF(ROUND($L$19,3)=$L$19,3,IF(ROUND($L$19,4)=$L$19,4,IF(ROUND($L$19,5)=$L$19,5,IF(ROUND($L$19,6)=$L$19,6,7)))))))),"?") -> 7.200
B21: Substituição | C21: ="Convertendo para o SI: V = "&$L$18&" m³ e t = "&$L$20&" s."&CHAR(10)&"Q = "&$L$18&" ÷ "&$L$20&" = "&$L$16&" m³/s" -> Convertendo para o SI: V = 360 m³ e t = 7.200 s. Q = 360 ÷ 7.200 = 0,05 m³/s | K21: [Ex 1.1] Qd (arredondado) | L21: =IFERROR(ROUND($L$10,IF($L$10=0,0,4-INT(LOG10(ABS($L$10))))),"") -> 4320
B22: Resolução | C22: ="1) Converter para o SI: V = "&$L$18&" m³ e t = "&$L$20&" s."&CHAR(10)&"2) Q = V ÷ t = "&$L$18&" ÷ "&$L$20&" = "&$L$16&" m³/s."&CHAR(10)&"3) Converter: × 1000 = "&$L$26&" L/s; × 3600 = "&$L$24&" m³/h; × 86400 = "&$L$22&" m³/dia." -> 1) Converter para o SI: V = 360 m³ e t = 7.200 s. 2) Q = V ÷ t = 360 ÷ 7.200 = 0,05 m³/s. 3) Converter: × 1000 = 50 L/s; × 3600 = 180 m³/h; × 86400 = 4.320 m³/dia. | K22: [Ex 1.1] Qd (texto) | L22: =IF(ISNUMBER($L$21),FIXED($L$21,IF(ROUND($L$21,0)=$L$21,0,IF(ROUND($L$21,1)=$L$21,1,IF(ROUND($L$21,2)=$L$21,2,IF(ROUND($L$21,3)=$L$21,3,IF(ROUND($L$21,4)=$L$21,4,IF(ROUND($L$21,5)=$L$21,5,IF(ROUND($L$21,6)=$L$21,6,7)))))))),"?") -> 4.320
B23: Resultado | C23: ="Q = "&$L$24&" m³/h = "&$L$26&" L/s = "&$L$16&" m³/s" -> Q = 180 m³/h = 50 L/s = 0,05 m³/s | K23: [Ex 1.1] Qh (arredondado) | L23: =IFERROR(ROUND($L$8,IF($L$8=0,0,4-INT(LOG10(ABS($L$8))))),"") -> 180
B24: Explicação simples | C24: ="A cada hora passam "&$L$24&" m³ de líquido. Isso é o mesmo que "&$L$26&" litros por segundo, ou "&$L$22&" m³ por dia." -> A cada hora passam 180 m³ de líquido. Isso é o mesmo que 50 litros por segundo, ou 4.320 m³ por dia. | K24: [Ex 1.1] Qh (texto) | L24: =IF(ISNUMBER($L$23),FIXED($L$23,IF(ROUND($L$23,0)=$L$23,0,IF(ROUND($L$23,1)=$L$23,1,IF(ROUND($L$23,2)=$L$23,2,IF(ROUND($L$23,3)=$L$23,3,IF(ROUND($L$23,4)=$L$23,4,IF(ROUND($L$23,5)=$L$23,5,IF(ROUND($L$23,6)=$L$23,6,7)))))))),"?") -> 180
B25: Teste na calculadora | C25: Na aba 02 — Vazão e Hidráulica, vá até a Ferramenta 1 e escolha Exemplo 01 na lista Cenário. Depois troque para Meu cálculo e teste outros valores. | K25: [Ex 1.1] Ql (arredondado) | L25: =IFERROR(ROUND($L$9,IF($L$9=0,0,4-INT(LOG10(ABS($L$9))))),"") -> 50
K26: [Ex 1.1] Ql (texto) | L26: =IF(ISNUMBER($L$25),FIXED($L$25,IF(ROUND($L$25,0)=$L$25,0,IF(ROUND($L$25,1)=$L$25,1,IF(ROUND($L$25,2)=$L$25,2,IF(ROUND($L$25,3)=$L$25,3,IF(ROUND($L$25,4)=$L$25,4,IF(ROUND($L$25,5)=$L$25,5,IF(ROUND($L$25,6)=$L$25,6,7)))))))),"?") -> 50
B27: EXEMPLO 1.2 · Esvaziamento de reservatório | G27: ▶ Abrir na calculadora | K27: [Ex 1.2] fV | L27: =IFERROR(CHOOSE(MATCH('02 — Vazão e Hidráulica'!$D$31,{"m³","L"},0),1,0.001),"") -> 0.001
B28: Situação prática | C28: Um reservatório com 15.000 litros foi esvaziado em 25 minutos. Qual foi a vazão média de saída? | K28: [Ex 1.2] ft | L28: =IFERROR(CHOOSE(MATCH('02 — Vazão e Hidráulica'!$D$33,{"s","min","h","dia"},0),1,60,3600,86400),"") -> 60
B29: Dados utilizados | C29: ="V = "&$L$36&" "&'02 — Vazão e Hidráulica'!$D$31&" | "&"t = "&$L$38&" "&'02 — Vazão e Hidráulica'!$D$33 -> V = 15.000 L | t = 25 min | K29: [Ex 1.2] Vm | L29: =IFERROR('02 — Vazão e Hidráulica'!$D$30*$L$27,"") -> 15
B30: Fórmula | C30: Q = V ÷ t | K30: [Ex 1.2] ts | L30: =IFERROR('02 — Vazão e Hidráulica'!$D$32*$L$28,"") -> 1500
B31: Substituição | C31: ="Convertendo para o SI: V = "&$L$42&" m³ e t = "&$L$44&" s."&CHAR(10)&"Q = "&$L$42&" ÷ "&$L$44&" = "&$L$40&" m³/s" -> Convertendo para o SI: V = 15 m³ e t = 1.500 s. Q = 15 ÷ 1.500 = 0,01 m³/s | K31: [Ex 1.2] Qs | L31: =IFERROR($L$29/$L$30,"") -> 0.01
B32: Resolução | C32: ="1) Converter para o SI: V = "&$L$42&" m³ e t = "&$L$44&" s."&CHAR(10)&"2) Q = V ÷ t = "&$L$42&" ÷ "&$L$44&" = "&$L$40&" m³/s."&CHAR(10)&"3) Converter: × 1000 = "&$L$50&" L/s; × 3600 = "&$L$48&" m³/h; × 86400 = "&$L$46&" m³/dia." -> 1) Converter para o SI: V = 15 m³ e t = 1.500 s. 2) Q = V ÷ t = 15 ÷ 1.500 = 0,01 m³/s. 3) Converter: × 1000 = 10 L/s; × 3600 = 36 m³/h; × 86400 = 864 m³/dia. | K32: [Ex 1.2] Qh | L32: =IFERROR($L$31*3600,"") -> 36
B33: Resultado | C33: ="Q = "&$L$48&" m³/h = "&$L$50&" L/s = "&$L$40&" m³/s" -> Q = 36 m³/h = 10 L/s = 0,01 m³/s | K33: [Ex 1.2] Ql | L33: =IFERROR($L$31*1000,"") -> 10
B34: Explicação simples | C34: ="A cada hora passam "&$L$48&" m³ de líquido. Isso é o mesmo que "&$L$50&" litros por segundo, ou "&$L$46&" m³ por dia." -> A cada hora passam 36 m³ de líquido. Isso é o mesmo que 10 litros por segundo, ou 864 m³ por dia. | K34: [Ex 1.2] Qd | L34: =IFERROR($L$31*86400,"") -> 864
B35: Teste na calculadora | C35: Na aba 02 — Vazão e Hidráulica, vá até a Ferramenta 1 e escolha Exemplo 02 na lista Cenário. Depois troque para Meu cálculo e teste outros valores. | K35: [Ex 1.2] V (arredondado) | L35: =IFERROR(ROUND('02 — Vazão e Hidráulica'!$D$30,IF('02 — Vazão e Hidráulica'!$D$30=0,0,4-INT(LOG10(ABS('02 — Vazão e Hidráulica'!$D$30))))),"") -> 15000
K36: [Ex 1.2] V (texto) | L36: =IF(ISNUMBER($L$35),FIXED($L$35,IF(ROUND($L$35,0)=$L$35,0,IF(ROUND($L$35,1)=$L$35,1,IF(ROUND($L$35,2)=$L$35,2,IF(ROUND($L$35,3)=$L$35,3,IF(ROUND($L$35,4)=$L$35,4,IF(ROUND($L$35,5)=$L$35,5,IF(ROUND($L$35,6)=$L$35,6,7)))))))),"?") -> 15.000
B37: EXEMPLO 1.3 · Adutora de água tratada | G37: ▶ Abrir na calculadora | K37: [Ex 1.2] t (arredondado) | L37: =IFERROR(ROUND('02 — Vazão e Hidráulica'!$D$32,IF('02 — Vazão e Hidráulica'!$D$32=0,0,4-INT(LOG10(ABS('02 — Vazão e Hidráulica'!$D$32))))),"") -> 25
B38: Situação prática | C38: Uma adutora tem diâmetro interno de 0,30 m e a água escoa a 1,5 m/s. Qual é a vazão transportada? | K38: [Ex 1.2] t (texto) | L38: =IF(ISNUMBER($L$37),FIXED($L$37,IF(ROUND($L$37,0)=$L$37,0,IF(ROUND($L$37,1)=$L$37,1,IF(ROUND($L$37,2)=$L$37,2,IF(ROUND($L$37,3)=$L$37,3,IF(ROUND($L$37,4)=$L$37,4,IF(ROUND($L$37,5)=$L$37,5,IF(ROUND($L$37,6)=$L$37,6,7)))))))),"?") -> 25
B39: Dados utilizados | C39: ="D = "&$L$58&" "&'02 — Vazão e Hidráulica'!$C$67&" | "&"v = "&$L$60&" "&"m/s" -> D = 0,3 m | v = 1,5 m/s | K39: [Ex 1.2] Qs (arredondado) | L39: =IFERROR(ROUND($L$31,IF($L$31=0,0,4-INT(LOG10(ABS($L$31))))),"") -> 0.01
B40: Fórmula | C40: Q = A × v, com A = π × D² ÷ 4 | K40: [Ex 1.2] Qs (texto) | L40: =IF(ISNUMBER($L$39),FIXED($L$39,IF(ROUND($L$39,0)=$L$39,0,IF(ROUND($L$39,1)=$L$39,1,IF(ROUND($L$39,2)=$L$39,2,IF(ROUND($L$39,3)=$L$39,3,IF(ROUND($L$39,4)=$L$39,4,IF(ROUND($L$39,5)=$L$39,5,IF(ROUND($L$39,6)=$L$39,6,7)))))))),"?") -> 0,01
B41: Substituição | C41: ="D em metros = "&$L$64&" m."&CHAR(10)&"A = π × "&$L$64&"² ÷ 4 = "&$L$62&" m² → Q = "&$L$62&" × "&$L$60&" = "&$L$66&" m³/s" -> D em metros = 0,3 m. A = π × 0,3² ÷ 4 = 0,070686 m² → Q = 0,070686 × 1,5 = 0,10603 m³/s | K41: [Ex 1.2] Vm (arredondado) | L41: =IFERROR(ROUND($L$29,IF($L$29=0,0,4-INT(LOG10(ABS($L$29))))),"") -> 15
B42: Resolução | C42: ="1) Diâmetro em metros: D = "&$L$64&" m."&CHAR(10)&"2) Área: A = π × "&$L$64&"² ÷ 4 = "&$L$62&" m²."&CHAR(10)&"3) Vazão: Q = A × v = "&$L$62&" × "&$L$60&" = "&$L$66&" m³/s (× 1000 = "&$L$68&" L/s)." -> 1) Diâmetro em metros: D = 0,3 m. 2) Área: A = π × 0,3² ÷ 4 = 0,070686 m². 3) Vazão: Q = A × v = 0,070686 × 1,5 = 0,10603 m³/s (× 1000 = 106,03 L/s). | K42: [Ex 1.2] Vm (texto) | L42: =IF(ISNUMBER($L$41),FIXED($L$41,IF(ROUND($L$41,0)=$L$41,0,IF(ROUND($L$41,1)=$L$41,1,IF(ROUND($L$41,2)=$L$41,2,IF(ROUND($L$41,3)=$L$41,3,IF(ROUND($L$41,4)=$L$41,4,IF(ROUND($L$41,5)=$L$41,5,IF(ROUND($L$41,6)=$L$41,6,7)))))))),"?") -> 15
B43: Resultado | C43: ="A = "&$L$62&" m² | Q = "&$L$66&" m³/s = "&$L$68&" L/s" -> A = 0,070686 m² | Q = 0,10603 m³/s = 106,03 L/s | K43: [Ex 1.2] ts (arredondado) | L43: =IFERROR(ROUND($L$30,IF($L$30=0,0,4-INT(LOG10(ABS($L$30))))),"") -> 1500
B44: Explicação simples | C44: ="Pela seção de "&$L$62&" m² passam "&$L$68&" litros por segundo."&IF(OR('02 — Vazão e Hidráulica'!$C$68<0.6,'02 — Vazão e Hidráulica'!$C$68>3)," Atenção: a velocidade informada está fora da faixa de referência usual em tubulações de água (cerca de 0,6 a 3 m/s). Confira o dado.","") -> Pela seção de 0,070686 m² passam 106,03 litros por segundo. | K44: [Ex 1.2] ts (texto) | L44: =IF(ISNUMBER($L$43),FIXED($L$43,IF(ROUND($L$43,0)=$L$43,0,IF(ROUND($L$43,1)=$L$43,1,IF(ROUND($L$43,2)=$L$43,2,IF(ROUND($L$43,3)=$L$43,3,IF(ROUND($L$43,4)=$L$43,4,IF(ROUND($L$43,5)=$L$43,5,IF(ROUND($L$43,6)=$L$43,6,7)))))))),"?") -> 1.500
B45: Teste na calculadora | C45: Na aba 02 — Vazão e Hidráulica, vá até a Ferramenta 2 e escolha Exemplo 01 na lista Cenário. Depois troque para Meu cálculo e teste outros valores. | K45: [Ex 1.2] Qd (arredondado) | L45: =IFERROR(ROUND($L$34,IF($L$34=0,0,4-INT(LOG10(ABS($L$34))))),"") -> 864
K46: [Ex 1.2] Qd (texto) | L46: =IF(ISNUMBER($L$45),FIXED($L$45,IF(ROUND($L$45,0)=$L$45,0,IF(ROUND($L$45,1)=$L$45,1,IF(ROUND($L$45,2)=$L$45,2,IF(ROUND($L$45,3)=$L$45,3,IF(ROUND($L$45,4)=$L$45,4,IF(ROUND($L$45,5)=$L$45,5,IF(ROUND($L$45,6)=$L$45,6,7)))))))),"?") -> 864
B47: EXEMPLO 1.4 · Tubo de esgoto tratado | G47: ▶ Abrir na calculadora | K47: [Ex 1.2] Qh (arredondado) | L47: =IFERROR(ROUND($L$32,IF($L$32=0,0,4-INT(LOG10(ABS($L$32))))),"") -> 36
B48: Situação prática | C48: Um tubo com 150 mm de diâmetro interno conduz esgoto tratado a 0,8 m/s. Qual é a vazão? | K48: [Ex 1.2] Qh (texto) | L48: =IF(ISNUMBER($L$47),FIXED($L$47,IF(ROUND($L$47,0)=$L$47,0,IF(ROUND($L$47,1)=$L$47,1,IF(ROUND($L$47,2)=$L$47,2,IF(ROUND($L$47,3)=$L$47,3,IF(ROUND($L$47,4)=$L$47,4,IF(ROUND($L$47,5)=$L$47,5,IF(ROUND($L$47,6)=$L$47,6,7)))))))),"?") -> 36
B49: Dados utilizados | C49: ="D = "&$L$76&" "&'02 — Vazão e Hidráulica'!$D$67&" | "&"v = "&$L$78&" "&"m/s" -> D = 150 mm | v = 0,8 m/s | K49: [Ex 1.2] Ql (arredondado) | L49: =IFERROR(ROUND($L$33,IF($L$33=0,0,4-INT(LOG10(ABS($L$33))))),"") -> 10
B50: Fórmula | C50: Q = A × v, com A = π × D² ÷ 4 | K50: [Ex 1.2] Ql (texto) | L50: =IF(ISNUMBER($L$49),FIXED($L$49,IF(ROUND($L$49,0)=$L$49,0,IF(ROUND($L$49,1)=$L$49,1,IF(ROUND($L$49,2)=$L$49,2,IF(ROUND($L$49,3)=$L$49,3,IF(ROUND($L$49,4)=$L$49,4,IF(ROUND($L$49,5)=$L$49,5,IF(ROUND($L$49,6)=$L$49,6,7)))))))),"?") -> 10
B51: Substituição | C51: ="D em metros = "&$L$82&" m."&CHAR(10)&"A = π × "&$L$82&"² ÷ 4 = "&$L$80&" m² → Q = "&$L$80&" × "&$L$78&" = "&$L$84&" m³/s" -> D em metros = 0,15 m. A = π × 0,15² ÷ 4 = 0,017671 m² → Q = 0,017671 × 0,8 = 0,014137 m³/s | K51: [Ex 1.3] fD | L51: =IFERROR(CHOOSE(MATCH('02 — Vazão e Hidráulica'!$C$67,{"m","cm","mm","pol"},0),1,0.01,0.001,0.0254),"") -> 1
B52: Resolução | C52: ="1) Diâmetro em metros: D = "&$L$82&" m."&CHAR(10)&"2) Área: A = π × "&$L$82&"² ÷ 4 = "&$L$80&" m²."&CHAR(10)&"3) Vazão: Q = A × v = "&$L$80&" × "&$L$78&" = "&$L$84&" m³/s (× 1000 = "&$L$86&" L/s)." -> 1) Diâmetro em metros: D = 0,15 m. 2) Área: A = π × 0,15² ÷ 4 = 0,017671 m². 3) Vazão: Q = A × v = 0,017671 × 0,8 = 0,014137 m³/s (× 1000 = 14,137 L/s). | K52: [Ex 1.3] Dm | L52: =IFERROR('02 — Vazão e Hidráulica'!$C$66*$L$51,"") -> 0.3
B53: Resultado | C53: ="A = "&$L$80&" m² | Q = "&$L$84&" m³/s = "&$L$86&" L/s" -> A = 0,017671 m² | Q = 0,014137 m³/s = 14,137 L/s | K53: [Ex 1.3] A | L53: =IFERROR(PI()*$L$52^2/4,"") -> 0.070685835
B54: Explicação simples | C54: ="Pela seção de "&$L$80&" m² passam "&$L$86&" litros por segundo."&IF(OR('02 — Vazão e Hidráulica'!$D$68<0.6,'02 — Vazão e Hidráulica'!$D$68>3)," Atenção: a velocidade informada está fora da faixa de referência usual em tubulações de água (cerca de 0,6 a 3 m/s). Confira o dado.","") -> Pela seção de 0,017671 m² passam 14,137 litros por segundo. | K54: [Ex 1.3] Q | L54: =IFERROR($L$53*'02 — Vazão e Hidráulica'!$C$68,"") -> 0.10602875
B55: Teste na calculadora | C55: Na aba 02 — Vazão e Hidráulica, vá até a Ferramenta 2 e escolha Exemplo 02 na lista Cenário. Depois troque para Meu cálculo e teste outros valores. | K55: [Ex 1.3] Ql | L55: =IFERROR($L$54*1000,"") -> 106.02875
K56: [Ex 1.3] Qh | L56: =IFERROR($L$54*3600,"") -> 381.70351
B57: EXEMPLO 1.5 · Velocidade em uma tubulação de 0,20 m | G57: ▶ Abrir na calculadora | K57: [Ex 1.3] D (arredondado) | L57: =IFERROR(ROUND('02 — Vazão e Hidráulica'!$C$66,IF('02 — Vazão e Hidráulica'!$C$66=0,0,4-INT(LOG10(ABS('02 — Vazão e Hidráulica'!$C$66))))),"") -> 0.3
B58: Situação prática | C58: Uma tubulação de 0,20 m de diâmetro interno transporta 0,05 m³/s. Qual é a velocidade média? | K58: [Ex 1.3] D (texto) | L58: =IF(ISNUMBER($L$57),FIXED($L$57,IF(ROUND($L$57,0)=$L$57,0,IF(ROUND($L$57,1)=$L$57,1,IF(ROUND($L$57,2)=$L$57,2,IF(ROUND($L$57,3)=$L$57,3,IF(ROUND($L$57,4)=$L$57,4,IF(ROUND($L$57,5)=$L$57,5,IF(ROUND($L$57,6)=$L$57,6,7)))))))),"?") -> 0,3
B59: Dados utilizados | C59: ="Q = "&$L$96&" "&'02 — Vazão e Hidráulica'!$C$102&" | "&"D = "&$L$94&" "&'02 — Vazão e Hidráulica'!$C$104 -> Q = 0,05 m³/s | D = 0,2 m | K59: [Ex 1.3] v (arredondado) | L59: =IFERROR(ROUND('02 — Vazão e Hidráulica'!$C$68,IF('02 — Vazão e Hidráulica'!$C$68=0,0,4-INT(LOG10(ABS('02 — Vazão e Hidráulica'!$C$68))))),"") -> 1.5
B60: Fórmula | C60: v = Q ÷ A, com A = π × D² ÷ 4 | K60: [Ex 1.3] v (texto) | L60: =IF(ISNUMBER($L$59),FIXED($L$59,IF(ROUND($L$59,0)=$L$59,0,IF(ROUND($L$59,1)=$L$59,1,IF(ROUND($L$59,2)=$L$59,2,IF(ROUND($L$59,3)=$L$59,3,IF(ROUND($L$59,4)=$L$59,4,IF(ROUND($L$59,5)=$L$59,5,IF(ROUND($L$59,6)=$L$59,6,7)))))))),"?") -> 1,5
B61: Substituição | C61: ="Q = "&$L$102&" m³/s e D = "&$L$100&" m."&CHAR(10)&"A = π × "&$L$100&"² ÷ 4 = "&$L$98&" m² → v = "&$L$102&" ÷ "&$L$98&" = "&$L$104&" m/s" -> Q = 0,05 m³/s e D = 0,2 m. A = π × 0,2² ÷ 4 = 0,031416 m² → v = 0,05 ÷ 0,031416 = 1,5915 m/s | K61: [Ex 1.3] A (arredondado) | L61: =IFERROR(ROUND($L$53,IF($L$53=0,0,4-INT(LOG10(ABS($L$53))))),"") -> 0.070686
B62: Resolução | C62: ="1) Converter: Q = "&$L$102&" m³/s e D = "&$L$100&" m."&CHAR(10)&"2) Área: A = π × "&$L$100&"² ÷ 4 = "&$L$98&" m²."&CHAR(10)&"3) Velocidade: v = Q ÷ A = "&$L$102&" ÷ "&$L$98&" = "&$L$104&" m/s." -> 1) Converter: Q = 0,05 m³/s e D = 0,2 m. 2) Área: A = π × 0,2² ÷ 4 = 0,031416 m². 3) Velocidade: v = Q ÷ A = 0,05 ÷ 0,031416 = 1,5915 m/s. | K62: [Ex 1.3] A (texto) | L62: =IF(ISNUMBER($L$61),FIXED($L$61,IF(ROUND($L$61,0)=$L$61,0,IF(ROUND($L$61,1)=$L$61,1,IF(ROUND($L$61,2)=$L$61,2,IF(ROUND($L$61,3)=$L$61,3,IF(ROUND($L$61,4)=$L$61,4,IF(ROUND($L$61,5)=$L$61,5,IF(ROUND($L$61,6)=$L$61,6,7)))))))),"?") -> 0,070686
B63: Resultado | C63: ="v = "&$L$104&" m/s" -> v = 1,5915 m/s | K63: [Ex 1.3] Dm (arredondado) | L63: =IFERROR(ROUND($L$52,IF($L$52=0,0,4-INT(LOG10(ABS($L$52))))),"") -> 0.3
B64: Explicação simples | C64: ="O líquido percorre "&$L$104&" metros a cada segundo dentro do tubo."&IF($L$92<0.6," A velocidade está abaixo de 0,6 m/s: valores baixos favorecem o depósito de sólidos.",IF($L$92>3," A velocidade está acima de 3 m/s: valores altos aumentam a perda de carga e o risco de golpe de aríete."," A velocidade está dentro da faixa de referência usual (cerca de 0,6 a 3 m/s).")) -> O líquido percorre 1,5915 metros a cada segundo dentro do tubo. A velocidade está dentro da faixa de referência usual (cerca de 0,6 a 3 m/s). | K64: [Ex 1.3] Dm (texto) | L64: =IF(ISNUMBER($L$63),FIXED($L$63,IF(ROUND($L$63,0)=$L$63,0,IF(ROUND($L$63,1)=$L$63,1,IF(ROUND($L$63,2)=$L$63,2,IF(ROUND($L$63,3)=$L$63,3,IF(ROUND($L$63,4)=$L$63,4,IF(ROUND($L$63,5)=$L$63,5,IF(ROUND($L$63,6)=$L$63,6,7)))))))),"?") -> 0,3
B65: Teste na calculadora | C65: Na aba 02 — Vazão e Hidráulica, vá até a Ferramenta 3 e escolha Exemplo 01 na lista Cenário. Depois troque para Meu cálculo e teste outros valores. | K65: [Ex 1.3] Q (arredondado) | L65: =IFERROR(ROUND($L$54,IF($L$54=0,0,4-INT(LOG10(ABS($L$54))))),"") -> 0.10603
K66: [Ex 1.3] Q (texto) | L66: =IF(ISNUMBER($L$65),FIXED($L$65,IF(ROUND($L$65,0)=$L$65,0,IF(ROUND($L$65,1)=$L$65,1,IF(ROUND($L$65,2)=$L$65,2,IF(ROUND($L$65,3)=$L$65,3,IF(ROUND($L$65,4)=$L$65,4,IF(ROUND($L$65,5)=$L$65,5,IF(ROUND($L$65,6)=$L$65,6,7)))))))),"?") -> 0,10603
B67: EXEMPLO 1.6 · Linha de recalque de 100 mm | G67: ▶ Abrir na calculadora | K67: [Ex 1.3] Ql (arredondado) | L67: =IFERROR(ROUND($L$55,IF($L$55=0,0,4-INT(LOG10(ABS($L$55))))),"") -> 106.03
B68: Situação prática | C68: Uma linha de recalque com 100 mm de diâmetro interno recebe 20 L/s. Qual é a velocidade? | K68: [Ex 1.3] Ql (texto) | L68: =IF(ISNUMBER($L$67),FIXED($L$67,IF(ROUND($L$67,0)=$L$67,0,IF(ROUND($L$67,1)=$L$67,1,IF(ROUND($L$67,2)=$L$67,2,IF(ROUND($L$67,3)=$L$67,3,IF(ROUND($L$67,4)=$L$67,4,IF(ROUND($L$67,5)=$L$67,5,IF(ROUND($L$67,6)=$L$67,6,7)))))))),"?") -> 106,03
B69: Dados utilizados | C69: ="Q = "&$L$114&" "&'02 — Vazão e Hidráulica'!$D$102&" | "&"D = "&$L$112&" "&'02 — Vazão e Hidráulica'!$D$104 -> Q = 20 L/s | D = 100 mm | K69: [Ex 1.4] fD | L69: =IFERROR(CHOOSE(MATCH('02 — Vazão e Hidráulica'!$D$67,{"m","cm","mm","pol"},0),1,0.01,0.001,0.0254),"") -> 0.001
B70: Fórmula | C70: v = Q ÷ A, com A = π × D² ÷ 4 | K70: [Ex 1.4] Dm | L70: =IFERROR('02 — Vazão e Hidráulica'!$D$66*$L$69,"") -> 0.15
B71: Substituição | C71: ="Q = "&$L$120&" m³/s e D = "&$L$118&" m."&CHAR(10)&"A = π × "&$L$118&"² ÷ 4 = "&$L$116&" m² → v = "&$L$120&" ÷ "&$L$116&" = "&$L$122&" m/s" -> Q = 0,02 m³/s e D = 0,1 m. A = π × 0,1² ÷ 4 = 0,007854 m² → v = 0,02 ÷ 0,007854 = 2,5465 m/s | K71: [Ex 1.4] A | L71: =IFERROR(PI()*$L$70^2/4,"") -> 0.017671459
B72: Resolução | C72: ="1) Converter: Q = "&$L$120&" m³/s e D = "&$L$118&" m."&CHAR(10)&"2) Área: A = π × "&$L$118&"² ÷ 4 = "&$L$116&" m²."&CHAR(10)&"3) Velocidade: v = Q ÷ A = "&$L$120&" ÷ "&$L$116&" = "&$L$122&" m/s." -> 1) Converter: Q = 0,02 m³/s e D = 0,1 m. 2) Área: A = π × 0,1² ÷ 4 = 0,007854 m². 3) Velocidade: v = Q ÷ A = 0,02 ÷ 0,007854 = 2,5465 m/s. | K72: [Ex 1.4] Q | L72: =IFERROR($L$71*'02 — Vazão e Hidráulica'!$D$68,"") -> 0.014137167
B73: Resultado | C73: ="v = "&$L$122&" m/s" -> v = 2,5465 m/s | K73: [Ex 1.4] Ql | L73: =IFERROR($L$72*1000,"") -> 14.137167
B74: Explicação simples | C74: ="O líquido percorre "&$L$122&" metros a cada segundo dentro do tubo."&IF($L$110<0.6," A velocidade está abaixo de 0,6 m/s: valores baixos favorecem o depósito de sólidos.",IF($L$110>3," A velocidade está acima de 3 m/s: valores altos aumentam a perda de carga e o risco de golpe de aríete."," A velocidade está dentro da faixa de referência usual (cerca de 0,6 a 3 m/s).")) -> O líquido percorre 2,5465 metros a cada segundo dentro do tubo. A velocidade está dentro da faixa de referência usual (cerca de 0,6 a 3 m/s). | K74: [Ex 1.4] Qh | L74: =IFERROR($L$72*3600,"") -> 50.893801
B75: Teste na calculadora | C75: Na aba 02 — Vazão e Hidráulica, vá até a Ferramenta 3 e escolha Exemplo 02 na lista Cenário. Depois troque para Meu cálculo e teste outros valores. | K75: [Ex 1.4] D (arredondado) | L75: =IFERROR(ROUND('02 — Vazão e Hidráulica'!$D$66,IF('02 — Vazão e Hidráulica'!$D$66=0,0,4-INT(LOG10(ABS('02 — Vazão e Hidráulica'!$D$66))))),"") -> 150
K76: [Ex 1.4] D (texto) | L76: =IF(ISNUMBER($L$75),FIXED($L$75,IF(ROUND($L$75,0)=$L$75,0,IF(ROUND($L$75,1)=$L$75,1,IF(ROUND($L$75,2)=$L$75,2,IF(ROUND($L$75,3)=$L$75,3,IF(ROUND($L$75,4)=$L$75,4,IF(ROUND($L$75,5)=$L$75,5,IF(ROUND($L$75,6)=$L$75,6,7)))))))),"?") -> 150
B77: EXEMPLO 1.7 · Tanque de equalização | G77: ▶ Abrir na calculadora | K77: [Ex 1.4] v (arredondado) | L77: =IFERROR(ROUND('02 — Vazão e Hidráulica'!$D$68,IF('02 — Vazão e Hidráulica'!$D$68=0,0,4-INT(LOG10(ABS('02 — Vazão e Hidráulica'!$D$68))))),"") -> 0.8
B78: Situação prática | C78: Um tanque de equalização tem volume útil de 500 m³ e recebe 50 m³/h. Quanto tempo o efluente fica no tanque? | K78: [Ex 1.4] v (texto) | L78: =IF(ISNUMBER($L$77),FIXED($L$77,IF(ROUND($L$77,0)=$L$77,0,IF(ROUND($L$77,1)=$L$77,1,IF(ROUND($L$77,2)=$L$77,2,IF(ROUND($L$77,3)=$L$77,3,IF(ROUND($L$77,4)=$L$77,4,IF(ROUND($L$77,5)=$L$77,5,IF(ROUND($L$77,6)=$L$77,6,7)))))))),"?") -> 0,8
B79: Dados utilizados | C79: ="V = "&$L$133&" "&'02 — Vazão e Hidráulica'!$C$138&" | "&"Q = "&$L$131&" "&'02 — Vazão e Hidráulica'!$C$140 -> V = 500 m³ | Q = 50 m³/h | K79: [Ex 1.4] A (arredondado) | L79: =IFERROR(ROUND($L$71,IF($L$71=0,0,4-INT(LOG10(ABS($L$71))))),"") -> 0.017671
B80: Fórmula | C80: TDH = V ÷ Q | K80: [Ex 1.4] A (texto) | L80: =IF(ISNUMBER($L$79),FIXED($L$79,IF(ROUND($L$79,0)=$L$79,0,IF(ROUND($L$79,1)=$L$79,1,IF(ROUND($L$79,2)=$L$79,2,IF(ROUND($L$79,3)=$L$79,3,IF(ROUND($L$79,4)=$L$79,4,IF(ROUND($L$79,5)=$L$79,5,IF(ROUND($L$79,6)=$L$79,6,7)))))))),"?") -> 0,017671
B81: Substituição | C81: ="V = "&$L$137&" m³ e Q = "&$L$135&" m³/h."&CHAR(10)&"TDH = "&$L$137&" ÷ "&$L$135&" = "&$L$139&" h" -> V = 500 m³ e Q = 50 m³/h. TDH = 500 ÷ 50 = 10 h | K81: [Ex 1.4] Dm (arredondado) | L81: =IFERROR(ROUND($L$70,IF($L$70=0,0,4-INT(LOG10(ABS($L$70))))),"") -> 0.15
B82: Resolução | C82: ="1) Converter: V = "&$L$137&" m³ e Q = "&$L$135&" m³/h."&CHAR(10)&"2) TDH = V ÷ Q = "&$L$137&" ÷ "&$L$135&" = "&$L$139&" h."&CHAR(10)&"3) Em minutos: "&$L$139&" × 60 = "&$L$141&" min." -> 1) Converter: V = 500 m³ e Q = 50 m³/h. 2) TDH = V ÷ Q = 500 ÷ 50 = 10 h. 3) Em minutos: 10 × 60 = 600 min. | K82: [Ex 1.4] Dm (texto) | L82: =IF(ISNUMBER($L$81),FIXED($L$81,IF(ROUND($L$81,0)=$L$81,0,IF(ROUND($L$81,1)=$L$81,1,IF(ROUND($L$81,2)=$L$81,2,IF(ROUND($L$81,3)=$L$81,3,IF(ROUND($L$81,4)=$L$81,4,IF(ROUND($L$81,5)=$L$81,5,IF(ROUND($L$81,6)=$L$81,6,7)))))))),"?") -> 0,15
B83: Resultado | C83: ="TDH = "&$L$139&" h = "&$L$141&" min" -> TDH = 10 h = 600 min | K83: [Ex 1.4] Q (arredondado) | L83: =IFERROR(ROUND($L$72,IF($L$72=0,0,4-INT(LOG10(ABS($L$72))))),"") -> 0.014137
B84: Explicação simples | C84: ="Em média, cada porção de líquido fica "&$L$139&" horas ("&$L$141&" minutos) dentro da unidade antes de sair." -> Em média, cada porção de líquido fica 10 horas (600 minutos) dentro da unidade antes de sair. | K84: [Ex 1.4] Q (texto) | L84: =IF(ISNUMBER($L$83),FIXED($L$83,IF(ROUND($L$83,0)=$L$83,0,IF(ROUND($L$83,1)=$L$83,1,IF(ROUND($L$83,2)=$L$83,2,IF(ROUND($L$83,3)=$L$83,3,IF(ROUND($L$83,4)=$L$83,4,IF(ROUND($L$83,5)=$L$83,5,IF(ROUND($L$83,6)=$L$83,6,7)))))))),"?") -> 0,014137
B85: Teste na calculadora | C85: Na aba 02 — Vazão e Hidráulica, vá até a Ferramenta 4 e escolha Exemplo 01 na lista Cenário. Depois troque para Meu cálculo e teste outros valores. | K85: [Ex 1.4] Ql (arredondado) | L85: =IFERROR(ROUND($L$73,IF($L$73=0,0,4-INT(LOG10(ABS($L$73))))),"") -> 14.137
K86: [Ex 1.4] Ql (texto) | L86: =IF(ISNUMBER($L$85),FIXED($L$85,IF(ROUND($L$85,0)=$L$85,0,IF(ROUND($L$85,1)=$L$85,1,IF(ROUND($L$85,2)=$L$85,2,IF(ROUND($L$85,3)=$L$85,3,IF(ROUND($L$85,4)=$L$85,4,IF(ROUND($L$85,5)=$L$85,5,IF(ROUND($L$85,6)=$L$85,6,7)))))))),"?") -> 14,137
B87: EXEMPLO 1.8 · Lagoa de estabilização | G87: ▶ Abrir na calculadora | K87: [Ex 1.5] fQ | L87: =IFERROR(CHOOSE(MATCH('02 — Vazão e Hidráulica'!$C$102,{"m³/s","L/s","m³/h","m³/dia"},0),1,0.001,1/3600,1/86400),"") -> 1
B88: Situação prática | C88: Uma lagoa com 1.200 m³ de volume útil recebe 4.800 m³/dia. Qual é o tempo de detenção? | K88: [Ex 1.5] Qs | L88: =IFERROR('02 — Vazão e Hidráulica'!$C$101*$L$87,"") -> 0.05
B89: Dados utilizados | C89: ="V = "&$L$152&" "&'02 — Vazão e Hidráulica'!$D$138&" | "&"Q = "&$L$150&" "&'02 — Vazão e Hidráulica'!$D$140 -> V = 1.200 m³ | Q = 4.800 m³/dia | K89: [Ex 1.5] fD | L89: =IFERROR(CHOOSE(MATCH('02 — Vazão e Hidráulica'!$C$104,{"m","cm","mm","pol"},0),1,0.01,0.001,0.0254),"") -> 1
B90: Fórmula | C90: TDH = V ÷ Q | K90: [Ex 1.5] Dm | L90: =IFERROR('02 — Vazão e Hidráulica'!$C$103*$L$89,"") -> 0.2
B91: Substituição | C91: ="V = "&$L$156&" m³ e Q = "&$L$154&" m³/h."&CHAR(10)&"TDH = "&$L$156&" ÷ "&$L$154&" = "&$L$158&" h" -> V = 1.200 m³ e Q = 200 m³/h. TDH = 1.200 ÷ 200 = 6 h | K91: [Ex 1.5] A | L91: =IFERROR(PI()*$L$90^2/4,"") -> 0.031415927
B92: Resolução | C92: ="1) Converter: V = "&$L$156&" m³ e Q = "&$L$154&" m³/h."&CHAR(10)&"2) TDH = V ÷ Q = "&$L$156&" ÷ "&$L$154&" = "&$L$158&" h."&CHAR(10)&"3) Em minutos: "&$L$158&" × 60 = "&$L$160&" min." -> 1) Converter: V = 1.200 m³ e Q = 200 m³/h. 2) TDH = V ÷ Q = 1.200 ÷ 200 = 6 h. 3) Em minutos: 6 × 60 = 360 min. | K92: [Ex 1.5] vel | L92: =IFERROR($L$88/$L$91,"") -> 1.5915494
B93: Resultado | C93: ="TDH = "&$L$158&" h = "&$L$160&" min" -> TDH = 6 h = 360 min | K93: [Ex 1.5] D (arredondado) | L93: =IFERROR(ROUND('02 — Vazão e Hidráulica'!$C$103,IF('02 — Vazão e Hidráulica'!$C$103=0,0,4-INT(LOG10(ABS('02 — Vazão e Hidráulica'!$C$103))))),"") -> 0.2
B94: Explicação simples | C94: ="Em média, cada porção de líquido fica "&$L$158&" horas ("&$L$160&" minutos) dentro da unidade antes de sair." -> Em média, cada porção de líquido fica 6 horas (360 minutos) dentro da unidade antes de sair. | K94: [Ex 1.5] D (texto) | L94: =IF(ISNUMBER($L$93),FIXED($L$93,IF(ROUND($L$93,0)=$L$93,0,IF(ROUND($L$93,1)=$L$93,1,IF(ROUND($L$93,2)=$L$93,2,IF(ROUND($L$93,3)=$L$93,3,IF(ROUND($L$93,4)=$L$93,4,IF(ROUND($L$93,5)=$L$93,5,IF(ROUND($L$93,6)=$L$93,6,7)))))))),"?") -> 0,2
B95: Teste na calculadora | C95: Na aba 02 — Vazão e Hidráulica, vá até a Ferramenta 4 e escolha Exemplo 02 na lista Cenário. Depois troque para Meu cálculo e teste outros valores. | K95: [Ex 1.5] Q (arredondado) | L95: =IFERROR(ROUND('02 — Vazão e Hidráulica'!$C$101,IF('02 — Vazão e Hidráulica'!$C$101=0,0,4-INT(LOG10(ABS('02 — Vazão e Hidráulica'!$C$101))))),"") -> 0.05
K96: [Ex 1.5] Q (texto) | L96: =IF(ISNUMBER($L$95),FIXED($L$95,IF(ROUND($L$95,0)=$L$95,0,IF(ROUND($L$95,1)=$L$95,1,IF(ROUND($L$95,2)=$L$95,2,IF(ROUND($L$95,3)=$L$95,3,IF(ROUND($L$95,4)=$L$95,4,IF(ROUND($L$95,5)=$L$95,5,IF(ROUND($L$95,6)=$L$95,6,7)))))))),"?") -> 0,05
K97: [Ex 1.5] A (arredondado) | L97: =IFERROR(ROUND($L$91,IF($L$91=0,0,4-INT(LOG10(ABS($L$91))))),"") -> 0.031416
B98: 🏭 CALCULADORA 02 · CARGA POLUIDORA | H98: ▲ Voltar ao índice | K98: [Ex 1.5] A (texto) | L98: =IF(ISNUMBER($L$97),FIXED($L$97,IF(ROUND($L$97,0)=$L$97,0,IF(ROUND($L$97,1)=$L$97,1,IF(ROUND($L$97,2)=$L$97,2,IF(ROUND($L$97,3)=$L$97,3,IF(ROUND($L$97,4)=$L$97,4,IF(ROUND($L$97,5)=$L$97,5,IF(ROUND($L$97,6)=$L$97,6,7)))))))),"?") -> 0,031416
K99: [Ex 1.5] Dm (arredondado) | L99: =IFERROR(ROUND($L$90,IF($L$90=0,0,4-INT(LOG10(ABS($L$90))))),"") -> 0.2
B100: EXEMPLO 2.1 · Carga de DBO de uma indústria | G100: ▶ Abrir na calculadora | K100: [Ex 1.5] Dm (texto) | L100: =IF(ISNUMBER($L$99),FIXED($L$99,IF(ROUND($L$99,0)=$L$99,0,IF(ROUND($L$99,1)=$L$99,1,IF(ROUND($L$99,2)=$L$99,2,IF(ROUND($L$99,3)=$L$99,3,IF(ROUND($L$99,4)=$L$99,4,IF(ROUND($L$99,5)=$L$99,5,IF(ROUND($L$99,6)=$L$99,6,7)))))))),"?") -> 0,2
...
